Workbook

Sheet 4. DISPENSA E INEXIGIBILIDADE
B3: GESTÃO DE COMPRAS: DISPENSA E INEXIGIBILIDADE | K3: inserir controles de saldos ND | S3: Inserir link gerado no WordPress | AG3: PNCP | AJ3: ARQUIVOS DA LICITAÇÃO (LINKS WORD PRESS - SITE) | AP3: RENOMEAÇÃO AQUIVOS
B4: DATA RECEBIDO | C4: RESPONSÁVEL GCC | D4: STATUS | E4: ETAPA | F4: Nº PROCESSO SIGA | G4: DIRETORIA | H4: ÁREA REQUISITANTE | I4: TIPO DO OBJETO | J4: OBJETO | K4: MODALIDADE | L4: NATUREZA DO CONTRATO | M4: FORNECEDOR | N4: CNPJ/CPF | O4: TIPO DO CONTRATO | P4: NOTA DE EMPENHO | Q4: Nº CONTRATO | R4: Nº CTR assinado | S4: DATA ASSINATURA | T4: INÍCIO VIGÊNCIA | U4: FINAL VIGÊNCIA | V4: VALOR CONTRATO | W4: Nº DEG | X4: FISCAL DO CONTRATO | Y4: SIGILO | Z4: Nº RC SAP | AA4: Nº Fornecedor SAP | AB4: Nº CTR SAP | AC4: DATA FINALIZADO | AD4: DIAS ÚTEIS | AE4: RESPONSÁVEL GESTÃO | AF4: OBSERVAÇÃO | AG4: Nº DA LICITAÇÃO | AH4: Compra divulgada no PNCP | AI4: Publicação do Contrato PNCP | AJ4: Arquivo do contrato | AK4: TR | AL4: JUST. ESCOLHA FORNECEDOR | AM4: ATO RATIFICAÇÃO (Autor. Sup) | AP4: SEQ | AQ4: TR | AR4: JUST. ESCOLHA FORNECEDOR | AS4: ATO RATIFICAÇÃO (Autor. Sup)
B5: 45600 | C5: FRANCIELE | D5: FINALIZADO | E5: FINALIZADO | F5: TLB-PRO-2024/05723 | G5: 2000-DAFRI | H5: GLOG | I5: Serviços | J5: Contratação de empresa especializada em assessoria esportiva, organização, apoio técnico, logístico e estrutural para participação da equipe de colaboradores da Telebras, em caminhada (3km) e corrida (5km e 10km) no evento MARATONA MONUMENTAL DE BRASÍLIA em comemoração ao aniversário de 52 anos da empresa e a Semana Interna de Prevenção de Acidentes do Trabalho (SIPAT. | K5: Dispensa | L5: ADMINISTRATIVO | M5: MARCIA GONCALVES FARIA ROSA | N5: 16.454.959/0001-37 | O5: Nota de Empenho | P5: 2024NE001059 | Q5: 2024NE001059 | R5: 2024NE001059 | S5: 45604 | T5: 45604 | U5: 45657 | V5: 29500 | W5: TLB-DEG-2024/00126 | X5: Rosilda Ferreira da Cunha | Y5: PÚBLICO | Z5: 10015000 | AA5: 10003761 | AB5: 2024NE001059 | AC5: 45600 | AD5: =NETWORKDAYS.INTL(Tab_4.DISP_INEX[[#This Row],[DATA RECEBIDO]],Tab_4.DISP_INEX[[#This Row],[DATA FINALIZADO]],1,Lista!$U$3:$U$15) -> 1 | AJ5: https://www.telebras.com.br/wp-content/uploads/2025/02/69.2024NE001059-MARCIA-GONCALVES-FARIA-ROSA.pdf | AK5: https://www.telebras.com.br/wp-content/uploads/2026/06/1_TR_MARCIA-GONCALVES-FARIA-ROSA.pdf | AL5: https://www.telebras.com.br/wp-content/uploads/2026/06/1_JUST_MARCIA-GONCALVES-FARIA-ROSA.pdf | AM5: - | AP5: 1 | AQ5: =_xlfn.CONCAT(AP5,"_","TR","_",Tab_4.DISP_INEX[[#This Row],[FORNECEDOR]]) -> 1_TR_MARCIA GONCALVES FARIA ROSA | AR5: =_xlfn.CONCAT(AP5,"_","JUST","_",Tab_4.DISP_INEX[[#This Row],[FORNECEDOR]]) -> 1_JUST_MARCIA GONCALVES FARIA ROSA | AS5: =_xlfn.CONCAT(AP5,"_","RAT","_",Tab_4.DISP_INEX[[#This Row],[FORNECEDOR]]) -> 1_RAT_MARCIA GONCALVES FARIA ROSA
B6: 45628 | C6: LUCIANA | D6: FINALIZADO | E6: FINALIZADO | F6: TLB-PRO-2024/04811 | G6: 2000-DAFRI | H6: GPR -ASCOM | I6: Compras | J6: Aquisição de drone | K6: Dispensa | L6: ADMINISTRATIVO | M6: NW SHOP COMÉRCIO LTDA | N6: 30.282.962/0001-41 | O6: Nota de Empenho | P6: 2024NE001121 | Q6: 2024NE001121 | R6: TLB-ASS-2024/17078 | S6: 45632 | T6: 45632 | U6: 45657 | V6: 9495 | W6: TLB-DEG-2024/00137 | X6: Érico Luís Cortes Cazarré | Y6: PÚBLICO | Z6: 10014689 | AB6: 2024NE001121 | AC6: 45646 | AD6: =NETWORKDAYS.INTL(Tab_4.DISP_INEX[[#This Row],[DATA RECEBIDO]],Tab_4.DISP_INEX[[#This Row],[DATA FINALIZADO]],1,Lista!$U$3:$U$15) -> 15 | AJ6: https://www.telebras.com.br/wp-content/uploads/2026/04/1.-2024NE001121-NW-SHOP-COMERCIO-LTDA-1.pdf | AK6: https://www.telebras.com.br/wp-content/uploads/2026/06/2_TR_NW-SHOP-COMERCIO-LTDA.pdf | AL6: https://www.telebras.com.br/wp-content/uploads/2026/06/2_JUST_NW-SHOP-COMERCIO-LTDA.pdf | AM6: - | AP6: 2 | AQ6: =_xlfn.CONCAT(AP6,"_","TR","_",Tab_4.DISP_INEX[[#This Row],[FORNECEDOR]]) -> 2_TR_NW SHOP COMÉRCIO LTDA | AR6: =_xlfn.CONCAT(AP6,"_","JUST","_",Tab_4.DISP_INEX[[#This Row],[FORNECEDOR]]) -> 2_JUST_NW SHOP COMÉRCIO LTDA | AS6: =_xlfn.CONCAT(AP6,"_","RAT","_",Tab_4.DISP_INEX[[#This Row],[FORNECEDOR]]) -> 2_RAT_NW SHOP COMÉRCIO LTDA
B7: 45618 | C7: LUCIANA | D7: FINALIZADO | E7: FINALIZADO | F7: TLB-PRO-2024/03879 | G7: 3000-DTO | H7: GORS | I7: Serviços | J7: Contratação de serviços de reparo e higienização das cadeiras de escritório do CIGR | K7: Dispensa | L7: ADMINISTRATIVO | M7: GS SERVICOS LTDA | N7: 34.292.339/0001-20 | O7: Nota de Empenho | P7: 2024NE001102 | Q7: 2024NE001102 | R7: TLB-ASS-2024/17013 | S7: 45632 | T7: 45632 | U7: 45657 | V7: 4909.98 | W7: TLB-DEG-2024/00148 | X7: Eder Viana Silva | Y7: PÚBLICO | Z7: 10014940 | AB7: - | AD7: =NETWORKDAYS.INTL(Tab_4.DISP_INEX[[#This Row],[DATA RECEBIDO]],Tab_4.DISP_INEX[[#This Row],[DATA FINALIZADO]],1,Lista!$U$3:$U$15) -> -32577 | AJ7: https://www.telebras.com.br/wp-content/uploads/2026/04/2.-2024NE001102-GS-SERVICOS-LTDA-1.pdf | AK7: https://www.telebras.com.br/wp-content/uploads/2026/06/3_TR_GS-SERVICOS-LTDA.pdf | AL7: https://www.telebras.com.br/wp-content/uploads/2026/06/3_JUST_GS-SERVICOS-LTDA.pdf | AM7: - | AP7: 3 | AQ7: =_xlfn.CONCAT(AP7,"_","TR","_",Tab_4.DISP_INEX[[#This Row],[FORNECEDOR]]) -> 3_TR_GS SERVICOS LTDA | AR7: =_xlfn.CONCAT(AP7,"_","JUST","_",Tab_4.DISP_INEX[[#This Row],[FORNECEDOR]]) -> 3_JUST_GS SERVICOS LTDA | AS7: =_xlfn.CONCAT(AP7,"_","RAT","_",Tab_4.DISP_INEX[[#This Row],[FORNECEDOR]]) -> 3_RAT_GS SERVICOS LTDA
B8: 45632 | C8: LUCIANA | D8: FINALIZADO | E8: FINALIZADO | F8: TLB-PRO-2024/06305 | G8: 3000-DTO | H8: GERP | I8: Informática (TIC) | J8: Compra de placas, transceivers e cabos compatíveis com os equipamentos DATACOM para a realização de upgrade do Switch DATACOM 4004 instalado na localidade de Presidente Dutra/MA para atendimento da demanda da Infovia do Maranhão. | K8: Inexigibilidade | L8: ADMINISTRATIVO | M8: Teracom Telemática S.A | N8: 02.820.966/0001-09 | O8: Nota de Empenho | P8: 2024NE001125 | Q8: 2024NE001125 | R8: TLB-ASS-2024/17112 | S8: 45632 | T8: 45632 | U8: 45657 | V8: 56350.5 | W8: TLB-DEG-2024/00149 | X8: MIRELE DE ALMEIDA MENCARI | Y8: PÚBLICO | AB8: - | AC8: =TODAY() -> 46190 | AD8: =NETWORKDAYS.INTL(Tab_4.DISP_INEX[[#This Row],[DATA RECEBIDO]],Tab_4.DISP_INEX[[#This Row],[DATA FINALIZADO]],1,Lista!$U$3:$U$15) -> 398 | AJ8: https://www.telebras.com.br/wp-content/uploads/2026/04/3.-2024NE001125-TERACOM-TELEMATICA-SA-1.pdf | AK8: https://www.telebras.com.br/wp-content/uploads/2026/06/4_TR_Teracom-Telematica-S.A.pdf | AL8: - | AM8: https://www.telebras.com.br/wp-content/uploads/2026/06/4_RAT_Teracom-Telematica-S.A.pdf | AP8: 4 | AQ8: =_xlfn.CONCAT(AP8,"_","TR","_",Tab_4.DISP_INEX[[#This Row],[FORNECEDOR]]) -> 4_TR_Teracom Telemática S.A | AR8: =_xlfn.CONCAT(AP8,"_","JUST","_",Tab_4.DISP_INEX[[#This Row],[FORNECEDOR]]) -> 4_JUST_Teracom Telemática S.A | AS8: =_xlfn.CONCAT(AP8,"_","RAT","_",Tab_4.DISP_INEX[[#This Row],[FORNECEDOR]]) -> 4_RAT_Teracom Telemática S.A
B9: 45342 | C9: FRANCIELE | D9: FINALIZADO | E9: FINALIZADO | F9: TLB-PRO-2024/00927 | G9: 2000-DAFRI | H9: GGP | I9: Serviços | J9: Palestrante moderador para o Evento "Telebras Day" | K9: Inexigibilidade | L9: ADMINISTRATIVO | M9: Inlabs Capacitação Profissional Ltda | N9: 16.700.677/0001-72 | O9: Nota de Empenho | P9: 2024NE000601 | Q9: 2024NE000601 | R9: 2024NE000601 | S9: 45350 | T9: 45350 | U9: 45350 | V9: 32500 | W9: TLB-DEG-2024/00016 | X9: ADRYANA RAMOS DE OLIVEIRA | Y9: PÚBLICO | Z9: 10014463 | AA9: 10004001 | AB9: 2024NE000601 | AC9: 45342 | AD9: =NETWORKDAYS.INTL(Tab_4.DISP_INEX[[#This Row],[DATA RECEBIDO]],Tab_4.DISP_INEX[[#This Row],[DATA FINALIZADO]],1,Lista!$U$3:$U$15) -> 1 | AE9: FRANCIELE | AF9: CAPACITAÇÃO | AJ9: https://www.telebras.com.br/wp-content/uploads/2024/12/14.2024NE000601-INLABS-CAPACITACAO-PROFISSIONAL-LTDA.pdf | AK9: https://www.telebras.com.br/wp-content/uploads/2026/06/5_TR_Inlabs-Capacitacao-Profissional-Ltda.pdf | AL9: https://www.telebras.com.br/wp-content/uploads/2026/06/5_JUST_Inlabs-Capacitacao-Profissional-Ltda.pdf | AM9: https://www.telebras.com.br/wp-content/uploads/2026/06/5_RAT_Inlabs-Capacitacao-Profissional-Ltda.pdf | AP9: 5 | AQ9: =_xlfn.CONCAT(AP9,"_","TR","_",Tab_4.DISP_INEX[[#This Row],[FORNECEDOR]]) -> 5_TR_Inlabs Capacitação Profissional Ltda | AR9: =_xlfn.CONCAT(AP9,"_","JUST","_",Tab_4.DISP_INEX[[#This Row],[FORNECEDOR]]) -> 5_JUST_Inlabs Capacitação Profissional Ltda | AS9: =_xlfn.CONCAT(AP9,"_","RAT","_",Tab_4.DISP_INEX[[#This Row],[FORNECEDOR]]) -> 5_RAT_Inlabs Capacitação Profissional Ltda
B10: 45342 | C10: FRANCIELE | D10: FINALIZADO | E10: FINALIZADO | F10: TLB-PRO-2024/00201 | G10: 2000-DAFRI | H10: GGP | I10: Serviços | J10: Conferência Satellite 2024 | K10: Inexigibilidade | L10: ADMINISTRATIVO | M10: ACCESS INTELLIGENCE, LLC | N10: EX242162 | O10: Nota de Empenho | P10: 2024NE000566 | Q10: 2024NE000566 | R10: 2024NE000566 | S10: 45345 | T10: 45345 | U10: 45345 | V10: 22586.6 | W10: TLB-DEG-2024/00013 | X10: ADRYANA RAMOS DE OLIVEIRA | Y10: PÚBLICO | Z10: 10014468 | AB10: 2024NE000566 | AC10: 45343 | AD10: =NETWORKDAYS.INTL(Tab_4.DISP_INEX[[#This Row],[DATA RECEBIDO]],Tab_4.DISP_INEX[[#This Row],[DATA FINALIZADO]],1,Lista!$U$3:$U$15) -> 2 | AE10: FRANCIELE | AF10: EVENTO | AJ10: https://www.telebras.com.br/wp-content/uploads/2024/12/12.2024NE000566-ACCESS-INTELLIGENCE-LLC.pdf | AK10: https://www.telebras.com.br/wp-content/uploads/2026/06/6_TR_ACCESS-INTELLIGENCE-LLC.pdf | AL10: https://www.telebras.com.br/wp-content/uploads/2026/06/6_JUST_ACCESS-INTELLIGENCE-LLC.pdf | AM10: https://www.telebras.com.br/wp-content/uploads/2026/06/6_RAT_ACCESS-INTELLIGENCE-LLC.pdf | AP10: 6 | AQ10: =_xlfn.CONCAT(AP10,"_","TR","_",Tab_4.DISP_INEX[[#This Row],[FORNECEDOR]]) -> 6_TR_ACCESS INTELLIGENCE, LLC | AR10: =_xlfn.CONCAT(AP10,"_","JUST","_",Tab_4.DISP_INEX[[#This Row],[FORNECEDOR]]) -> 6_JUST_ACCESS INTELLIGENCE, LLC | AS10: =_xlfn.CONCAT(AP10,"_","RAT","_",Tab_4.DISP_INEX[[#This Row],[FORNECEDOR]]) -> 6_RAT_ACCESS INTELLIGENCE, LLC
B11: 45351 | C11: FRANCIELE | D11: FINALIZADO | E11: FINALIZADO | F11: TLB-PRO-2024/00613 | G11: 2000-DAFRI | H11: GIRC | I11: Serviços | J11: Filiação da Telebras à Fundação Nacional da Qualidade – FNQ | K11: Inexigibilidade | L11: ADMINISTRATIVO | M11: Fundação Nacional de Qualidade - FNQ | N11: 67.145.383/0001-67 | O11: Nota de Empenho | P11: 2024NE000891 | Q11: 2024NE000891 | R11: TLB-ASS-2024/10894 | S11: 45488 | T11: 45524 | U11: 45889 | V11: 6615 | W11: TLB-DEG-2024/00098 | X11: JANINE OLIVEIRA | Y11: PÚBLICO | Z11: 10014428 | AA11: 10003997 | AB11: 2024NE000891 | AC11: 45357 | AD11: =NETWORKDAYS.INTL(Tab_4.DISP_INEX[[#This Row],[DATA RECEBIDO]],Tab_4.DISP_INEX[[#This Row],[DATA FINALIZADO]],1,Lista!$U$3:$U$15) -> 5 | AE11: FRANCIELE | AF11: FILIAÇÃO | AJ11: https://www.telebras.com.br/wp-content/uploads/2026/04/12.-2024NE000891-FUNDACAO-NACIONAL-DE-QUALIDADE-FNQ-1.pdf | AK11: https://www.telebras.com.br/wp-content/uploads/2026/06/7_TR_Fundacao-Nacional-de-Qualidade-FNQ.pdf | AL11: https://www.telebras.com.br/wp-content/uploads/2026/06/7_JUST_Fundacao-Nacional-de-Qualidade-FNQ.pdf | AM11: https://www.telebras.com.br/wp-content/uploads/2026/06/7_RAT_Fundacao-Nacional-de-Qualidade-FNQ.pdf | AP11: 7 | AQ11: =_xlfn.CONCAT(AP11,"_","TR","_",Tab_4.DISP_INEX[[#This Row],[FORNECEDOR]]) -> 7_TR_Fundação Nacional de Qualidade - FNQ | AR11: =_xlfn.CONCAT(AP11,"_","JUST","_",Tab_4.DISP_INEX[[#This Row],[FORNECEDOR]]) -> 7_JUST_Fundação Nacional de Qualidade - FNQ | AS11: =_xlfn.CONCAT(AP11,"_","RAT","_",Tab_4.DISP_INEX[[#This Row],[FORNECEDOR]]) -> 7_RAT_Fundação Nacional de Qualidade - FNQ
B12: 45364 | C12: ROSILDA | D12: FINALIZADO | E12: FINALIZADO | F12: TLB-PRO-2024/01201 | G12: 2000-DAFRI | H12: GCC | I12: Serviços | J12: Zênite Fácil - Estatais - Assinatura anual | K12: Inexigibilidade | L12: ADMINISTRATIVO | M12: Zênite Informação e Consultoria S/A | N12: 86.781.069/0001-15 | O12: Nota de Empenho | P12: 2024NE000632 | Q12: 2024NE000632 | R12: TLB-ASS-2024/04794 | S12: 45373 | T12: 45373 | U12: 45738 | V12: 11670 | W12: TLB-DEG-2024/00027 | X12: GENARA LOPES BÜHLER | Y12: PÚBLICO | Z12: 10014530 | AB12: 2024NE000632 | AC12: 45365 | AD12: =NETWORKDAYS.INTL(Tab_4.DISP_INEX[[#This Row],[DATA RECEBIDO]],Tab_4.DISP_INEX[[#This Row],[DATA FINALIZADO]],1,Lista!$U$3:$U$15) -> 2 | AJ12: https://www.telebras.com.br/wp-content/uploads/2024/12/16.2024NE000632-ZENITE-INFORMACAO-E-CONSULTORIA-SA.pdf | AK12: https://www.telebras.com.br/wp-content/uploads/2026/06/8_TR_Zenite-Informacao-e-Consultoria-SA.pdf | AL12: https://www.telebras.com.br/wp-content/uploads/2026/06/8_JUST_Zenite-Informacao-e-Consultoria-SA.pdf | AM12: https://www.telebras.com.br/wp-content/uploads/2026/06/8_RAT_Zenite-Informacao-e-Consultoria-SA.pdf | AP12: 8 | AQ12: =_xlfn.CONCAT(AP12,"_","TR","_",Tab_4.DISP_INEX[[#This Row],[FORNECEDOR]]) -> 8_TR_Zênite Informação e Consultoria S/A | AR12: =_xlfn.CONCAT(AP12,"_","JUST","_",Tab_4.DISP_INEX[[#This Row],[FORNECEDOR]]) -> 8_JUST_Zênite Informação e Consultoria S/A | AS12: =_xlfn.CONCAT(AP12,"_","RAT","_",Tab_4.DISP_INEX[[#This Row],[FORNECEDOR]]) -> 8_RAT_Zênite Informação e Consultoria S/A
B13: 45370 | C13: FRANCIELE | D13: FINALIZADO | E13: FINALIZADO | F13: TLB-PRO-2024/00922 | G13: 2000-DAFRI | H13: GEOS | I13: Serviços | J13: Participação da Telebras no Simpósio Internacional Especializado em Dinâmica de Vôo Espacial - International Symposium on Space Flight Dynamics (ISSFD). | K13: Inexigibilidade | L13: ADMINISTRATIVO | M13: ATP Specials BV | O13: Nota de Empenho | P13: 2024NE000628 | Q13: 2024NE000628 | R13: 2024NE000628 | S13: 45373 | T13: 45373 | U13: 45373 | V13: 6927.9 | W13: TLB-DEG-2024/00025 | X13: MÁRCIA MANUELA MEDRADO NUNES | Y13: PÚBLICO | Z13: 10014538 | AB13: 2024NE000628 | AC13: 45370 | AD13: =NETWORKDAYS.INTL(Tab_4.DISP_INEX[[#This Row],[DATA RECEBIDO]],Tab_4.DISP_INEX[[#This Row],[DATA FINALIZADO]],1,Lista!$U$3:$U$15) -> 1 | AE13: FRANCIELE | AF13: EVENTO | AJ13: https://www.telebras.com.br/wp-content/uploads/2024/12/13.2024NE000628-ATP-SPECIALS-BV.pdf | AK13: https://www.telebras.com.br/wp-content/uploads/2026/06/9_TR_ATP-Specials-BV.pdf | AL13: https://www.telebras.com.br/wp-content/uploads/2026/06/9_JUST_ATP-Specials-BV.pdf | AM13: https://www.telebras.com.br/wp-content/uploads/2026/06/9_RAT_ATP-Specials-BV.pdf | AP13: 9 | AQ13: =_xlfn.CONCAT(AP13,"_","TR","_",Tab_4.DISP_INEX[[#This Row],[FORNECEDOR]]) -> 9_TR_ATP Specials BV | AR13: =_xlfn.CONCAT(AP13,"_","JUST","_",Tab_4.DISP_INEX[[#This Row],[FORNECEDOR]]) -> 9_JUST_ATP Specials BV | AS13: =_xlfn.CONCAT(AP13,"_","RAT","_",Tab_4.DISP_INEX[[#This Row],[FORNECEDOR]]) -> 9_RAT_ATP Specials BV
B14: 45372 | C14: FRANCIELE | D14: FINALIZADO | E14: FINALIZADO | F14: TLB-PRO-2024/01130 | G14: 2000-DAFRI | H14: GIRC | I14: Serviços | J14: Associação da Telebras ao Instituto Brasileiro de Governança Corporativa - IBGC | K14: Inexigibilidade | L14: ADMINISTRATIVO | M14: Instituto Brasileiro de Governança Corporativa - IBGC | N14: 01.082.331/0001-80 | O14: Contrato | P14: 2024NE000837 | Q14: TLB-CTR-2024/00045 | R14: TLB-AUT-2024/10835 | S14: 45463 | T14: 45463 | U14: 45657 | V14: 17289 | W14: TLB-DEG-2024/00070 | X14: ANTÔNIO CELSON DE JESUS NERIS | Y14: PÚBLICO | Z14: 10014520 | AA14: 10003951 | AB14: TLB-CTR-2024/00045 | AC14: 45373 | AD14: =NETWORKDAYS.INTL(Tab_4.DISP_INEX[[#This Row],[DATA RECEBIDO]],Tab_4.DISP_INEX[[#This Row],[DATA FINALIZADO]],1,Lista!$U$3:$U$15) -> 2 | AE14: FRANCIELE | AF14: ASSOCIAÇÃO | AJ14: https://www.telebras.com.br/wp-content/uploads/2024/12/29.-TLB-CTR-2024-00045-INSTITUTO-BRASILEIRO-DE-GOVERNANCA-CORPORATIVA-IBGC.pdf | AK14: https://www.telebras.com.br/wp-content/uploads/2026/06/10_TR_-Instituto-Brasileiro-de-Governanca-Corporativa-IBGC.pdf | AL14: https://www.telebras.com.br/wp-content/uploads/2026/06/10_JUST_-Instituto-Brasileiro-de-Governanca-Corporativa-IBGC.pdf | AM14: https://www.telebras.com.br/wp-content/uploads/2026/06/10_RAT_-Instituto-Brasileiro-de-Governanca-Corporativa-IBGC.pdf | AP14: 10 | AQ14: =_xlfn.CONCAT(AP14,"_","TR","_",Tab_4.DISP_INEX[[#This Row],[FORNECEDOR]]) -> 10_TR_ Instituto Brasileiro de Governança Corporativa - IBGC | AR14: =_xlfn.CONCAT(AP14,"_","JUST","_",Tab_4.DISP_INEX[[#This Row],[FORNECEDOR]]) -> 10_JUST_ Instituto Brasileiro de Governança Corporativa - IBGC | AS14: =_xlfn.CONCAT(AP14,"_","RAT","_",Tab_4.DISP_INEX[[#This Row],[FORNECEDOR]]) -> 10_RAT_ Instituto Brasileiro de Governança Corporativa - IBGC
B15: 45372 | C15: ROSILDA | D15: FINALIZADO | E15: FINALIZADO | F15: TLB-PRO-2024/00728 | G15: 2000-DAFRI | H15: GD | I15: Serviços | J15: Consultoria para Evolução da Gestão do Conhecimento | K15: Inexigibilidade | L15: ADMINISTRATIVO | M15: IMPAKT CONSULTORIA S/S LIMITADA | N15: 08.170.564/0001-84 | O15: Nota de Empenho | P15: 2024NE000824 | Q15: 2024NE000824 | R15: TLB-ASS-2024/16668 | S15: 45628 | T15: 45628 | U15: 45811 | V15: 262200 | Y15: PÚBLICO | Z15: 10014500 | AB15: 2024NE000824 | AC15: 45385 | AD15: =NETWORKDAYS.INTL(Tab_4.DISP_INEX[[#This Row],[DATA RECEBIDO]],Tab_4.DISP_INEX[[#This Row],[DATA FINALIZADO]],1,Lista!$U$3:$U$15) -> 9 | AJ15: https://www.telebras.com.br/wp-content/uploads/2026/04/4.-2024NE000824-IMPAKT-CONSULTORIA-1.pdf | AK15: https://www.telebras.com.br/wp-content/uploads/2026/06/11_TR_IMPAKT-CONSULTORIA-SS-LIMITADA.pdf | AL15: https://www.telebras.com.br/wp-content/uploads/2026/06/11_JUST_IMPAKT-CONSULTORIA-SS-LIMITADA.pdf | AM15: https://www.telebras.com.br/wp-content/uploads/2026/06/11_RAT_IMPAKT-CONSULTORIA-SS-LIMITADA.pdf | AP15: 11 | AQ15: =_xlfn.CONCAT(AP15,"_","TR","_",Tab_4.DISP_INEX[[#This Row],[FORNECEDOR]]) -> 11_TR_IMPAKT CONSULTORIA S/S LIMITADA | AR15: =_xlfn.CONCAT(AP15,"_","JUST","_",Tab_4.DISP_INEX[[#This Row],[FORNECEDOR]]) -> 11_JUST_IMPAKT CONSULTORIA S/S LIMITADA | AS15: =_xlfn.CONCAT(AP15,"_","RAT","_",Tab_4.DISP_INEX[[#This Row],[FORNECEDOR]]) -> 11_RAT_IMPAKT CONSULTORIA S/S LIMITADA
B16: 45394 | C16: ROSILDA | D16: FINALIZADO | E16: FINALIZADO | F16: TLB-PRO-2024/01473 | G16: 2000-DAFRI | H16: GCONT | I16: Serviços | J16: Curso de ICMS - Teoria e Prática | K16: Inexigibilidade | L16: ADMINISTRATIVO | M16: IBET Instituto Brasileiro de Estudos Tributários | N16: 63.104.475/0001-48 | O16: Nota de Empenho | P16: 2024NE000684 | Q16: 2024NE000684 | R16: TLB-ASS-2024/06584 | S16: 45407 | T16: 45414 | U16: 45414 | V16: 10500 | W16: TLB-DEG-2024/00044 | X16: ADRYANA RAMOS DE OLIVEIRA | Y16: PÚBLICO | Z16: 10014610 | AB16: 2024NE000684 | AC16: 45415 | AD16: =NETWORKDAYS.INTL(Tab_4.DISP_INEX[[#This Row],[DATA RECEBIDO]],Tab_4.DISP_INEX[[#This Row],[DATA FINALIZADO]],1,Lista!$U$3:$U$15) -> 15 | AF16: CAPACITAÇÃO | AJ16: https://www.telebras.com.br/wp-content/uploads/2024/12/34.2024NE000684-IBET-INSTITUTO-BRASILEIRO-DE-ESTUDOS-TRIBUTARIOS.pdf | AK16: https://www.telebras.com.br/wp-content/uploads/2026/06/12_TR_IBET-Instituto-Brasileiro-de-Estudos-Tributarios.pdf | AL16: https://www.telebras.com.br/wp-content/uploads/2026/06/12_JUST_IBET-Instituto-Brasileiro-de-Estudos-Tributarios.pdf | AM16: https://www.telebras.com.br/wp-content/uploads/2026/06/12_RAT_IBET-Instituto-Brasileiro-de-Estudos-Tributarios.pdf | AP16: 12 | AQ16: =_xlfn.CONCAT(AP16,"_","TR","_",Tab_4.DISP_INEX[[#This Row],[FORNECEDOR]]) -> 12_TR_IBET Instituto Brasileiro de Estudos Tributários | AR16: =_xlfn.CONCAT(AP16,"_","JUST","_",Tab_4.DISP_INEX[[#This Row],[FORNECEDOR]]) -> 12_JUST_IBET Instituto Brasileiro de Estudos Tributários | AS16: =_xlfn.CONCAT(AP16,"_","RAT","_",Tab_4.DISP_INEX[[#This Row],[FORNECEDOR]]) -> 12_RAT_IBET Instituto Brasileiro de Estudos Tributários
B17: 45384 | C17: FRANCIELE | D17: FINALIZADO | E17: FINALIZADO | F17: TLB-PRO-2024/01475 | G17: 2000-DAFRI | H17: GCONT | I17: Serviços | J17: Contratação da capacitação "Formação em PIS e Cofins" | K17: Inexigibilidade | L17: ADMINISTRATIVO | M17: Cenofisco Centro de Capacitação Profissional Ltda | N17: 07.799.454/0001-13 | O17: Nota de Empenho | P17: 2024NE000653 | Q17: 2024NE000653 | R17: 2024NE000653 | S17: 45390 | T17: 45390 | U17: 45390 | V17: 1744 | W17: TLB-DEG-2024/00031 | X17: GLAHICON ROGERIO GREGORIO | Y17: PÚBLICO | Z17: 10014577 | AA17: 10003625 | AB17: 2024NE000653 | AC17: 45385 | AD17: =NETWORKDAYS.INTL(Tab_4.DISP_INEX[[#This Row],[DATA RECEBIDO]],Tab_4.DISP_INEX[[#This Row],[DATA FINALIZADO]],1,Lista!$U$3:$U$15) -> 2 | AE17: ROSILDA | AF17: CAPACITAÇÃO | AJ17: https://www.telebras.com.br/wp-content/uploads/2024/12/17.2024NE000653-CENOFISCO-CENTRO-DE-CAPACITACAO-PROFISSIONAL-LTDA.pdf | AK17: https://www.telebras.com.br/wp-content/uploads/2026/06/13_TR_Cenofisco-Centro-de-Capacitacao-Profissional-Ltda.pdf | AL17: https://www.telebras.com.br/wp-content/uploads/2026/06/13_JUST_Cenofisco-Centro-de-Capacitacao-Profissional-Ltda.pdf | AM17: https://www.telebras.com.br/wp-content/uploads/2026/06/13_RAT_Cenofisco-Centro-de-Capacitacao-Profissional-Ltda.pdf | AP17: 13 | AQ17: =_xlfn.CONCAT(AP17,"_","TR","_",Tab_4.DISP_INEX[[#This Row],[FORNECEDOR]]) -> 13_TR_Cenofisco Centro de Capacitação Profissional Ltda | AR17: =_xlfn.CONCAT(AP17,"_","JUST","_",Tab_4.DISP_INEX[[#This Row],[FORNECEDOR]]) -> 13_JUST_Cenofisco Centro de Capacitação Profissional Ltda | AS17: =_xlfn.CONCAT(AP17,"_","RAT","_",Tab_4.DISP_INEX[[#This Row],[FORNECEDOR]]) -> 13_RAT_Cenofisco Centro de Capacitação Profissional Ltda
B18: 45405 | C18: ROSILDA | D18: FINALIZADO | E18: FINALIZADO | F18: TLB-PRO-2024/01308 | G18: 2000-DAFRI | H18: GIRC | I18: Serviços | J18: Participação no 11º Congresso Internacional de Compliance | K18: Inexigibilidade | L18: ADMINISTRATIVO | M18: LEC Educação e Pesquisa Ltda | N18: 16.457.791/0001-13 | O18: Nota de Empenho | P18: 2024NE000693 | Q18: 2024NE000693 | R18: TLB-ASS-2024/06684 | S18: 45408 | T18: 45414 | U18: 45414 | V18: 18900 | W18: TLB-DEG-2024/00046 | X18: ÉRIKA NEVES OLIVEIRA | Y18: PÚBLICO | Z18: 10014578 | AB18: 2024NE000693 | AC18: 45414 | AD18: =NETWORKDAYS.INTL(Tab_4.DISP_INEX[[#This Row],[DATA RECEBIDO]],Tab_4.DISP_INEX[[#This Row],[DATA FINALIZADO]],1,Lista!$U$3:$U$15) -> 7 | AF18: CAPACITAÇÃO | AJ18: https://www.telebras.com.br/wp-content/uploads/2026/04/5.-2024NE000693-LEC-EDUC-E-PESQUISA-LTDA-1.pdf | AK18: https://www.telebras.com.br/wp-content/uploads/2026/06/14_TR_LEC-Educacao-e-Pesquisa-Ltda.pdf | AL18: https://www.telebras.com.br/wp-content/uploads/2026/06/14_JUST_LEC-Educacao-e-Pesquisa-Ltda.pdf | AM18: https://www.telebras.com.br/wp-content/uploads/2026/06/14_RAT_LEC-Educacao-e-Pesquisa-Ltda.pdf | AP18: 14 | AQ18: =_xlfn.CONCAT(AP18,"_","TR","_",Tab_4.DISP_INEX[[#This Row],[FORNECEDOR]]) -> 14_TR_LEC Educação e Pesquisa Ltda | AR18: =_xlfn.CONCAT(AP18,"_","JUST","_",Tab_4.DISP_INEX[[#This Row],[FORNECEDOR]]) -> 14_JUST_LEC Educação e Pesquisa Ltda | AS18: =_xlfn.CONCAT(AP18,"_","RAT","_",Tab_4.DISP_INEX[[#This Row],[FORNECEDOR]]) -> 14_RAT_LEC Educação e Pesquisa Ltda
B19: 45406 | C19: FRANCIELE | D19: FINALIZADO | E19: FINALIZADO | F19: TLB-PRO-2024/02102 | G19: 3000-DTO | H19: GPM | I19: Serviços | J19: Incluir a Telebras como associada da ABRINT - Associação Brasileira de Provedores de Internet sob o título de parceira- fornecedora. | K19: Inexigibilidade | L19: ADMINISTRATIVO | M19: Associação Brasileira de Provedores de Internet - ABRINT | N19: 11.369.542/0001-52 | O19: Nota de Empenho | P19: 2024NE000820 | Q19: 2024NE000820 | R19: TLB-ASS-2024/08452 | S19: 45439 | T19: 45449 | U19: 45808 | V19: 3600 | W19: TLB-DEG-2024/00059 | X19: MARIANA RODRIGUES BOAVISTA LEITE | Y19: PÚBLICO | Z19: 10014600 | AA19: 10001209 | AB19: 2024NE000820 | AC19: 45414 | AD19: =NETWORKDAYS.INTL(Tab_4.DISP_INEX[[#This Row],[DATA RECEBIDO]],Tab_4.DISP_INEX[[#This Row],[DATA FINALIZADO]],1,Lista!$U$3:$U$15) -> 6 | AJ19: https://www.telebras.com.br/wp-content/uploads/2026/04/6.-2024NE000820-ASSOC-BRAS-PROVEDORES-DE-INTERNET-ABRINT-1.pdf | AK19: - | AL19: - | AM19: - | AP19: 15 | AQ19: =_xlfn.CONCAT(AP19,"_","TR","_",Tab_4.DISP_INEX[[#This Row],[FORNECEDOR]]) -> 15_TR_Associação Brasileira de Provedores de Internet - ABRINT | AR19: =_xlfn.CONCAT(AP19,"_","JUST","_",Tab_4.DISP_INEX[[#This Row],[FORNECEDOR]]) -> 15_JUST_Associação Brasileira de Provedores de Internet - ABRINT | AS19: =_xlfn.CONCAT(AP19,"_","RAT","_",Tab_4.DISP_INEX[[#This Row],[FORNECEDOR]]) -> 15_RAT_Associação Brasileira de Provedores de Internet - ABRINT | AT19: O termo de refência e o objeto é o mesmo do n° 10
B20: 45411 | C20: FRANCIELE | D20: FINALIZADO | E20: FINALIZADO | F20: TLB-PRO-2024/01992 | G20: 2000-DAFRI | H20: GGP | I20: Serviços | J20: Curso T&D | K20: Inexigibilidade | L20: ADMINISTRATIVO | M20: Integração - Escola de Negócios Ltda | N20: 03.493.782/0001-36 | O20: Nota de Empenho | P20: 2024NE000711 | Q20: 2024NE000711 | R20: TLB-ASS-2024/06974 | S20: 45414 | T20: 45415 | U20: 45415 | V20: 5300 | W20: TLB-DEG-2024/00051 | X20: ADRYANA RAMOS DE OLIVEIRA | Y20: PÚBLICO | Z20: 10014616 | AA20: 10002720 | AB20: 2024NE000711 | AC20: 45411 | AD20: =NETWORKDAYS.INTL(Tab_4.DISP_INEX[[#This Row],[DATA RECEBIDO]],Tab_4.DISP_INEX[[#This Row],[DATA FINALIZADO]],1,Lista!$U$3:$U$15) -> 1 | AE20: FRANCIELE | AF20: CAPACITAÇÃO | AJ20: https://www.telebras.com.br/wp-content/uploads/2026/04/7.-2024NE000711-INTEG-ESCOLA-DE-NEGOCIOS-LTDA-1.pdf | AK20: https://www.telebras.com.br/wp-content/uploads/2026/06/16_TR_Integracao-Escola-de-Negocios-Ltda.pdf | AL20: https://www.telebras.com.br/wp-content/uploads/2026/06/16_JUST_Integracao-Escola-de-Negocios-Ltda.pdf | AM20: https://www.telebras.com.br/wp-content/uploads/2026/06/16_RAT_Integracao-Escola-de-Negocios-Ltda.pdf | AP20: 16 | AQ20: =_xlfn.CONCAT(AP20,"_","TR","_",Tab_4.DISP_INEX[[#This Row],[FORNECEDOR]]) -> 16_TR_Integração - Escola de Negócios Ltda | AR20: =_xlfn.CONCAT(AP20,"_","JUST","_",Tab_4.DISP_INEX[[#This Row],[FORNECEDOR]]) -> 16_JUST_Integração - Escola de Negócios Ltda | AS20: =_xlfn.CONCAT(AP20,"_","RAT","_",Tab_4.DISP_INEX[[#This Row],[FORNECEDOR]]) -> 16_RAT_Integração - Escola de Negócios Ltda
B21: 45435 | C21: FRANCIELE | D21: FINALIZADO | E21: FINALIZADO | F21: TLB-PRO-2024/02662 | G21: 2000-DAFRI | H21: GGP | I21: Serviços | J21: Contratação da participação no evento "11º Congresso Internacional de Compliance" | K21: Inexigibilidade | L21: ADMINISTRATIVO | M21: LEC EDUCACAO E PESQUISA LTDA | N21: 16.457.791/0001-13 | O21: Nota de Empenho | P21: 2024NE000822 | Q21: 2024NE000822 | R21: TLB-ASS-2024/08497 | S21: 45440 | T21: 45440 | U21: 45440 | V21: 4905 | W21: TLB-DEG-2024/00057 | X21: ADRYANA RAMOS DE OLIVEIRA | Y21: PÚBLICO | Z21: 10014684 | AA21: 10004029 | AB21: 2024NE000822 | AC21: 45436 | AD21: =NETWORKDAYS.INTL(Tab_4.DISP_INEX[[#This Row],[DATA RECEBIDO]],Tab_4.DISP_INEX[[#This Row],[DATA FINALIZADO]],1,Lista!$U$3:$U$15) -> 2 | AE21: FRANCIELE | AF21: CAPACITAÇÃO | AJ21: https://www.telebras.com.br/wp-content/uploads/2026/04/8.-2024NE000822-LEC-EDUCACAO-E-PESQUISA-LTDA-1.pdf | AK21: https://www.telebras.com.br/wp-content/uploads/2026/06/17_TR_LEC-EDUCACAO-E-PESQUISA-LTDA.pdf | AL21: https://www.telebras.com.br/wp-content/uploads/2026/06/17_JUST_LEC-EDUCACAO-E-PESQUISA-LTDA.pdf | AM21: https://www.telebras.com.br/wp-content/uploads/2026/06/17_RAT_LEC-EDUCACAO-E-PESQUISA-LTDA.pdf | AP21: 17 | AQ21: =_xlfn.CONCAT(AP21,"_","TR","_",Tab_4.DISP_INEX[[#This Row],[FORNECEDOR]]) -> 17_TR_LEC EDUCACAO E PESQUISA LTDA | AR21: =_xlfn.CONCAT(AP21,"_","JUST","_",Tab_4.DISP_INEX[[#This Row],[FORNECEDOR]]) -> 17_JUST_LEC EDUCACAO E PESQUISA LTDA | AS21: =_xlfn.CONCAT(AP21,"_","RAT","_",Tab_4.DISP_INEX[[#This Row],[FORNECEDOR]]) -> 17_RAT_LEC EDUCACAO E PESQUISA LTDA
B22: 45470 | C22: FRANCIELE | D22: FINALIZADO | E22: FINALIZADO | F22: TLB-PRO-2024/03371 | G22: 2000-DAFRI | H22: GGP | I22: Serviços | J22: Contratação da participação no evento "GDI Connect 2024 DF" | K22: Inexigibilidade | L22: ADMINISTRATIVO | M22: PS Treinamento Profissional e Consultoria Empresarial Ltda | N22: 38.593.731/0001-60 | O22: Nota de Empenho | P22: 2024NE000885 | Q22: 2024NE000885 | R22: TLB-ASS-2024/10193 | S22: 45474 | T22: 45474 | U22: 45474 | V22: 397 | W22: TLB-DEG-2024/00075 | X22: VICTOR COELHO ASSUNÇÃO CARNEIRO | Y22: PÚBLICO | Z22: 10014783 | AA22: 10004052 | AB22: 2024NE000885 | AC22: 45470 | AD22: =NETWORKDAYS.INTL(Tab_4.DISP_INEX[[#This Row],[DATA RECEBIDO]],Tab_4.DISP_INEX[[#This Row],[DATA FINALIZADO]],1,Lista!$U$3:$U$15) -> 1 | AE22: FRANCIELE | AF22: CAPACITAÇÃO | AJ22: https://www.telebras.com.br/wp-content/uploads/2026/04/10.-2024NE000940-SPACE-DATA-ASSOCIATION-1.pdf | AK22: https://www.telebras.com.br/wp-content/uploads/2026/06/18_TR_PS-Treinamento-Profissional-e-Consultoria-Empresarial-Ltda.pdf | AL22: https://www.telebras.com.br/wp-content/uploads/2026/06/18_JUST_PS-Treinamento-Profissional-e-Consultoria-Empresarial-Ltda.pdf | AM22: https://www.telebras.com.br/wp-content/uploads/2026/06/18_RAT_PS-Treinamento-Profissional-e-Consultoria-Empresarial-Ltda.pdf | AP22: 18 | AQ22: =_xlfn.CONCAT(AP22,"_","TR","_",Tab_4.DISP_INEX[[#This Row],[FORNECEDOR]]) -> 18_TR_PS Treinamento Profissional e Consultoria Empresarial Ltda | AR22: =_xlfn.CONCAT(AP22,"_","JUST","_",Tab_4.DISP_INEX[[#This Row],[FORNECEDOR]]) -> 18_JUST_PS Treinamento Profissional e Consultoria Empresarial Ltda | AS22: =_xlfn.CONCAT(AP22,"_","RAT","_",Tab_4.DISP_INEX[[#This Row],[FORNECEDOR]]) -> 18_RAT_PS Treinamento Profissional e Consultoria Empresarial Ltda
B23: 45511 | C23: FRANCIELE | D23: FINALIZADO | E23: FINALIZADO | F23: TLB-PRO-2024/01102 | G23: 3000-DTO | H23: GEOS | I23: Serviços | J23: Associação da Telebras à Space Data Association – DAS | K23: Inexigibilidade | L23: ADMINISTRATIVO | M23: Space Data Association | O23: Nota de Empenho | P23: 2024NE000940 | Q23: 2024NE000940 | R23: TLB-ASS-2024/13821 | S23: 45530 | T23: 45533 | U23: 45898 | V23: 75948.05 | W23: TLB-DEG-2024/00105 | X23: MÁRCIA MANUELA MEDRADO NUNES | Y23: PÚBLICO | Z23: 10014763 | AB23: 2024NE000940 | AC23: 45516 | AD23: =NETWORKDAYS.INTL(Tab_4.DISP_INEX[[#This Row],[DATA RECEBIDO]],Tab_4.DISP_INEX[[#This Row],[DATA FINALIZADO]],1,Lista!$U$3:$U$15) -> 4 | AE23: FRANCIELE | AF23: ASSOCIAÇÃO | AJ23: https://www.telebras.com.br/wp-content/uploads/2026/04/10.-2024NE000940-SPACE-DATA-ASSOCIATION-1.pdf | AK23: https://www.telebras.com.br/wp-content/uploads/2026/06/19_TR_Space-Data-Association.pdf | AL23: https://www.telebras.com.br/wp-content/uploads/2026/06/19_JUST_Space-Data-Association.pdf | AM23: https://www.telebras.com.br/wp-content/uploads/2026/06/19_RAT_Space-Data-Association.pdf | AP23: 19 | AQ23: =_xlfn.CONCAT(AP23,"_","TR","_",Tab_4.DISP_INEX[[#This Row],[FORNECEDOR]]) -> 19_TR_Space Data Association | AR23: =_xlfn.CONCAT(AP23,"_","JUST","_",Tab_4.DISP_INEX[[#This Row],[FORNECEDOR]]) -> 19_JUST_Space Data Association | AS23: =_xlfn.CONCAT(AP23,"_","RAT","_",Tab_4.DISP_INEX[[#This Row],[FORNECEDOR]]) -> 19_RAT_Space Data Association
B24: 45476 | C24: FRANCIELE | D24: FINALIZADO | E24: FINALIZADO | F24: TLB-PRO-2024/02467 | G24: 2000-DAFRI | H24: GPM | I24: Serviços | J24: Participação da Telebras, por meio de ação promocional, no Seminário Nacional de TIC para a Gestão Pública SECOP 2024, evento organizado exclusivamente pela Associação Brasileira de Entidades Estaduais de Tecnologia da Informação e Comunicação ABEP. | K24: Inexigibilidade | L24: ADMINISTRATIVO | M24: Associação Brasileira de Entidades Estaduais e Públicas de tecnologia da Infrmção e comunicação ES - ABEP | N24: 77.639.433/0001-16 | O24: Contrato | P24: 2024NE000896 | Q24: TLB-CTR-2024/00056 | R24: TLB-AUT-2024/12823 | S24: 45491 | T24: 45491 | U24: 45657 | V24: 59988 | W24: TLB-DEG-2024/00080 | X24: MARIANA RODRIGUES BOAVISTA LEITE | Y24: PÚBLICO | Z24: 10014621 | AA24: 10001625 | AB24: TLB-CTR-2024/00056 | AC24: 45476 | AD24: =NETWORKDAYS.INTL(Tab_4.DISP_INEX[[#This Row],[DATA RECEBIDO]],Tab_4.DISP_INEX[[#This Row],[DATA FINALIZADO]],1,Lista!$U$3:$U$15) -> 1 | AE24: FRANCIELE | AF24: EVENTO | AJ24: https://www.telebras.com.br/wp-content/uploads/2024/12/41.2024NE000896-ASSOCIACAO-BRASILEIRA-DE-ENTIDADES-ESTADUAIS.pdf | AK24: https://www.telebras.com.br/wp-content/uploads/2026/06/20_TR_Associacao-Brasileira-de-Entidades-Estaduais-e-Publicas-de-tecnologia-da-Infrmcao-e-comunicacao-ES-ABEP.pdf | AL24: https://www.telebras.com.br/wp-content/uploads/2026/06/20_JUST_Associacao-Brasileira-de-Entidades-Estaduais-e-Publicas-de-tecnologia-da-Infrmcao-e-comunicacao-ES-ABEP.pdf | AM24: https://www.telebras.com.br/wp-content/uploads/2026/06/20_RAT_Associacao-Brasileira-de-Entidades-Estaduais-e-Publicas-de-tecnologia-da-Infrmcao-e-comunicacao-ES-ABEP.pdf | AP24: 20 | AQ24: =_xlfn.CONCAT(AP24,"_","TR","_",Tab_4.DISP_INEX[[#This Row],[FORNECEDOR]]) -> 20_TR_Associação Brasileira de Entidades Estaduais e Públicas de tecnologia da Infrmção e comunicação ES - ABEP | AR24: =_xlfn.CONCAT(AP24,"_","JUST","_",Tab_4.DISP_INEX[[#This Row],[FORNECEDOR]]) -> 20_JUST_Associação Brasileira de Entidades Estaduais e Públicas de tecnologia da Infrmção e comunicação ES - ABEP | AS24: =_xlfn.CONCAT(AP24,"_","RAT","_",Tab_4.DISP_INEX[[#This Row],[FORNECEDOR]]) -> 20_RAT_Associação Brasileira de Entidades Estaduais e Públicas de tecnologia da Infrmção e comunicação ES - ABEP
B25: 45490 | C25: FRANCIELE | D25: FINALIZADO | E25: FINALIZADO | F25: TLB-PRO-2024/03684 | G25: 2000-DAFRI | H25: CIPA | I25: Serviços | J25: Contratação de empresa especializada para a prestação de serviço de treinamento de Prevenção de Acidentes do Trabalho e de Assédio, para 10 (dez) membros da Comissão interna de Prevenção de Acidentes e de Assédio (CIPA) - Gestão 2024/2025 | K25: Inexigibilidade | L25: ADMINISTRATIVO | M25: Bioseg Brasília Soluções em Segurança e Medicina do Trabalho Ltda | N25: 46.590.489/0001-08 | O25: Nota de Empenho | P25: 2024NE000909 | Q25: 2024NE000909 | R25: TLB-ASS-2024/11469 | S25: 45503 | T25: 45503 | U25: 45503 | V25: 1900 | W25: TLB-DEG-2024/00085 | X25: ROSILDA FERREIRA DA CUNHA | Y25: PÚBLICO | Z25: 10014798 | AA25: 10003765 | AB25: 2024NE000909 | AC25: 45491 | AD25: =NETWORKDAYS.INTL(Tab_4.DISP_INEX[[#This Row],[DATA RECEBIDO]],Tab_4.DISP_INEX[[#This Row],[DATA FINALIZADO]],1,Lista!$U$3:$U$15) -> 2 | AE25: FRANCIELE | AF25: CAPACITAÇÃO | AJ25: https://www.telebras.com.br/wp-content/uploads/2024/12/39.2024NE000909-Bioseg-Brasilia-Solucoes-em-Seguranca-e-Medicina-do-Trabalho-Ltda.pdf | AK25: https://www.telebras.com.br/wp-content/uploads/2026/06/21_TR_Bioseg-Brasilia-Solucoes-em-Seguranca-e-Medicina-do-Trabalho-Ltda.pdf | AL25: https://www.telebras.com.br/wp-content/uploads/2026/06/21_JUST_Bioseg-Brasilia-Solucoes-em-Seguranca-e-Medicina-do-Trabalho-Ltda.pdf | AM25: https://www.telebras.com.br/wp-content/uploads/2026/06/21_RAT_Bioseg-Brasilia-Solucoes-em-Seguranca-e-Medicina-do-Trabalho-Ltda.pdf | AP25: 21 | AQ25: =_xlfn.CONCAT(AP25,"_","TR","_",Tab_4.DISP_INEX[[#This Row],[FORNECEDOR]]) -> 21_TR_Bioseg Brasília Soluções em Segurança e Medicina do Trabalho Ltda | AR25: =_xlfn.CONCAT(AP25,"_","JUST","_",Tab_4.DISP_INEX[[#This Row],[FORNECEDOR]]) -> 21_JUST_Bioseg Brasília Soluções em Segurança e Medicina do Trabalho Ltda | AS25: =_xlfn.CONCAT(AP25,"_","RAT","_",Tab_4.DISP_INEX[[#This Row],[FORNECEDOR]]) -> 21_RAT_Bioseg Brasília Soluções em Segurança e Medicina do Trabalho Ltda
B26: 45504 | C26: FRANCIELE | D26: FINALIZADO | E26: FINALIZADO | F26: TLB-PRO-2024/03973 | G26: 2000-DAFRI | H26: GGP | I26: Serviços | J26: Contratação da capacitação "AUDI 2 EOP" e associação ao Instituto dos Auditores Internos do Brasil | K26: Inexigibilidade | L26: ADMINISTRATIVO | M26: Instituto dos Auditores Internos do Brasil | N26: 62.070.115/0001-00 | O26: Nota de Empenho | P26: 2024NE000920 | Q26: 2024NE000920 | R26: TLB-ASS-2024/12082 | S26: 45513 | T26: 45518 | U26: 45518 | V26: 8250 | W26: TLB-DEG-2024/00093 | X26: ADRYANA RAMOS DE OLIVEIRA | Y26: PÚBLICO | Z26: 10014830 | AA26: 10004111 | AB26: 2024NE000920 | AC26: 45509 | AD26: =NETWORKDAYS.INTL(Tab_4.DISP_INEX[[#This Row],[DATA RECEBIDO]],Tab_4.DISP_INEX[[#This Row],[DATA FINALIZADO]],1,Lista!$U$3:$U$15) -> 4 | AE26: FRANCIELE | AF26: CAPACITAÇÃO | AJ26: https://www.telebras.com.br/wp-content/uploads/2026/04/11.-2024NE000920-INSTITUTO-DOS-AUDITORES-INTERNOS-DO-BRASIL-1.pdf | AK26: https://www.telebras.com.br/wp-content/uploads/2026/06/22_TR_Instituto-dos-Auditores-Internos-do-Brasil.pdf | AL26: https://www.telebras.com.br/wp-content/uploads/2026/06/22_JUST_Instituto-dos-Auditores-Internos-do-Brasil.pdf | AM26: https://www.telebras.com.br/wp-content/uploads/2026/06/22_RAT_Instituto-dos-Auditores-Internos-do-Brasil.pdf | AP26: 22 | AQ26: =_xlfn.CONCAT(AP26,"_","TR","_",Tab_4.DISP_INEX[[#This Row],[FORNECEDOR]]) -> 22_TR_Instituto dos Auditores Internos do Brasil | AR26: =_xlfn.CONCAT(AP26,"_","JUST","_",Tab_4.DISP_INEX[[#This Row],[FORNECEDOR]]) -> 22_JUST_Instituto dos Auditores Internos do Brasil | AS26: =_xlfn.CONCAT(AP26,"_","RAT","_",Tab_4.DISP_INEX[[#This Row],[FORNECEDOR]]) -> 22_RAT_Instituto dos Auditores Internos do Brasil
B27: 45484 | C27: ROSILDA | D27: FINALIZADO | E27: FINALIZADO | F27: TLB-PRO-2024/02951 | G27: 2000-DAFRI | H27: GGP | I27: Serviços | J27: Participação da GGP/DAFRI no CONARH 2024 - Congresso Nacional de Gestão de Pessoas. | K27: Inexigibilidade | L27: ADMINISTRATIVO | M27: Associação Brasileira de Recursos Humanos | N27: 43.456.425/0001-12 | O27: Nota de Empenho | P27: 2024NE000895 | Q27: 2024NE000895 | R27: TLB-ASS-2024/11013 | S27: 45490 | T27: 45490 | U27: 45490 | V27: 13760 | W27: TLB-DEG-2024/00082 | X27: ADRYANA RAMOS DE OLIVEIRA | Y27: PÚBLICO | Z27: 10014768 | AB27: 2024NE000895 | AC27: 45495 | AD27: =NETWORKDAYS.INTL(Tab_4.DISP_INEX[[#This Row],[DATA RECEBIDO]],Tab_4.DISP_INEX[[#This Row],[DATA FINALIZADO]],1,Lista!$U$3:$U$15) -> 8 | AJ27: https://www.telebras.com.br/wp-content/uploads/2024/12/42.2024NE000895-ASSOCIACAO-BRASILEIRA-DE-RECURSOS-HUMANOS.pdf | AK27: https://www.telebras.com.br/wp-content/uploads/2026/06/23_TR_-Associacao-Brasileira-de-Recursos-Humanos.pdf | AL27: https://www.telebras.com.br/wp-content/uploads/2026/06/23_JUST_-Associacao-Brasileira-de-Recursos-Humanos.pdf | AM27: https://www.telebras.com.br/wp-content/uploads/2026/06/23_RAT_-Associacao-Brasileira-de-Recursos-Humanos.pdf | AP27: 23 | AQ27: =_xlfn.CONCAT(AP27,"_","TR","_",Tab_4.DISP_INEX[[#This Row],[FORNECEDOR]]) -> 23_TR_ Associação Brasileira de Recursos Humanos | AR27: =_xlfn.CONCAT(AP27,"_","JUST","_",Tab_4.DISP_INEX[[#This Row],[FORNECEDOR]]) -> 23_JUST_ Associação Brasileira de Recursos Humanos | AS27: =_xlfn.CONCAT(AP27,"_","RAT","_",Tab_4.DISP_INEX[[#This Row],[FORNECEDOR]]) -> 23_RAT_ Associação Brasileira de Recursos Humanos
B28: 45504 | C28: ROSILDA | D28: FINALIZADO | E28: FINALIZADO | F28: TLB-PRO-2024/02910 | G28: 2000-DAFRI | H28: GGP | I28: Serviços | J28: Associação/Filiação da Telebras à Sociedade Brasileira de Gestão do Conhecimento - SBGC. | K28: Inexigibilidade | L28: ADMINISTRATIVO | M28: Associação Brasileira de Gestão do Conhecimento - SBGC | N28: 04.471.222/0001-43 | O28: Nota de Empenho | P28: 2024NE000948 | Q28: 2024NE000948 | R28: TLB-ASS-2024/13048 | S28: 45539 | T28: 45551 | U28: 45924 | V28: 6500 | W28: TLB-DEG-2024/00110 | X28: CAMILA DANIELA LIMA DE SOUZA GOMES | Y28: PÚBLICO | Z28: 10014747 | AB28: TLB-ASS-2024/13480 | AC28: 45565 | AD28: =NETWORKDAYS.INTL(Tab_4.DISP_INEX[[#This Row],[DATA RECEBIDO]],Tab_4.DISP_INEX[[#This Row],[DATA FINALIZADO]],1,Lista!$U$3:$U$15) -> 44 | AJ28: https://www.telebras.com.br/wp-content/uploads/2026/04/13.-2024NE000948-ASSOC-BRAS-DE-GESTAO-CONHECIMENTO-SBGC-1.pdf | AK28: https://www.telebras.com.br/wp-content/uploads/2026/06/24_TR_Associacao-Brasileira-de-Gestao-do-Conhecimento-SBGC.pdf | AL28: https://www.telebras.com.br/wp-content/uploads/2026/06/24_JUST_Associacao-Brasileira-de-Gestao-do-Conhecimento-SBGC.pdf | AM28: https://www.telebras.com.br/wp-content/uploads/2026/06/24_RAT_Associacao-Brasileira-de-Gestao-do-Conhecimento-SBGC.pdf | AP28: 24 | AQ28: =_xlfn.CONCAT(AP28,"_","TR","_",Tab_4.DISP_INEX[[#This Row],[FORNECEDOR]]) -> 24_TR_Associação Brasileira de Gestão do Conhecimento - SBGC | AR28: =_xlfn.CONCAT(AP28,"_","JUST","_",Tab_4.DISP_INEX[[#This Row],[FORNECEDOR]]) -> 24_JUST_Associação Brasileira de Gestão do Conhecimento - SBGC | AS28: =_xlfn.CONCAT(AP28,"_","RAT","_",Tab_4.DISP_INEX[[#This Row],[FORNECEDOR]]) -> 24_RAT_Associação Brasileira de Gestão do Conhecimento - SBGC
B29: 45506 | C29: FRANCIELE | D29: FINALIZADO | E29: FINALIZADO | F29: TLB-PRO-2024/04037 | G29: 2000-DAFRI | H29: GGP | I29: Serviços | J29: Curso Governance Officer oferecido pelo Instituto Brasileiro de Governança | K29: Inexigibilidade | L29: ADMINISTRATIVO | M29: Instituto Brasileiro de Governança Corporativa | N29: 01.082.331/0001-80 | O29: Nota de Empenho | P29: 2024NE000915 | Q29: 2024NE000915 | R29: TLB-ASS-2024/11845 | S29: 45510 | T29: 45511 | U29: 45511 | V29: 16230 | W29: TLB-DEG-2024/00088 | X29: ALLYNE CUNHA DE OLIVEIRA | Y29: PÚBLICO | Z29: 10014842 | AA29: 10003951 | AB29: 2024NE000915 | AC29: 45506 | AD29: =NETWORKDAYS.INTL(Tab_4.DISP_INEX[[#This Row],[DATA RECEBIDO]],Tab_4.DISP_INEX[[#This Row],[DATA FINALIZADO]],1,Lista!$U$3:$U$15) -> 1 | AE29: FRANCIELE | AF29: CAPACITAÇÃO | AJ29: https://www.telebras.com.br/wp-content/uploads/2026/04/14.-2024NE000915-INST-BRAS-DE-GOVERNANCA-CORPORATIVA-1.pdf | AK29: https://www.telebras.com.br/wp-content/uploads/2026/06/25_TR_Instituto-Brasileiro-de-Governanca-Corporativa.pdf | AL29: https://www.telebras.com.br/wp-content/uploads/2026/06/25_JUST_Instituto-Brasileiro-de-Governanca-Corporativa.pdf | AM29: https://www.telebras.com.br/wp-content/uploads/2026/06/25_RAT_Instituto-Brasileiro-de-Governanca-Corporativa.pdf | AP29: 25 | AQ29: =_xlfn.CONCAT(AP29,"_","TR","_",Tab_4.DISP_INEX[[#This Row],[FORNECEDOR]]) -> 25_TR_Instituto Brasileiro de Governança Corporativa | AR29: =_xlfn.CONCAT(AP29,"_","JUST","_",Tab_4.DISP_INEX[[#This Row],[FORNECEDOR]]) -> 25_JUST_Instituto Brasileiro de Governança Corporativa | AS29: =_xlfn.CONCAT(AP29,"_","RAT","_",Tab_4.DISP_INEX[[#This Row],[FORNECEDOR]]) -> 25_RAT_Instituto Brasileiro de Governança Corporativa
B30: 45525 | C30: FRANCIELE | D30: FINALIZADO | E30: FINALIZADO | F30: TLB-PRO-2024/04040 | G30: 2000-DAFRI | H30: GGP | I30: Serviços | J30: Capacitação Controladoria | K30: Inexigibilidade | L30: ADMINISTRATIVO | M30: Fundação Getulio Vargas | N30: 33.641.663/0001-44 | O30: Nota de Empenho | P30: 2024NE000946 | Q30: 2024NE000946 | R30: TLB-ASS-2024/12840 | S30: 45533 | T30: 45534 | U30: 45534 | V30: 2992.8 | W30: TLB-DEG-2024/00106 | X30: HUGO PORTIERI PIGNATTI | Y30: PÚBLICO | Z30: 10014881 | AA30: 10002313 | AB30: 2024NE000946 | AC30: 45530 | AD30: =NETWORKDAYS.INTL(Tab_4.DISP_INEX[[#This Row],[DATA RECEBIDO]],Tab_4.DISP_INEX[[#This Row],[DATA FINALIZADO]],1,Lista!$U$3:$U$15) -> 4 | AE30: FRANCIELE | AF30: CAPACITAÇÃO | AJ30: https://www.telebras.com.br/wp-content/uploads/2025/02/68.2024NE000946-Fundacao-Getulio-Vargas.pdf | AK30: https://www.telebras.com.br/wp-content/uploads/2026/06/26_TR_Fundacao-Getulio-Vargas.pdf | AL30: https://www.telebras.com.br/wp-content/uploads/2026/06/26_JUST_Fundacao-Getulio-Vargas.pdf | AM30: https://www.telebras.com.br/wp-content/uploads/2026/06/26_RAT_Fundacao-Getulio-Vargas.pdf | AP30: 26 | AQ30: =_xlfn.CONCAT(AP30,"_","TR","_",Tab_4.DISP_INEX[[#This Row],[FORNECEDOR]]) -> 26_TR_Fundação Getulio Vargas | AR30: =_xlfn.CONCAT(AP30,"_","JUST","_",Tab_4.DISP_INEX[[#This Row],[FORNECEDOR]]) -> 26_JUST_Fundação Getulio Vargas | AS30: =_xlfn.CONCAT(AP30,"_","RAT","_",Tab_4.DISP_INEX[[#This Row],[FORNECEDOR]]) -> 26_RAT_Fundação Getulio Vargas
B31: 45559 | C31: FRANCIELE | D31: FINALIZADO | E31: FINALIZADO | F31: TLB-PRO-2024/04850 | G31: 2000-DAFRI | H31: GGP | I31: Serviços | J31: Capacitação Controladoria | K31: Inexigibilidade | L31: ADMINISTRATIVO | M31: Fundação Getulio Vargas | N31: 33.641.663/0001-44 | O31: Nota de Empenho | P31: 2024NE001135 | Q31: 2024NE001135 | R31: TLB-ASS-2024/17513 | S31: 45642 | T31: 45568 | U31: 45568 | V31: 2992.8 | W31: TLB-DEG-2024/00117 | X31: HUGO PORTIERI PIGNATTI | Y31: PÚBLICO | Z31: 10014941 | AA31: 10002313 | AB31: 2024NE000971 | AC31: 45561 | AD31: =NETWORKDAYS.INTL(Tab_4.DISP_INEX[[#This Row],[DATA RECEBIDO]],Tab_4.DISP_INEX[[#This Row],[DATA FINALIZADO]],1,Lista!$U$3:$U$15) -> 3 | AE31: FRANCIELE | AF31: CAPACITAÇÃO | AJ31: https://www.telebras.com.br/wp-content/uploads/2026/04/15.-2024NE001135-FUNDACAO-GETULIO-VARGAS-1.pdf | AK31: https://www.telebras.com.br/wp-content/uploads/2026/06/27_TR_Fundacao-Getulio-Vargas.pdf | AL31: https://www.telebras.com.br/wp-content/uploads/2026/06/27_JUST_Fundacao-Getulio-Vargas.pdf | AM31: https://www.telebras.com.br/wp-content/uploads/2026/06/27_RAT_Fundacao-Getulio-Vargas.pdf | AP31: 27 | AQ31: =_xlfn.CONCAT(AP31,"_","TR","_",Tab_4.DISP_INEX[[#This Row],[FORNECEDOR]]) -> 27_TR_Fundação Getulio Vargas | AR31: =_xlfn.CONCAT(AP31,"_","JUST","_",Tab_4.DISP_INEX[[#This Row],[FORNECEDOR]]) -> 27_JUST_Fundação Getulio Vargas | AS31: =_xlfn.CONCAT(AP31,"_","RAT","_",Tab_4.DISP_INEX[[#This Row],[FORNECEDOR]]) -> 27_RAT_Fundação Getulio Vargas
B32: 45566 | C32: FRANCIELE | D32: FINALIZADO | E32: FINALIZADO | F32: TLB-PRO-2024/05179 | G32: 2000-DAFRI | H32: GGP | I32: Serviços | J32: 25º Congresso IBGC - Cultura de Governança e os Desafios do Brasil | K32: Inexigibilidade | L32: ADMINISTRATIVO | M32: Instituto Brasileiro de Governança Corporativa | N32: 01.082.331/0001-80 | O32: Nota de Empenho | P32: 2024NE000972 | Q32: 2024NE000972 | R32: TLB-ASS-2024/14022 | S32: 02/10/2024 | T32: 45568 | U32: 45568 | V32: 22610 | W32: TLB-DEG-2024/00116 | X32: ADRYANA RAMOS DE OLIVEIRA | Y32: PÚBLICO | Z32: 10014955 | AA32: 10003951 | AB32: 2024NE000972 | AC32: 45566 | AD32: =NETWORKDAYS.INTL(Tab_4.DISP_INEX[[#This Row],[DATA RECEBIDO]],Tab_4.DISP_INEX[[#This Row],[DATA FINALIZADO]],1,Lista!$U$3:$U$15) -> 1 | AE32: FRANCIELE | AF32: EVENTO | AJ32: https://www.telebras.com.br/wp-content/uploads/2024/12/56.2024NE000972-INSTITUTO-BRASILEIRO-DE-GOVERNANCA-CORPORATIVA.pdf | AK32: https://www.telebras.com.br/wp-content/uploads/2026/06/28_TR_Instituto-Brasileiro-de-Governanca-Corporativa.pdf | AL32: https://www.telebras.com.br/wp-content/uploads/2026/06/28_JUST_Instituto-Brasileiro-de-Governanca-Corporativa.pdf | AM32: https://www.telebras.com.br/wp-content/uploads/2026/06/28_RAT_Instituto-Brasileiro-de-Governanca-Corporativa.pdf | AP32: 28 | AQ32: =_xlfn.CONCAT(AP32,"_","TR","_",Tab_4.DISP_INEX[[#This Row],[FORNECEDOR]]) -> 28_TR_Instituto Brasileiro de Governança Corporativa | AR32: =_xlfn.CONCAT(AP32,"_","JUST","_",Tab_4.DISP_INEX[[#This Row],[FORNECEDOR]]) -> 28_JUST_Instituto Brasileiro de Governança Corporativa | AS32: =_xlfn.CONCAT(AP32,"_","RAT","_",Tab_4.DISP_INEX[[#This Row],[FORNECEDOR]]) -> 28_RAT_Instituto Brasileiro de Governança Corporativa
B33: 45573 | C33: FRANCIELE | D33: FINALIZADO | E33: FINALIZADO | F33: TLB-PRO-2024/04517 | G33: 2000-DAFRI | H33: GGP | I33: Serviços | J33: Capacitação NRs 06, 10, 12, 20 e 35 | K33: Inexigibilidade | L33: ADMINISTRATIVO | M33: Bioseg Brasília Soluções em Segurança e Medicina do Trabalho Ltda | N33: 46.590.489/0001-08 | O33: Nota de Empenho | P33: 2024NE000985 | Q33: 2024NE000985 | R33: TLB-ASS-2024/14431 | S33: 45576 | T33: 45580 | U33: 45580 | V33: 15100 | W33: TLB-DEG-2024/00118 | X33: ADRYANA RAMOS DE OLIVEIRA | Y33: PÚBLICO | Z33: 10014956 | AA33: 10003765 | AB33: 2024NE000985 | AC33: 45574 | AD33: =NETWORKDAYS.INTL(Tab_4.DISP_INEX[[#This Row],[DATA RECEBIDO]],Tab_4.DISP_INEX[[#This Row],[DATA FINALIZADO]],1,Lista!$U$3:$U$15) -> 2 | AE33: FRANCIELE | AF33: CAPACITAÇÃO | AJ33: https://www.telebras.com.br/wp-content/uploads/2024/12/58.2024NE000985-Bioseg-Brasilia-Solucoes-em-Seguranca-e-Medicina-do-Trabalho-Ltda.pdf | AK33: https://www.telebras.com.br/wp-content/uploads/2026/06/29_TR_Bioseg-Brasilia-Solucoes-em-Seguranca-e-Medicina-do-Trabalho-Ltda.pdf | AL33: https://www.telebras.com.br/wp-content/uploads/2026/06/29_JUST_Bioseg-Brasilia-Solucoes-em-Seguranca-e-Medicina-do-Trabalho-Ltda.pdf | AM33: https://www.telebras.com.br/wp-content/uploads/2026/06/29_RAT_Bioseg-Brasilia-Solucoes-em-Seguranca-e-Medicina-do-Trabalho-Ltda.pdf | AP33: 29 | AQ33: =_xlfn.CONCAT(AP33,"_","TR","_",Tab_4.DISP_INEX[[#This Row],[FORNECEDOR]]) -> 29_TR_Bioseg Brasília Soluções em Segurança e Medicina do Trabalho Ltda | AR33: =_xlfn.CONCAT(AP33,"_","JUST","_",Tab_4.DISP_INEX[[#This Row],[FORNECEDOR]]) -> 29_JUST_Bioseg Brasília Soluções em Segurança e Medicina do Trabalho Ltda | AS33: =_xlfn.CONCAT(AP33,"_","RAT","_",Tab_4.DISP_INEX[[#This Row],[FORNECEDOR]]) -> 29_RAT_Bioseg Brasília Soluções em Segurança e Medicina do Trabalho Ltda
B34: 45587 | C34: ROSILDA | D34: FINALIZADO | E34: FINALIZADO | F34: TLB-PRO-2024/05477 | G34: 2000-DAFRI | H34: GCC | I34: Serviços | J34: Contratação da ferramenta de pesquisa e comparação de preços praticados pela administração pública, denominada Banco de Preços | K34: Inexigibilidade | L34: ADMINISTRATIVO | M34: NP Tecnologia e Gestão de Dados Ltda | N34: 07.797.967/0001-95 | O34: Nota de Empenho | P34: 2024NE001046 | Q34: 2024NE001046 | R34: TLB-ASS-2024/15214 | S34: 45590 | T34: 45595 | U34: 45595 | V34: 11960 | W34: TLB-DEG-2024/00125 | X34: ROSILDA ABREU DA SILVA | Y34: PÚBLICO | Z34: 10014984 | AB34: 2024NE001046 | AC34: 45595 | AD34: =NETWORKDAYS.INTL(Tab_4.DISP_INEX[[#This Row],[DATA RECEBIDO]],Tab_4.DISP_INEX[[#This Row],[DATA FINALIZADO]],1,Lista!$U$3:$U$15) -> 7 | AE34: ROSILDA | AJ34: https://www.telebras.com.br/wp-content/uploads/2024/12/59.2024NE001046-NP-Tecnologia-e-Gestao-de-Dados-Ltda.pdf | AK34: https://www.telebras.com.br/wp-content/uploads/2026/06/30_TR_NP-Tecnologia-e-Gestao-de-Dados-Ltda.pdf | AL34: https://www.telebras.com.br/wp-content/uploads/2026/06/30_JUST_NP-Tecnologia-e-Gestao-de-Dados-Ltda.pdf | AM34: https://www.telebras.com.br/wp-content/uploads/2026/06/30_RAT_NP-Tecnologia-e-Gestao-de-Dados-Ltda.pdf | AP34: 30 | AQ34: =_xlfn.CONCAT(AP34,"_","TR","_",Tab_4.DISP_INEX[[#This Row],[FORNECEDOR]]) -> 30_TR_NP Tecnologia e Gestão de Dados Ltda | AR34: =_xlfn.CONCAT(AP34,"_","JUST","_",Tab_4.DISP_INEX[[#This Row],[FORNECEDOR]]) -> 30_JUST_NP Tecnologia e Gestão de Dados Ltda | AS34: =_xlfn.CONCAT(AP34,"_","RAT","_",Tab_4.DISP_INEX[[#This Row],[FORNECEDOR]]) -> 30_RAT_NP Tecnologia e Gestão de Dados Ltda
B35: 45610 | C35: ROSILDA | D35: FINALIZADO | E35: FINALIZADO | F35: TLB-PRO-2024/06064 | G35: 2000-DAFRI | H35: GGP | I35: Serviços | J35: Capacitação Credenciamento | K35: Inexigibilidade | L35: ADMINISTRATIVO | M35: Zênite Informação e Consultoria S/A | N35: 86.781.069/0001-15 | O35: Nota de Empenho | P35: 2024NE001078 | Q35: 2024NE001078 | R35: TLB-ASS-2024/16489 | S35: 45623 | T35: 45624 | U35: 45624 | V35: 3944 | W35: TLB-DEG-2024/00129 | X35: ROSILDA ABREU DA SILVA | Y35: PÚBLICO | Z35: 10015151 | AB35: 2024NE001078 | AC35: 45624 | AD35: =NETWORKDAYS.INTL(Tab_4.DISP_INEX[[#This Row],[DATA RECEBIDO]],Tab_4.DISP_INEX[[#This Row],[DATA FINALIZADO]],1,Lista!$U$3:$U$15) -> 9 | AE35: ROSILDA | AF35: CAPACITAÇÃO | AJ35: https://www.telebras.com.br/wp-content/uploads/2025/02/70.2024NE001078-ZENITE-INFORMACAO-E-CONSULTORIA-SA.pdf | AK35: https://www.telebras.com.br/wp-content/uploads/2026/06/31_TR_Zenite-Informacao-e-Consultoria-SA.pdf | AL35: https://www.telebras.com.br/wp-content/uploads/2026/06/31_JUST_Zenite-Informacao-e-Consultoria-SA.pdf | AM35: https://www.telebras.com.br/wp-content/uploads/2026/06/31_RAT_Zenite-Informacao-e-Consultoria-SA.pdf | AP35: 31 | AQ35: =_xlfn.CONCAT(AP35,"_","TR","_",Tab_4.DISP_INEX[[#This Row],[FORNECEDOR]]) -> 31_TR_Zênite Informação e Consultoria S/A | AR35: =_xlfn.CONCAT(AP35,"_","JUST","_",Tab_4.DISP_INEX[[#This Row],[FORNECEDOR]]) -> 31_JUST_Zênite Informação e Consultoria S/A | AS35: =_xlfn.CONCAT(AP35,"_","RAT","_",Tab_4.DISP_INEX[[#This Row],[FORNECEDOR]]) -> 31_RAT_Zênite Informação e Consultoria S/A
B36: 45618 | C36: FRANCIELE | D36: FINALIZADO | E36: FINALIZADO | F36: TLB-PRO-2024/06102 | G36: 2000-DAFRI | H36: GGP | I36: Serviços | J36: Curso Treinamento Executivo Risk University | K36: Inexigibilidade | L36: ADMINISTRATIVO | M36: KPMG Consultoria Ltda | N36: 01.708.167/0001-74 | O36: Nota de Empenho | P36: 2024NE001079 | Q36: 2024NE001079 | R36: TLB-ASS-2024/16552 | S36: 45628 | T36: 45628 | U36: 45628 | V36: 22066 | X36: ADRYANA RAMOS DE OLIVEIRA | Y36: PÚBLICO | Z36: 10015075 | AB36: 2024NE001079 | AC36: 45622 | AD36: =NETWORKDAYS.INTL(Tab_4.DISP_INEX[[#This Row],[DATA RECEBIDO]],Tab_4.DISP_INEX[[#This Row],[DATA FINALIZADO]],1,Lista!$U$3:$U$15) -> 3 | AE36: FRANCIELE | AF36: PROCESSO CANCELADO E INSTAURADO NOVO | AJ36: https://www.telebras.com.br/wp-content/uploads/2025/02/71.2024NE001081-INSTITUTO-BRASILEIRO-DE-GOVERNANCA-CORPORATIV_1.pdf | AK36: https://www.telebras.com.br/wp-content/uploads/2026/06/32_TR_KPMG-Consultoria-Ltda.pdf | AL36: https://www.telebras.com.br/wp-content/uploads/2026/06/32_JUST_KPMG-Consultoria-Ltda.pdf | AM36: https://www.telebras.com.br/wp-content/uploads/2026/06/32_RAT_KPMG-Consultoria-Ltda.pdf | AP36: 32 | AQ36: =_xlfn.CONCAT(AP36,"_","TR","_",Tab_4.DISP_INEX[[#This Row],[FORNECEDOR]]) -> 32_TR_KPMG Consultoria Ltda | AR36: =_xlfn.CONCAT(AP36,"_","JUST","_",Tab_4.DISP_INEX[[#This Row],[FORNECEDOR]]) -> 32_JUST_KPMG Consultoria Ltda | AS36: =_xlfn.CONCAT(AP36,"_","RAT","_",Tab_4.DISP_INEX[[#This Row],[FORNECEDOR]]) -> 32_RAT_KPMG Consultoria Ltda
B37: 45621 | C37: FRANCIELE | D37: FINALIZADO | E37: FINALIZADO | F37: TLB-PRO-2024/06203 | G37: 2000-DAFRI | H37: GGP | I37: Serviços | J37: Curso Governança Corporativa para Empresas Estatais | K37: Inexigibilidade | L37: ADMINISTRATIVO | M37: INSTITUTO BRASILEIRO DE GOVERNANÇA CORPORATIVA | N37: 01.082.331/0001-80 | O37: Nota de Empenho | P37: 2024NE001081 | Q37: 2024NE001081 | R37: TLB-ASS-2024/16583 | S37: 45625 | T37: 45629 | U37: 45629 | V37: 36800 | W37: TLB-DEG-2024/00130 | X37: ADRYANA RAMOS DE OLIVEIRA | Y37: PÚBLICO | Z37: 10015226 | AA37: 10003951 | AB37: 2024NE001081 | AC37: 45623 | AD37: =NETWORKDAYS.INTL(Tab_4.DISP_INEX[[#This Row],[DATA RECEBIDO]],Tab_4.DISP_INEX[[#This Row],[DATA FINALIZADO]],1,Lista!$U$3:$U$15) -> 3 | AE37: FRANCIELE | AF37: CAPACITAÇÃO | AJ37: https://www.telebras.com.br/wp-content/uploads/2025/02/71.2024NE001081-INSTITUTO-BRASILEIRO-DE-GOVERNANCA-CORPORATIV_1.pdf | AK37: https://www.telebras.com.br/wp-content/uploads/2026/06/33_TR_INSTITUTO-BRASILEIRO-DE-GOVERNANCA-CORPORATIVA.pdf | AL37: https://www.telebras.com.br/wp-content/uploads/2026/06/33_JUST_INSTITUTO-BRASILEIRO-DE-GOVERNANCA-CORPORATIVA.pdf | AM37: https://www.telebras.com.br/wp-content/uploads/2026/06/33_RAT_INSTITUTO-BRASILEIRO-DE-GOVERNANCA-CORPORATIVA.pdf | AP37: 33 | AQ37: =_xlfn.CONCAT(AP37,"_","TR","_",Tab_4.DISP_INEX[[#This Row],[FORNECEDOR]]) -> 33_TR_INSTITUTO BRASILEIRO DE GOVERNANÇA CORPORATIVA | AR37: =_xlfn.CONCAT(AP37,"_","JUST","_",Tab_4.DISP_INEX[[#This Row],[FORNECEDOR]]) -> 33_JUST_INSTITUTO BRASILEIRO DE GOVERNANÇA CORPORATIVA | AS37: =_xlfn.CONCAT(AP37,"_","RAT","_",Tab_4.DISP_INEX[[#This Row],[FORNECEDOR]]) -> 33_RAT_INSTITUTO BRASILEIRO DE GOVERNANÇA CORPORATIVA
B38: 45624 | C38: FRANCIELE | D38: FINALIZADO | E38: FINALIZADO | F38: TLB-PRO-2024/06226 | G38: 2000-DAFRI | H38: GGP | I38: Serviços | J38: Treinamento na Trilha: Tecnologia celular 4G – LTE | K38: Inexigibilidade | L38: ADMINISTRATIVO | M38: Fundação Instituto Nacional de Telecomunicações | N38: 24.492.886/0001-04 | O38: Nota de Empenho | P38: 2024NE001084 | Q38: 2024NE001084 | R38: TLB-ASS-2024/16671 | S38: 45628 | T38: 45630 | U38: 45630 | V38: 5397.3 | W38: TLB-DEG-2024/00134 | X38: ADRYANA RAMOS DE OLIVEIRA | Y38: PÚBLICO | Z38: 10015230 | AA38: 10004137 | AB38: 2024NE001084 | AC38: 45624 | AD38: =NETWORKDAYS.INTL(Tab_4.DISP_INEX[[#This Row],[DATA RECEBIDO]],Tab_4.DISP_INEX[[#This Row],[DATA FINALIZADO]],1,Lista!$U$3:$U$15) -> 1 | AE38: FRANCIELE | AF38: CAPACITAÇÃO | AJ38: https://www.telebras.com.br/wp-content/uploads/2025/02/72.2024NE001084-FUNDACAO-INSTITUTO-NACIONAL-DE-TELECOMUNICACO_2.pdf | AK38: https://www.telebras.com.br/wp-content/uploads/2026/06/34_TR_Fundacao-Instituto-Nacional-de-Telecomunicacoes.pdf | AL38: https://www.telebras.com.br/wp-content/uploads/2026/06/34_JUST_Fundacao-Instituto-Nacional-de-Telecomunicacoes.pdf | AM38: https://www.telebras.com.br/wp-content/uploads/2026/06/34_RAT_Fundacao-Instituto-Nacional-de-Telecomunicacoes.pdf | AP38: 34 | AQ38: =_xlfn.CONCAT(AP38,"_","TR","_",Tab_4.DISP_INEX[[#This Row],[FORNECEDOR]]) -> 34_TR_Fundação Instituto Nacional de Telecomunicações | AR38: =_xlfn.CONCAT(AP38,"_","JUST","_",Tab_4.DISP_INEX[[#This Row],[FORNECEDOR]]) -> 34_JUST_Fundação Instituto Nacional de Telecomunicações | AS38: =_xlfn.CONCAT(AP38,"_","RAT","_",Tab_4.DISP_INEX[[#This Row],[FORNECEDOR]]) -> 34_RAT_Fundação Instituto Nacional de Telecomunicações
B39: 45622 | C39: FRANCIELE | D39: FINALIZADO | E39: FINALIZADO | F39: TLB-PRO-2024/06217 | G39: 2000-DAFRI | H39: GGP | I39: Serviços | J39: Formação de Facilitadores em Modelagem da Cultura Organizacional | K39: Inexigibilidade | L39: ADMINISTRATIVO | M39: Akademia de Transformação Organizacional LTDA | N39: 29.484.585/0001-44 | O39: Nota de Empenho | P39: 2024NE001085 | Q39: 2024NE001085 | R39: TLB-ASS-2024/16672 | S39: 45628 | T39: 45630 | U39: 45630 | V39: 2497 | W39: TLB-DEG-2024/00135 | X39: MADALENE MENEZES VERTELO | Y39: PÚBLICO | Z39: 10015234 | AA39: 10004138 | AB39: 2024NE001085 | AC39: 45624 | AD39: =NETWORKDAYS.INTL(Tab_4.DISP_INEX[[#This Row],[DATA RECEBIDO]],Tab_4.DISP_INEX[[#This Row],[DATA FINALIZADO]],1,Lista!$U$3:$U$15) -> 3 | AE39: FRANCIELE | AF39: CAPACITAÇÃO | AJ39: https://www.telebras.com.br/wp-content/uploads/2025/02/73.2024NE001085-AKADEMIA-DE-TRANSFORMACAO-ORGANIZACIONAL-LTDA.pdf | AK39: https://www.telebras.com.br/wp-content/uploads/2026/06/35_TR_Akademia-de-Transformacao-Organizacional-LTDA.pdf | AL39: https://www.telebras.com.br/wp-content/uploads/2026/06/35_JUST_Akademia-de-Transformacao-Organizacional-LTDA.pdf | AM39: https://www.telebras.com.br/wp-content/uploads/2026/06/35_RAT_Akademia-de-Transformacao-Organizacional-LTDA.pdf | AP39: 35 | AQ39: =_xlfn.CONCAT(AP39,"_","TR","_",Tab_4.DISP_INEX[[#This Row],[FORNECEDOR]]) -> 35_TR_Akademia de Transformação Organizacional LTDA | AR39: =_xlfn.CONCAT(AP39,"_","JUST","_",Tab_4.DISP_INEX[[#This Row],[FORNECEDOR]]) -> 35_JUST_Akademia de Transformação Organizacional LTDA | AS39: =_xlfn.CONCAT(AP39,"_","RAT","_",Tab_4.DISP_INEX[[#This Row],[FORNECEDOR]]) -> 35_RAT_Akademia de Transformação Organizacional LTDA
B40: 45623 | C40: FRANCIELE | D40: FINALIZADO | E40: FINALIZADO | F40: TLB-PRO-2024/06221 | G40: 2000-DAFRI | H40: GGP | I40: Serviços | J40: Capacitação Técnica em Comunicação e Produção de Conteúdo para Gestão do Conhecimento. | K40: Inexigibilidade | L40: ADMINISTRATIVO | M40: Mariana Rodrigues de Lima | N40: 52.552.337/0001-05 | O40: Nota de Empenho | P40: 2024NE001082 | Q40: 2024NE001082 | R40: TLB-ASS-2024/16669 | S40: 02/12/2024 | T40: 45630 | U40: 45630 | V40: 8000 | W40: TLB-DEG-2024/00136 | X40: CAMILA DANIELA LIMA DE SOUZA GOMES | Y40: PÚBLICO | Z40: 10015238 | AA40: 10004139 | AB40: 2024NE001082 | AC40: 45624 | AD40: =NETWORKDAYS.INTL(Tab_4.DISP_INEX[[#This Row],[DATA RECEBIDO]],Tab_4.DISP_INEX[[#This Row],[DATA FINALIZADO]],1,Lista!$U$3:$U$15) -> 2 | AE40: FRANCIELE | AF40: CAPACITAÇÃO | AJ40: https://www.telebras.com.br/wp-content/uploads/2025/02/74.2024NE001082-MARIANA-RODRIGUES-DE-LIMA_3.pdf | AK40: - | AL40: - | AM40: - | AP40: 36 | AQ40: =_xlfn.CONCAT(AP40,"_","TR","_",Tab_4.DISP_INEX[[#This Row],[FORNECEDOR]]) -> 36_TR_Mariana Rodrigues de Lima | AR40: =_xlfn.CONCAT(AP40,"_","JUST","_",Tab_4.DISP_INEX[[#This Row],[FORNECEDOR]]) -> 36_JUST_Mariana Rodrigues de Lima | AS40: =_xlfn.CONCAT(AP40,"_","RAT","_",Tab_4.DISP_INEX[[#This Row],[FORNECEDOR]]) -> 36_RAT_Mariana Rodrigues de Lima
B41: 45625 | C41: FRANCIELE | D41: FINALIZADO | E41: FINALIZADO | F41: TLB-PRO-2024/06280 | G41: 2000-DAFRI | H41: GGP | I41: Serviços | J41: Desenvolvimento de Talentos e Gestão de Carreiras | K41: Inexigibilidade | L41: ADMINISTRATIVO | M41: Ibmec Educacional Ltda | N41: 04.298.309/0007-56 | O41: Nota de Empenho | P41: 2024NE001088 | Q41: 2024NE001088 | R41: TLB-ASS-2024/16858 | S41: 45630 | T41: 45636 | U41: 45636 | V41: 499 | W41: TLB-DEG-2024/00138 | X41: ADRYANA RAMOS DE OLIVEIRA | Y41: PÚBLICO | Z41: 10015251 | AA41: 10004165 | AB41: 2024NE001088 | AC41: 45628 | AD41: =NETWORKDAYS.INTL(Tab_4.DISP_INEX[[#This Row],[DATA RECEBIDO]],Tab_4.DISP_INEX[[#This Row],[DATA FINALIZADO]],1,Lista!$U$3:$U$15) -> 2 | AE41: FRANCIELE | AF41: CAPACITAÇÃO | AJ41: https://www.telebras.com.br/wp-content/uploads/2025/02/75.2024NE001088-BMEC-EDUCACIONAL-LTDA_4.pdf | AK41: - | AL41: - | AM41: - | AP41: 37 | AQ41: =_xlfn.CONCAT(AP41,"_","TR","_",Tab_4.DISP_INEX[[#This Row],[FORNECEDOR]]) -> 37_TR_Ibmec Educacional Ltda | AR41: =_xlfn.CONCAT(AP41,"_","JUST","_",Tab_4.DISP_INEX[[#This Row],[FORNECEDOR]]) -> 37_JUST_Ibmec Educacional Ltda | AS41: =_xlfn.CONCAT(AP41,"_","RAT","_",Tab_4.DISP_INEX[[#This Row],[FORNECEDOR]]) -> 37_RAT_Ibmec Educacional Ltda
B42: 45628 | C42: FRANCIELE | D42: FINALIZADO | E42: FINALIZADO | F42: TLB-PRO-2024/06285 | G42: 2000-DAFRI | H42: GGP | I42: Serviços | J42: Curso de COBIT®️ 2019 Foundation para profissionais lotados na GTI | K42: Inexigibilidade | L42: ADMINISTRATIVO | M42: Singulares Tecnologia da Informação Ltda | N42: 23.992.391/0001-73 | O42: Nota de Empenho | P42: 2024NE001105 | Q42: 2024NE001105 | R42: TLB-ASS-2024/17036 | S42: 45632 | T42: 45636 | U42: 45636 | V42: 5850 | W42: TLB-DEG-2024/00145 | X42: ADRYANA RAMOS DE OLIVEIRA | Y42: PÚBLICO | Z42: 10015253 | AA42: 10004256 | AB42: 2024NE001105 | AC42: 45630 | AD42: =NETWORKDAYS.INTL(Tab_4.DISP_INEX[[#This Row],[DATA RECEBIDO]],Tab_4.DISP_INEX[[#This Row],[DATA FINALIZADO]],1,Lista!$U$3:$U$15) -> 3 | AE42: FRANCIELE | AF42: CAPACITAÇÃO | AJ42: https://www.telebras.com.br/wp-content/uploads/2025/02/76.2024NE001105-SINGULARES-TECNOLOGIA-DA-INFORMACAO-LTDA.pdf | AK42: - | AL42: - | AM42: - | AP42: 38 | AQ42: =_xlfn.CONCAT(AP42,"_","TR","_",Tab_4.DISP_INEX[[#This Row],[FORNECEDOR]]) -> 38_TR_Singulares Tecnologia da Informação Ltda | AR42: =_xlfn.CONCAT(AP42,"_","JUST","_",Tab_4.DISP_INEX[[#This Row],[FORNECEDOR]]) -> 38_JUST_Singulares Tecnologia da Informação Ltda | AS42: =_xlfn.CONCAT(AP42,"_","RAT","_",Tab_4.DISP_INEX[[#This Row],[FORNECEDOR]]) -> 38_RAT_Singulares Tecnologia da Informação Ltda
B43: 45628 | C43: FRANCIELE | D43: FINALIZADO | E43: FINALIZADO | F43: TLB-PRO-2024/06308 | G43: 2000-DAFRI | H43: GGP | I43: Serviços | J43: Curso básico de DevOps, identificado como DevOps Fundamentos, na TRAINNING Education Center para os colaboradores da GTI | K43: Inexigibilidade | L43: ADMINISTRATIVO | M43: MINDWORKS -TECNOLOGIA E TREINAMENTO LTDA | N43: 48.933.398/0001-45 | O43: Nota de Empenho | P43: 2024NE001098 | Q43: 2024NE001098 | R43: TLB-ASS-2024/17006 | S43: 45632 | T43: 45636 | U43: 45636 | V43: 5170 | W43: TLB-DEG-2024/00139 | X43: ADRYANA RAMOS DE OLIVEIRA | Y43: PÚBLICO | Z43: 10015252 | AA43: 10004133 | AB43: 2024NE001098 | AC43: 45628 | AD43: =NETWORKDAYS.INTL(Tab_4.DISP_INEX[[#This Row],[DATA RECEBIDO]],Tab_4.DISP_INEX[[#This Row],[DATA FINALIZADO]],1,Lista!$U$3:$U$15) -> 1 | AE43: FRANCIELE | AF43: CAPACITAÇÃO | AJ43: https://www.telebras.com.br/wp-content/uploads/2025/02/77.2024NE001098-MINDWORKS-TECNOLOGIA-E-TREINAMENTO-LTDA_5.pdf | AK43: - | AL43: - | AM43: - | AP43: 39 | AQ43: =_xlfn.CONCAT(AP43,"_","TR","_",Tab_4.DISP_INEX[[#This Row],[FORNECEDOR]]) -> 39_TR_MINDWORKS -TECNOLOGIA E TREINAMENTO LTDA | AR43: =_xlfn.CONCAT(AP43,"_","JUST","_",Tab_4.DISP_INEX[[#This Row],[FORNECEDOR]]) -> 39_JUST_MINDWORKS -TECNOLOGIA E TREINAMENTO LTDA | AS43: =_xlfn.CONCAT(AP43,"_","RAT","_",Tab_4.DISP_INEX[[#This Row],[FORNECEDOR]]) -> 39_RAT_MINDWORKS -TECNOLOGIA E TREINAMENTO LTDA
B44: 45628 | C44: FRANCIELE | D44: FINALIZADO | E44: FINALIZADO | F44: TLB-PRO-2024/06369 | G44: 2000-DAFRI | H44: GGP | I44: Serviços | J44: Curso/Treinamento: Relações com Investidores na prática: Completo | K44: Inexigibilidade | L44: ADMINISTRATIVO | M44: FUNDAÇÃO INSTITUTO DE PESQUISAS CONTABEIS, ATUARIAIS E FINANCEIRAS - FIPECAFI | N44: 46.359.865/0001-40 | O44: Nota de Empenho | P44: 2024NE001103 | Q44: 2024NE001103 | R44: TLB-ASS-2024/17017 | S44: 45632 | T44: 45636 | U44: 45636 | V44: 2805 | W44: TLB-DEG-2024/00140 | X44: ADRYANA RAMOS DE OLIVEIRA | Y44: PÚBLICO | Z44: 10015243 | AA44: 10002554 | AB44: 2024NE001103 | AC44: 45629 | AD44: =NETWORKDAYS.INTL(Tab_4.DISP_INEX[[#This Row],[DATA RECEBIDO]],Tab_4.DISP_INEX[[#This Row],[DATA FINALIZADO]],1,Lista!$U$3:$U$15) -> 2 | AE44: FRANCIELE | AF44: CAPACITAÇÃO | AJ44: https://www.telebras.com.br/wp-content/uploads/2025/02/78.2024NE001103-FUNDACAO-INSTITUTO-DE-PESQUISAS-CONTABEIS-AT.pdf | AK44: - | AL44: - | AM44: - | AP44: 40 | AQ44: =_xlfn.CONCAT(AP44,"_","TR","_",Tab_4.DISP_INEX[[#This Row],[FORNECEDOR]]) -> 40_TR_FUNDAÇÃO INSTITUTO DE PESQUISAS CONTABEIS, ATUARIAIS E FINANCEIRAS - FIPECAFI | AR44: =_xlfn.CONCAT(AP44,"_","JUST","_",Tab_4.DISP_INEX[[#This Row],[FORNECEDOR]]) -> 40_JUST_FUNDAÇÃO INSTITUTO DE PESQUISAS CONTABEIS, ATUARIAIS E FINANCEIRAS - FIPECAFI | AS44: =_xlfn.CONCAT(AP44,"_","RAT","_",Tab_4.DISP_INEX[[#This Row],[FORNECEDOR]]) -> 40_RAT_FUNDAÇÃO INSTITUTO DE PESQUISAS CONTABEIS, ATUARIAIS E FINANCEIRAS - FIPECAFI
B45: 45629 | C45: FRANCIELE | D45: FINALIZADO | E45: FINALIZADO | F45: TLB-PRO-2024/06355 | G45: 2000-DAFRI | H45: GGP | I45: Serviços | J45: Capacitação GID Análise de dados | K45: Inexigibilidade | L45: ADMINISTRATIVO | M45: Mindworks - Tecnologia e Treinamento Ltda | N45: 48.933.398/0001-45 | O45: Nota de Empenho | P45: 2024NE001108 | Q45: 2024NE001108 | R45: TLB-ASS-2024/17038 | S45: 45632 | T45: 45636 | U45: 10/12/2024 | V45: 7080 | W45: TLB-DEG-2024/00142 | X45: ADRYANA RAMOS DE OLIVEIRA | Y45: PÚBLICO | Z45: 10015245 | AA45: 10004133 | AB45: 2024NE001108 | AC45: 45630 | AD45: =NETWORKDAYS.INTL(Tab_4.DISP_INEX[[#This Row],[DATA RECEBIDO]],Tab_4.DISP_INEX[[#This Row],[DATA FINALIZADO]],1,Lista!$U$3:$U$15) -> 2 | AE45: FRANCIELE | AF45: CAPACITAÇÃO | AJ45: https://www.telebras.com.br/wp-content/uploads/2025/02/79.2024NE001108-MINDWORKS-TECNOLOGIA-E-TREINAMENTO-LTDA.pdf | AK45: - | AL45: - | AM45: - | AP45: 41 | AQ45: =_xlfn.CONCAT(AP45,"_","TR","_",Tab_4.DISP_INEX[[#This Row],[FORNECEDOR]]) -> 41_TR_Mindworks - Tecnologia e Treinamento Ltda | AR45: =_xlfn.CONCAT(AP45,"_","JUST","_",Tab_4.DISP_INEX[[#This Row],[FORNECEDOR]]) -> 41_JUST_Mindworks - Tecnologia e Treinamento Ltda | AS45: =_xlfn.CONCAT(AP45,"_","RAT","_",Tab_4.DISP_INEX[[#This Row],[FORNECEDOR]]) -> 41_RAT_Mindworks - Tecnologia e Treinamento Ltda
B46: 45629 | C46: FRANCIELE | D46: FINALIZADO | E46: FINALIZADO | F46: TLB-PRO-2024/06358 | G46: 2000-DAFRI | H46: GGP | I46: Serviços | J46: Capacitação em modelagem de dados e Automação | K46: Inexigibilidade | L46: ADMINISTRATIVO | M46: Mindworks - Tecnologia e Treinamento Ltda | N46: 48.933.398/0001-45 | O46: Nota de Empenho | P46: 2024NE001104 | Q46: 2024NE001104 | R46: TLB-ASS-2024/17033 | S46: 45632 | T46: 45636 | U46: 45636 | V46: 5415 | W46: TLB-DEG-2024/00143 | X46: ADRYANA RAMOS DE OLIVEIRA | Y46: PÚBLICO | Z46: 10015258 | AA46: 10004133 | AB46: 2024NE001104 | AC46: 45630 | AD46: =NETWORKDAYS.INTL(Tab_4.DISP_INEX[[#This Row],[DATA RECEBIDO]],Tab_4.DISP_INEX[[#This Row],[DATA FINALIZADO]],1,Lista!$U$3:$U$15) -> 2 | AE46: FRANCIELE | AF46: CAPACITAÇÃO | AJ46: https://www.telebras.com.br/wp-content/uploads/2025/02/80.2024NE001104-MINDWORKS-TECNOLOGIA-E-TREINAMENTO-LTDA.pdf | AK46: - | AL46: - | AM46: - | AP46: 42 | AQ46: =_xlfn.CONCAT(AP46,"_","TR","_",Tab_4.DISP_INEX[[#This Row],[FORNECEDOR]]) -> 42_TR_Mindworks - Tecnologia e Treinamento Ltda | AR46: =_xlfn.CONCAT(AP46,"_","JUST","_",Tab_4.DISP_INEX[[#This Row],[FORNECEDOR]]) -> 42_JUST_Mindworks - Tecnologia e Treinamento Ltda | AS46: =_xlfn.CONCAT(AP46,"_","RAT","_",Tab_4.DISP_INEX[[#This Row],[FORNECEDOR]]) -> 42_RAT_Mindworks - Tecnologia e Treinamento Ltda
B47: 45630 | C47: FRANCIELE | D47: FINALIZADO | E47: FINALIZADO | F47: TLB-PRO-2024/06390 | G47: 2000-DAFRI | H47: GGP | I47: Serviços | J47: Treinamento Executivo - Risk University Imersão | K47: Inexigibilidade | L47: ADMINISTRATIVO | M47: KPMG ASSURANCE SERVICES LTDA | N47: 06.240.429/0007-28 | O47: Nota de Empenho | P47: 2024NE001110 | Q47: 2024NE001110 | R47: TLB-ASS-2024/17057 | S47: 45632 | T47: 45636 | U47: 45636 | V47: 22066 | W47: TLB-DEG-2024/00144 | X47: ADRYANA RAMOS DE OLIVEIRA | Y47: PÚBLICO | Z47: 10015075 | AA47: 10004221 | AB47: 2024NE001110 | AC47: 45630 | AD47: =NETWORKDAYS.INTL(Tab_4.DISP_INEX[[#This Row],[DATA RECEBIDO]],Tab_4.DISP_INEX[[#This Row],[DATA FINALIZADO]],1,Lista!$U$3:$U$15) -> 1 | AE47: FRANCIELE | AF47: CAPACITAÇÃO | AJ47: https://www.telebras.com.br/wp-content/uploads/2025/02/81.2024NE001110-KPMG-ASSURANCE-SERVICES-LTDA.pdf | AK47: - | AL47: - | AM47: - | AP47: 43 | AQ47: =_xlfn.CONCAT(AP47,"_","TR","_",Tab_4.DISP_INEX[[#This Row],[FORNECEDOR]]) -> 43_TR_KPMG ASSURANCE SERVICES LTDA | AR47: =_xlfn.CONCAT(AP47,"_","JUST","_",Tab_4.DISP_INEX[[#This Row],[FORNECEDOR]]) -> 43_JUST_KPMG ASSURANCE SERVICES LTDA | AS47: =_xlfn.CONCAT(AP47,"_","RAT","_",Tab_4.DISP_INEX[[#This Row],[FORNECEDOR]]) -> 43_RAT_KPMG ASSURANCE SERVICES LTDA
B48: 45630 | C48: FRANCIELE | D48: FINALIZADO | E48: FINALIZADO | F48: TLB-PRO-2024/06363 | G48: 2000-DAFRI | H48: GGP | I48: Serviços | J48: Treinamento: Habilidades de T&D | K48: Inexigibilidade | L48: ADMINISTRATIVO | M48: ABTD ASSOCIAÇÃO BRASILEIRA DE TREINAMENTO | N48: 43.730.787/0001-50 | O48: Nota de Empenho | P48: 2024NE001109 | Q48: 2024NE001109 | R48: 2024NE001109 | S48: 45632 | T48: 45636 | U48: 45636 | V48: 2480 | W48: TLB-DEG-2024/00147 | X48: ADRYANA RAMOS DE OLIVEIRA | Y48: PÚBLICO | Z48: 10015246 | AA48: 10004145 | AB48: 2024NE001109 | AC48: 45630 | AD48: =NETWORKDAYS.INTL(Tab_4.DISP_INEX[[#This Row],[DATA RECEBIDO]],Tab_4.DISP_INEX[[#This Row],[DATA FINALIZADO]],1,Lista!$U$3:$U$15) -> 1 | AE48: FRANCIELE | AF48: CAPACITAÇÃO | AJ48: https://www.telebras.com.br/wp-content/uploads/2025/02/82.2024NE001109-ABTD-ASSOCIACAO-BRASILEIRA-DE-TREINAMENTO_6.pdf | AK48: - | AL48: - | AM48: - | AP48: 44 | AQ48: =_xlfn.CONCAT(AP48,"_","TR","_",Tab_4.DISP_INEX[[#This Row],[FORNECEDOR]]) -> 44_TR_ABTD ASSOCIAÇÃO BRASILEIRA DE TREINAMENTO | AR48: =_xlfn.CONCAT(AP48,"_","JUST","_",Tab_4.DISP_INEX[[#This Row],[FORNECEDOR]]) -> 44_JUST_ABTD ASSOCIAÇÃO BRASILEIRA DE TREINAMENTO | AS48: =_xlfn.CONCAT(AP48,"_","RAT","_",Tab_4.DISP_INEX[[#This Row],[FORNECEDOR]]) -> 44_RAT_ABTD ASSOCIAÇÃO BRASILEIRA DE TREINAMENTO
B49: 45639 | C49: FRANCIELE | D49: FINALIZADO | E49: FINALIZADO | F49: TLB-PRO-2024/06341 | G49: 2000-DAFRI | H49: GGP | I49: Serviços | J49: Treinamento e Certificação CISSP - Certified Information Systems Security Professional | K49: Inexigibilidade | L49: ADMINISTRATIVO | M49: KA SOLUTION INFORMÁTICA LTDA | N49: 04.527.228/0001-95 | O49: Nota de Empenho | P49: 2024NE001137 | Q49: 2024NE001137 | R49: 2024NE001137 | S49: 45643 | T49: 45644 | U49: 45644 | V49: 13234.53 | W49: TLB-DEG-2024/00150 | X49: ADRYANA RAMOS DE OLIVEIRA | Y49: PÚBLICO | Z49: 10015254 | AA49: 10004227 | AB49: 2024NE001137 | AC49: 45642 | AD49: =NETWORKDAYS.INTL(Tab_4.DISP_INEX[[#This Row],[DATA RECEBIDO]],Tab_4.DISP_INEX[[#This Row],[DATA FINALIZADO]],1,Lista!$U$3:$U$15) -> 2 | AE49: FRANCIELE | AF49: CAPACITAÇÃO | AJ49: https://www.telebras.com.br/wp-content/uploads/2025/02/83.2024NE001137-KA-SOLUTION-INFORMATICA-LTDA_7.pdf | AK49: - | AL49: - | AM49: - | AP49: 45 | AQ49: =_xlfn.CONCAT(AP49,"_","TR","_",Tab_4.DISP_INEX[[#This Row],[FORNECEDOR]]) -> 45_TR_KA SOLUTION INFORMÁTICA LTDA | AR49: =_xlfn.CONCAT(AP49,"_","JUST","_",Tab_4.DISP_INEX[[#This Row],[FORNECEDOR]]) -> 45_JUST_KA SOLUTION INFORMÁTICA LTDA | AS49: =_xlfn.CONCAT(AP49,"_","RAT","_",Tab_4.DISP_INEX[[#This Row],[FORNECEDOR]]) -> 45_RAT_KA SOLUTION INFORMÁTICA LTDA
B50: 45643 | C50: LAYLLAH | D50: FINALIZADO | E50: FINALIZADO | F50: TLB-PRO-2024/06558 | G50: 3000-DTO | H50: GTI | I50: Informática (TIC) | J50: Contratação de empresa especializada para fornecimento de suporte e garantia de switches Dell. | K50: Inexigibilidade | L50: ADMINISTRATIVO | M50: DELL COMPUTADORES DO BRASIL LTDA | N50: 72.381.189/0001-10 | O50: Contrato | P50: 2025NE000026 | Q50: TLB-CTR-2025/00023 | R50: TLB-AUT-2025/05769 | S50: 45743 | T50: 45743 | U50: 46407 | V50: 122605 | W50: TLB-DEG-2025/00058 | X50: Elias Rodrigues da Silva | Y50: PÚBLICO | Z50: 10015280 | AA50: 10003170 | AB50: 4400003080﻿ | AC50: =TODAY() -> 46190 | AD50: =NETWORKDAYS.INTL(Tab_4.DISP_INEX[[#This Row],[DATA RECEBIDO]],Tab_4.DISP_INEX[[#This Row],[DATA FINALIZADO]],1,Lista!$U$3:$U$15) -> 391 | AG50: 925150 - 9/2025 | AH50: 37753638000103-1-000027/2025 | AI50: SIM | AJ50: https://www.telebras.com.br/wp-content/uploads/2025/04/4.TLB-CTR-2025.00023-DELL-COMPUTADORES-DO-BRASIL-LTDA.pdf | AK50: - | AL50: - | AM50: - | AP50: 46 | AQ50: =_xlfn.CONCAT(AP50,"_","TR","_",Tab_4.DISP_INEX[[#This Row],[FORNECEDOR]]) -> 46_TR_DELL COMPUTADORES DO BRASIL LTDA | AR50: =_xlfn.CONCAT(AP50,"_","JUST","_",Tab_4.DISP_INEX[[#This Row],[FORNECEDOR]]) -> 46_JUST_DELL COMPUTADORES DO BRASIL LTDA | AS50: =_xlfn.CONCAT(AP50,"_","RAT","_",Tab_4.DISP_INEX[[#This Row],[FORNECEDOR]]) -> 46_RAT_DELL COMPUTADORES DO BRASIL LTDA
B51: 45649 | C51: LAYLLAH | D51: FINALIZADO | E51: FINALIZADO | F51: TLB-PRO-2024/05271 | G51: 3000-DTO | H51: GTI | I51: Informática (TIC) | J51: Contratação de empresa especializada para fornecimento de suporte e garantia de servidores Dell. | K51: Inexigibilidade | L51: ADMINISTRATIVO | M51: DELL COMPUTADORES DO BRASIL LTDA | N51: 72.381.189/0001-10 | O51: Contrato | P51: 2025NE000449 | Q51: TLB-CTR-2025/00022 | R51: TLB-AUT-2025/05781 | S51: 45743 | T51: 45743 | U51: 45947 | V51: 53604 | W51: TLB-DEG-2025/00057 | X51: Elias Rodrigues da Silva | Y51: PÚBLICO | Z51: 10015262 | AA51: 10003170 | AB51: 4400003079 | AC51: =TODAY() -> 46190 | AD51: =NETWORKDAYS.INTL(Tab_4.DISP_INEX[[#This Row],[DATA RECEBIDO]],Tab_4.DISP_INEX[[#This Row],[DATA FINALIZADO]],1,Lista!$U$3:$U$15) -> 387 | AG51: 925150 - 10/2025 | AH51: 37753638000103-1-000028/2025 | AI51: SIM | AJ51: https://www.telebras.com.br/wp-content/uploads/2025/04/5.TLB-CTR-2025.00022-DELL-COMPUTADORES-DO-BRASIL-LTDA.pdf | AK51: - | AL51: - | AM51: - | AP51: 47 | AQ51: =_xlfn.CONCAT(AP51,"_","TR","_",Tab_4.DISP_INEX[[#This Row],[FORNECEDOR]]) -> 47_TR_DELL COMPUTADORES DO BRASIL LTDA | AR51: =_xlfn.CONCAT(AP51,"_","JUST","_",Tab_4.DISP_INEX[[#This Row],[FORNECEDOR]]) -> 47_JUST_DELL COMPUTADORES DO BRASIL LTDA | AS51: =_xlfn.CONCAT(AP51,"_","RAT","_",Tab_4.DISP_INEX[[#This Row],[FORNECEDOR]]) -> 47_RAT_DELL COMPUTADORES DO BRASIL LTDA
B52: 45723 | C52: FRANCIELE | D52: FINALIZADO | E52: FINALIZADO | F52: TLB-PRO-2025/00933 | G52: 2000-DAFRI | H52: GCC | I52: Serviços | J52: Contratação da Capacitação - Inteligência Artificial Apliacada às Contratações Públicas | K52: Inexigibilidade | L52: ADMINISTRATIVO | M52: Zênite Informação e Consultoria S/A | N52: 86.781.069/0001-15 | O52: Nota de Empenho | P52: 2025NE000539 | Q52: 2025NE000539 | R52: 2025NE000539 | S52: 45727 | T52: 45729 | U52: 45744 | V52: 4860 | W52: TLB-DEG-2025/00035 | X52: ROSILDA ABREU DA SILVA | Y52: PÚBLICO | Z52: 10015557 | AA52: 10001269 | AC52: 45726 | AD52: =NETWORKDAYS.INTL(Tab_4.DISP_INEX[[#This Row],[DATA RECEBIDO]],Tab_4.DISP_INEX[[#This Row],[DATA FINALIZADO]],1,Lista!$U$3:$U$15) -> 2 | AE52: FRANCIELE | AF52: CAPACITAÇÃO | AG52: 925150 - 3/2025 | AH52: 37753638000103-1-000021/2025 | AI52: SIM | AJ52: https://www.telebras.com.br/wp-content/uploads/2025/04/2.2025NE000539-Zenite-Informacao-e-Consultoria.A.pdf | AK52: - | AL52: - | AM52: - | AP52: 48 | AQ52: =_xlfn.CONCAT(AP52,"_","TR","_",Tab_4.DISP_INEX[[#This Row],[FORNECEDOR]]) -> 48_TR_Zênite Informação e Consultoria S/A | AR52: =_xlfn.CONCAT(AP52,"_","JUST","_",Tab_4.DISP_INEX[[#This Row],[FORNECEDOR]]) -> 48_JUST_Zênite Informação e Consultoria S/A | AS52: =_xlfn.CONCAT(AP52,"_","RAT","_",Tab_4.DISP_INEX[[#This Row],[FORNECEDOR]]) -> 48_RAT_Zênite Informação e Consultoria S/A
B53: 45735 | C53: FRANCIELE | D53: FINALIZADO | E53: FINALIZADO | F53: TLB-PRO-2025/01070 | G53: 2000-DAFRI | H53: GCC | I53: Serviços | J53: Contratação da Capacitação - Pesquisa de Preços para Contratações Públicas com o uso de Inteligência Artificial | K53: Inexigibilidade | L53: ADMINISTRATIVO | M53: Inove Treinamentos e Capacitação Ltda | N53: 50.088.618/0001-23 | O53: Nota de Empenho | P53: 2025NE000572 | Q53: 2025NE000572 | R53: 2025NE000572 | S53: 45742 | T53: 45743 | U53: 45743 | V53: 1990 | W53: TLB-DEG-2025/00049 | X53: FRANCIELE FERREIRA DA SILVA | Y53: PÚBLICO | Z53: 10015602 | AA53: 10004236 | AC53: 45735 | AD53: =NETWORKDAYS.INTL(Tab_4.DISP_INEX[[#This Row],[DATA RECEBIDO]],Tab_4.DISP_INEX[[#This Row],[DATA FINALIZADO]],1,Lista!$U$3:$U$15) -> 1 | AE53: FRANCIELE | AF53: CAPACITAÇÃO | AG53: 925150 - 4/2025 | AH53: 37753638000103-1-000022/2025 | AI53: SIM | AJ53: https://www.telebras.com.br/wp-content/uploads/2025/04/3.2025NE000572-Inove-Treinamentos-e-Capacitacao-Ltda.pdf | AK53: - | AL53: - | AM53: - | AP53: 49 | AQ53: =_xlfn.CONCAT(AP53,"_","TR","_",Tab_4.DISP_INEX[[#This Row],[FORNECEDOR]]) -> 49_TR_Inove Treinamentos e Capacitação Ltda | AR53: =_xlfn.CONCAT(AP53,"_","JUST","_",Tab_4.DISP_INEX[[#This Row],[FORNECEDOR]]) -> 49_JUST_Inove Treinamentos e Capacitação Ltda | AS53: =_xlfn.CONCAT(AP53,"_","RAT","_",Tab_4.DISP_INEX[[#This Row],[FORNECEDOR]]) -> 49_RAT_Inove Treinamentos e Capacitação Ltda
B54: 45673 | C54: LAYLLAH | D54: FINALIZADO | E54: FINALIZADO | F54: TLB-PRO-2024/06004 | G54: 5000-DG | H54: GIRC | I54: Serviços | J54: Associação da Telebras ao Instituto Brasileiro de Governança Corporativa - IBGC | K54: Inexigibilidade | L54: ADMINISTRATIVO | M54: Instituto Brasileiro de Governança Corporativa - IBGC | N54: 01.082.331/0001-80 | O54: Nota de Empenho | P54: 2025NE000538 | Q54: 2025NE000538 | R54: TLB-AUT-2025/04867 | S54: 45734 | T54: 45734 | U54: 46099 | V54: 23474 | W54: TLB-DEG-2025/00041 | X54: ANTÔNIO CELSON DE JESUS NERIS | Y54: PÚBLICO | Z54: 10015394 | AC54: =TODAY() -> 46190 | AD54: =NETWORKDAYS.INTL(Tab_4.DISP_INEX[[#This Row],[DATA RECEBIDO]],Tab_4.DISP_INEX[[#This Row],[DATA FINALIZADO]],1,Lista!$U$3:$U$15) -> 370 | AG54: 925150 - 2/2025 | AH54: 37753638000103-1-000020/2025 | AI54: SIM | AJ54: https://www.telebras.com.br/wp-content/uploads/2025/04/1.2025NE000538-Instituto-Brasileiro-de-Governanca-Corporativa-IBGC.pdf | AK54: - | AL54: - | AM54: - | AP54: 50 | AQ54: =_xlfn.CONCAT(AP54,"_","TR","_",Tab_4.DISP_INEX[[#This Row],[FORNECEDOR]]) -> 50_TR_Instituto Brasileiro de Governança Corporativa - IBGC | AR54: =_xlfn.CONCAT(AP54,"_","JUST","_",Tab_4.DISP_INEX[[#This Row],[FORNECEDOR]]) -> 50_JUST_Instituto Brasileiro de Governança Corporativa - IBGC | AS54: =_xlfn.CONCAT(AP54,"_","RAT","_",Tab_4.DISP_INEX[[#This Row],[FORNECEDOR]]) -> 50_RAT_Instituto Brasileiro de Governança Corporativa - IBGC
B55: 45674 | C55: ROSILDA | D55: FINALIZADO | E55: FINALIZADO | F55: TLB-PRO-2024/06151 | G55: 2000-DAFRI | H55: GGP | I55: Compras | J55: Aquisição de impressora de cartão PVC/crachá para a Telebras. | K55: Dispensa | L55: ADMINISTRATIVO | M55: SC BRASIL GROUP SOLUÇÕES TECNOLÓGICAS LTDA | N55: 43.478.505/0001-79 | O55: Contrato | P55: 2025NE000544 | Q55: TLB-CTR-2025/00024 | R55: TLB-AUT-2025/05744-A | S55: 45744 | T55: 45744 | U55: 46109 | V55: 6500 | W55: TLB-DEG-2025/00055-A | X55: MARIA JOSÉ QUINTAS | Y55: PÚBLICO | Z55: 10015239 | AC55: 45761 | AD55: =NETWORKDAYS.INTL(Tab_4.DISP_INEX[[#This Row],[DATA RECEBIDO]],Tab_4.DISP_INEX[[#This Row],[DATA FINALIZADO]],1,Lista!$U$3:$U$15) -> 62 | AE55: DANIEL PENALVA | AG55: 90002/2025 | AH55: 37753638000103-1-000008/2025 | AI55: SIM | AJ55: https://www.telebras.com.br/wp-content/uploads/2025/04/11.TLB-CTR-2025.00024-SC-BRASIL-GROUP-SOLUCOES-TECNOLOGICAS-LTDA.pdf | AK55: - | AL55: - | AM55: - | AP55: 51 | AQ55: =_xlfn.CONCAT(AP55,"_","TR","_",Tab_4.DISP_INEX[[#This Row],[FORNECEDOR]]) -> 51_TR_SC BRASIL GROUP SOLUÇÕES TECNOLÓGICAS LTDA | AR55: =_xlfn.CONCAT(AP55,"_","JUST","_",Tab_4.DISP_INEX[[#This Row],[FORNECEDOR]]) -> 51_JUST_SC BRASIL GROUP SOLUÇÕES TECNOLÓGICAS LTDA | AS55: =_xlfn.CONCAT(AP55,"_","RAT","_",Tab_4.DISP_INEX[[#This Row],[FORNECEDOR]]) -> 51_RAT_SC BRASIL GROUP SOLUÇÕES TECNOLÓGICAS LTDA
B56: 45756 | C56: FRANCIELE | D56: FINALIZADO | E56: FINALIZADO | F56: TLB-PRO-2024/06219 | G56: 2000-DAFRI | H56: GGP | I56: Serviços | J56: Treinamento - Environmental, Social & Governance (ESG) | K56: Inexigibilidade | L56: ADMINISTRATIVO | M56: KPMG Business School |Treinamentos Corporativos | N56: 05.490.840/0001-01 | O56: Nota de Empenho | P56: 2025NE000608 | Q56: 2025NE000608 | R56: 2025NE000608 | S56: 45761 | T56: 45762 | U56: 45762 | V56: 5860 | W56: TLB-DEG-2025/00060 | X56: Camila Daniela Lima | Y56: PÚBLICO | Z56: 10015636 | AA56: 10003773 | AC56: 45758 | AD56: =NETWORKDAYS.INTL(Tab_4.DISP_INEX[[#This Row],[DATA RECEBIDO]],Tab_4.DISP_INEX[[#This Row],[DATA FINALIZADO]],1,Lista!$U$3:$U$15) -> 3 | AE56: FRANCIELE | AF56: CAPACITAÇÃO | AG56: 925150 - 6/2025 | AH56: 37753638000103-1-000024/2025 | AI56: SIM | AJ56: https://www.telebras.com.br/wp-content/uploads/2025/05/6.2025NE000608-KPMG-Business-School-Treinamentos-Corporativos.pdf | AK56: - | AL56: - | AM56: - | AP56: 52 | AQ56: =_xlfn.CONCAT(AP56,"_","TR","_",Tab_4.DISP_INEX[[#This Row],[FORNECEDOR]]) -> 52_TR_KPMG Business School |Treinamentos Corporativos | AR56: =_xlfn.CONCAT(AP56,"_","JUST","_",Tab_4.DISP_INEX[[#This Row],[FORNECEDOR]]) -> 52_JUST_KPMG Business School |Treinamentos Corporativos | AS56: =_xlfn.CONCAT(AP56,"_","RAT","_",Tab_4.DISP_INEX[[#This Row],[FORNECEDOR]]) -> 52_RAT_KPMG Business School |Treinamentos Corporativos
B57: 45756 | C57: FRANCIELE | D57: FINALIZADO | E57: FINALIZADO | F57: TLB-PRO-2025/01806 | G57: 2000-DAFRI | H57: GGP | I57: Serviços | J57: Curso Preparatório PMP | K57: Inexigibilidade | L57: ADMINISTRATIVO | M57: MODERNPMO GESTAO E TECNOLOGIA LTDA GESTAO E TECNOLOGIA LTDA | N57: 21.268.624/0001-64 | O57: Nota de Empenho | P57: 2025NE000607 | Q57: 2025NE000607 | R57: 2025NE000607 | S57: 45762 | T57: 45762 | U57: 45762 | V57: 2247 | W57: TLB-DEG-2025/00061 | X57: Camila Daniela Lima | Y57: PÚBLICO | Z57: 10015655 | AA57: 10004280 | AC57: 45757 | AD57: =NETWORKDAYS.INTL(Tab_4.DISP_INEX[[#This Row],[DATA RECEBIDO]],Tab_4.DISP_INEX[[#This Row],[DATA FINALIZADO]],1,Lista!$U$3:$U$15) -> 2 | AE57: FRANCIELE | AF57: CAPACITAÇÃO | AG57: 925150 - 7/2025 | AH57: 37753638000103-1-000025/2025 | AI57: SIM | AJ57: https://www.telebras.com.br/wp-content/uploads/2025/05/7.2025NE000607-MODERNPMO-GESTAO-E-TECNOLOGIA-LTDA-GESTAO-E-TECNOLOGIA-LTDA.pdf | AK57: - | AL57: - | AM57: - | AP57: 53 | AQ57: =_xlfn.CONCAT(AP57,"_","TR","_",Tab_4.DISP_INEX[[#This Row],[FORNECEDOR]]) -> 53_TR_MODERNPMO GESTAO E TECNOLOGIA LTDA GESTAO E TECNOLOGIA LTDA | AR57: =_xlfn.CONCAT(AP57,"_","JUST","_",Tab_4.DISP_INEX[[#This Row],[FORNECEDOR]]) -> 53_JUST_MODERNPMO GESTAO E TECNOLOGIA LTDA GESTAO E TECNOLOGIA LTDA | AS57: =_xlfn.CONCAT(AP57,"_","RAT","_",Tab_4.DISP_INEX[[#This Row],[FORNECEDOR]]) -> 53_RAT_MODERNPMO GESTAO E TECNOLOGIA LTDA GESTAO E TECNOLOGIA LTDA
B58: 45756 | C58: FRANCIELE | D58: FINALIZADO | E58: FINALIZADO | F58: TLB-PRO-2025/01053 | G58: 2000-DAFRI | H58: GGP | I58: Serviços | J58: Capacitação interna - Modelagem Financeira | K58: Inexigibilidade | L58: ADMINISTRATIVO | M58: A. F. Comércio de Livros e Cursos Especializados Ltda | N58: 06.336.797/0001-89 | O58: Nota de Empenho | P58: 2025NE000610 | Q58: 2025NE000610 | R58: 2025NE000610 | S58: 45762 | T58: 45763 | U58: 45763 | V58: 7180.8 | W58: TLB-DEG-2025/00062 | X58: Camila Daniela Lima | Y58: PÚBLICO | Z58: 10015603 | AA58: 10004237 | AC58: 45761 | AD58: =NETWORKDAYS.INTL(Tab_4.DISP_INEX[[#This Row],[DATA RECEBIDO]],Tab_4.DISP_INEX[[#This Row],[DATA FINALIZADO]],1,Lista!$U$3:$U$15) -> 4 | AE58: FRANCIELE | AF58: CAPACITAÇÃO | AG58: 925150 - 8/2025 | AH58: 37753638000103-1-000026/2025 | AI58: SIM | AJ58: https://www.telebras.com.br/wp-content/uploads/2025/05/8.2025NE000610-FK-PARTNERS.pdf | AK58: - | AL58: - | AM58: - | AP58: 54 | AQ58: =_xlfn.CONCAT(AP58,"_","TR","_",Tab_4.DISP_INEX[[#This Row],[FORNECEDOR]]) -> 54_TR_A. F. Comércio de Livros e Cursos Especializados Ltda | AR58: =_xlfn.CONCAT(AP58,"_","JUST","_",Tab_4.DISP_INEX[[#This Row],[FORNECEDOR]]) -> 54_JUST_A. F. Comércio de Livros e Cursos Especializados Ltda | AS58: =_xlfn.CONCAT(AP58,"_","RAT","_",Tab_4.DISP_INEX[[#This Row],[FORNECEDOR]]) -> 54_RAT_A. F. Comércio de Livros e Cursos Especializados Ltda
B59: 45749 | C59: FRANCIELE | D59: FINALIZADO | E59: FINALIZADO | F59: TLB-PRO-2025/01408 | G59: 2000-DAFRI | H59: GCC | I59: Serviços | J59: Contratação de assinatura anual dos produtos de suporte jurídico à administração referente às contratações públicas: Zênite Fácil - Estatais e Zênite Fácil Inteligência Artificial - ZIÁ, que é a assistente de pesquisa do Zênite Fácil - Estatais que utiliza IA generativa. | K59: Inexigibilidade | L59: ADMINISTRATIVO | M59: Zênite Informação e Consultoria S/A | N59: 86.781.069/0001-15 | O59: Nota de Empenho | P59: 2025NE000588 | Q59: 2025NE000588 | R59: 2025NE000588 | S59: 45751 | T59: 45751 | U59: 46116 | V59: 15546 | W59: TLB-DEG-2025/00056 | X59: Rosilda Abreu da Silva | Y59: PÚBLICO | Z59: 10015623 | AA59: 10001269 | AC59: 45749 | AD59: =NETWORKDAYS.INTL(Tab_4.DISP_INEX[[#This Row],[DATA RECEBIDO]],Tab_4.DISP_INEX[[#This Row],[DATA FINALIZADO]],1,Lista!$U$3:$U$15) -> 1 | AE59: FRANCIELE | AF59: ASSINATURA | AG59: 925150-1/2025 | AH59: 37753638000103-1-000019/2025 | AI59: SIM | AJ59: https://www.telebras.com.br/wp-content/uploads/2025/04/4.2025NE000588-Zenite-Informacao-e-Consultoria-SA.pdf | AK59: - | AL59: - | AM59: - | AP59: 55 | AQ59: =_xlfn.CONCAT(AP59,"_","TR","_",Tab_4.DISP_INEX[[#This Row],[FORNECEDOR]]) -> 55_TR_Zênite Informação e Consultoria S/A | AR59: =_xlfn.CONCAT(AP59,"_","JUST","_",Tab_4.DISP_INEX[[#This Row],[FORNECEDOR]]) -> 55_JUST_Zênite Informação e Consultoria S/A | AS59: =_xlfn.CONCAT(AP59,"_","RAT","_",Tab_4.DISP_INEX[[#This Row],[FORNECEDOR]]) -> 55_RAT_Zênite Informação e Consultoria S/A
B60: 45785 | C60: FRANCIELE | D60: FINALIZADO | E60: FINALIZADO | F60: TLB-PRO-2025/01052 | G60: 2000-DAFRI | H60: GGP | I60: Serviços | J60: Capacitação "Análise de Viabilidade de Projetos". | K60: Inexigibilidade | L60: ADMINISTRATIVO | M60: A. F. Comércio de Livros e Cursos Especializados Ltda | N60: 06.336.797/0001-89 | O60: Nota de Empenho | P60: 2025NE000690 | Q60: 2025NE000690 | R60: 2025NE000690 | S60: 45786 | T60: 45786 | U60: 45786 | V60: 19000 | W60: TLB-DEG-2025/00066 | X60: Camila Daniela Lima | Y60: PÚBLICO | Z60: 10015687 | AA60: 10004237 | AC60: 45785 | AD60: =NETWORKDAYS.INTL(Tab_4.DISP_INEX[[#This Row],[DATA RECEBIDO]],Tab_4.DISP_INEX[[#This Row],[DATA FINALIZADO]],1,Lista!$U$3:$U$15) -> 1 | AE60: FRANCIELE | AF60: CAPACITAÇÃO | AG60: 925150 - 12/2025 | AH60: 37753638000103-1-000032/2025 | AI60: SIM | AJ60: https://www.telebras.com.br/wp-content/uploads/2025/06/9.2025NE000690-A.-F.-Comercio-de-Livros-e-Cursos-Especializados-Ltda.pdf | AK60: - | AL60: - | AM60: - | AP60: 56 | AQ60: =_xlfn.CONCAT(AP60,"_","TR","_",Tab_4.DISP_INEX[[#This Row],[FORNECEDOR]]) -> 56_TR_A. F. Comércio de Livros e Cursos Especializados Ltda | AR60: =_xlfn.CONCAT(AP60,"_","JUST","_",Tab_4.DISP_INEX[[#This Row],[FORNECEDOR]]) -> 56_JUST_A. F. Comércio de Livros e Cursos Especializados Ltda | AS60: =_xlfn.CONCAT(AP60,"_","RAT","_",Tab_4.DISP_INEX[[#This Row],[FORNECEDOR]]) -> 56_RAT_A. F. Comércio de Livros e Cursos Especializados Ltda
B61: 45671 | C61: LAYLLAH | D61: FINALIZADO | E61: FINALIZADO | F61: TLB-PRO-2024/05944 | G61: 2000-DAFRI | H61: GCONT | I61: Serviços | J61: Contratação de empresa especializada na prestação de serviços de informações e pesquisa no âmbito fiscal, trabalhista, previdenciário, contábil, auditoria e societário. | K61: Dispensa | L61: ADMINISTRATIVO | M61: LEGIS JET LTDA | N61: 27.188.971/0001-63 | O61: Contrato | P61: 2025NE000532 | Q61: TLB-CTR-2025/00017 | R61: TLB-AUT-2025/04884 | S61: 45734 | T61: 45748 | U61: 46843 | V61: 29500 | W61: TLB-DEG-2025/00048 | X61: ANNA PAULA PEDROSA VIEIRA | Y61: PÚBLICO | Z61: 10015424 | AC61: 45686 | AD61: =NETWORKDAYS.INTL(Tab_4.DISP_INEX[[#This Row],[DATA RECEBIDO]],Tab_4.DISP_INEX[[#This Row],[DATA FINALIZADO]],1,Lista!$U$3:$U$15) -> 12 | AG61: 90001/2025 | AH61: 37753638000103-1-000007/2025 | AI61: SIM | AJ61: https://www.telebras.com.br/wp-content/uploads/2025/04/9.TLB-CTR-2025.00017-LEGIS-JET-LTDA.pdf | AK61: - | AL61: - | AM61: - | AP61: 57 | AQ61: =_xlfn.CONCAT(AP61,"_","TR","_",Tab_4.DISP_INEX[[#This Row],[FORNECEDOR]]) -> 57_TR_LEGIS JET LTDA | AR61: =_xlfn.CONCAT(AP61,"_","JUST","_",Tab_4.DISP_INEX[[#This Row],[FORNECEDOR]]) -> 57_JUST_LEGIS JET LTDA | AS61: =_xlfn.CONCAT(AP61,"_","RAT","_",Tab_4.DISP_INEX[[#This Row],[FORNECEDOR]]) -> 57_RAT_LEGIS JET LTDA
B62: 45754 | C62: LUCIANA | D62: FINALIZADO | E62: FINALIZADO | F62: TLB-PRO-2025/01643 | G62: 4000-DC | H62: GPM | I62: Serviços | J62: Participação da Telebras, por meio de ação promocional, no Evento Abrint Global Congress 2025, organizado exclusivamente pela Abrint - Associação Brasileira de Provedores de Internet. O evento ocorrerá no Anhembi, em São Paulo, de 07 a 09 de maio de 2025. | K62: Inexigibilidade | L62: ADMINISTRATIVO | M62: ABRINT | N62: 11.369.542/0001-52 | O62: Contrato de Adesão | P62: 2025NE000613 | Q62: TermodeAdesãonº04720000 | R62: TLB-AUT-2025/06589 | S62: 45764 | T62: 45764 | U62: 45786 | V62: 180470.65 | W62: TLB-DEG-2025/00075 | X62: Mariana Rodrigues Boavista Leite | Y62: PÚBLICO | Z62: 10015625 | AC62: =TODAY() -> 46190 | AD62: =NETWORKDAYS.INTL(Tab_4.DISP_INEX[[#This Row],[DATA RECEBIDO]],Tab_4.DISP_INEX[[#This Row],[DATA FINALIZADO]],1,Lista!$U$3:$U$15) -> 313 | AG62: 925150 - 5/2025 | AH62: 37753638000103-1-000023/2025 | AI62: SIM | AJ62: https://www.telebras.com.br/wp-content/uploads/2025/05/5.TA-no-04720000_2025NE000613-ABRINT.pdf | AK62: - | AL62: - | AM62: - | AP62: 58 | AQ62: =_xlfn.CONCAT(AP62,"_","TR","_",Tab_4.DISP_INEX[[#This Row],[FORNECEDOR]]) -> 58_TR_ABRINT | AR62: =_xlfn.CONCAT(AP62,"_","JUST","_",Tab_4.DISP_INEX[[#This Row],[FORNECEDOR]]) -> 58_JUST_ABRINT | AS62: =_xlfn.CONCAT(AP62,"_","RAT","_",Tab_4.DISP_INEX[[#This Row],[FORNECEDOR]]) -> 58_RAT_ABRINT
B63: 45743 | C63: ROSILDA | D63: FINALIZADO | E63: FINALIZADO | F63: TLB-PRO-2025/01491 | G63: 2000-DAFRI | H63: GJ | I63: Serviços | J63: Contratação de escritório de advocacia de notória especialização em matéria tributária. | K63: Inexigibilidade | L63: ADMINISTRATIVO | M63: SACHA CALMON - MISABEL DERZI, CONSULTORES E ADVOGADOS | N63: 00.140.626/0001-01 | O63: Contrato | P63: 2025NE809 | Q63: TLB-CTR-2025/00026 | R63: TLB-CTR-2025/00026 | S63: 45763 | T63: 45763 | U63: 47589 | V63: 5900000 | W63: TLB-DEG-2025/00064 | X63: Ezielma Braz Ferreira | Y63: PÚBLICO | Z63: 10015666 | AA63: 10004228 | AC63: =TODAY() -> 46190 | AD63: =NETWORKDAYS.INTL(Tab_4.DISP_INEX[[#This Row],[DATA RECEBIDO]],Tab_4.DISP_INEX[[#This Row],[DATA FINALIZADO]],1,Lista!$U$3:$U$15) -> 320 | AG63: 925150 - 11/2025 | AH63: 37753638000103-1-000029/2025 | AI63: SIM | AJ63: https://www.telebras.com.br/wp-content/uploads/2025/05/12.TLB-CTR-2025.00026-SACHA-CALMON-MISABEL-DERZI-CONSULTORES-E-ADVOGADOS.pdf | AK63: - | AL63: - | AM63: - | AP63: 59 | AQ63: =_xlfn.CONCAT(AP63,"_","TR","_",Tab_4.DISP_INEX[[#This Row],[FORNECEDOR]]) -> 59_TR_SACHA CALMON - MISABEL DERZI, CONSULTORES E ADVOGADOS | AR63: =_xlfn.CONCAT(AP63,"_","JUST","_",Tab_4.DISP_INEX[[#This Row],[FORNECEDOR]]) -> 59_JUST_SACHA CALMON - MISABEL DERZI, CONSULTORES E ADVOGADOS | AS63: =_xlfn.CONCAT(AP63,"_","RAT","_",Tab_4.DISP_INEX[[#This Row],[FORNECEDOR]]) -> 59_RAT_SACHA CALMON - MISABEL DERZI, CONSULTORES E ADVOGADOS
B64: 45796 | C64: FRANCIELE | D64: FINALIZADO | E64: FINALIZADO | F64: TLB-PRO-2025/02256 | G64: 2000-DAFRI | H64: GGP | I64: Serviços | J64: Contratação da Capacitação - Programa de Imersão: Gestão Estratégica por Resultados em Licitações e Contratos | K64: Inexigibilidade | L64: ADMINISTRATIVO | M64: 3R CAPACITA COMERCIO DE MATERIAIS DIDATICOS E SERVICOS EDUCACIONAIS LTDA | N64: 32.380.894/0001-89 | O64: Nota de Empenho | P64: 2025NE000716 | Q64: 2025NE000716 | R64: 2025NE000716 | S64: 45800 | T64: 45803 | U64: 45803 | V64: 8250 | W64: TLB-DEG-2025/00074 | X64: Rosilda Abreu da Silva | Y64: PÚBLICO | Z64: 10015696 | AA64: 10004243 | AC64: 45796 | AD64: =NETWORKDAYS.INTL(Tab_4.DISP_INEX[[#This Row],[DATA RECEBIDO]],Tab_4.DISP_INEX[[#This Row],[DATA FINALIZADO]],1,Lista!$U$3:$U$15) -> 1 | AE64: FRANCIELE | AF64: CAPACITAÇÃO | AG64: 925150 - 13/2025 | AH64: 37753638000103-1-000033/2025 | AI64: SIM | AJ64: https://www.telebras.com.br/wp-content/uploads/2025/06/10.2025NE000716-3R-CAPACITA-COMERCIO-DE-MATERIAIS-DIDATICOS-E-SERVICOS-EDUCACIONAIS-LTDA.pdf | AK64: - | AL64: - | AM64: - | AP64: 60 | AQ64: =_xlfn.CONCAT(AP64,"_","TR","_",Tab_4.DISP_INEX[[#This Row],[FORNECEDOR]]) -> 60_TR_3R CAPACITA COMERCIO DE MATERIAIS DIDATICOS E SERVICOS EDUCACIONAIS LTDA | AR64: =_xlfn.CONCAT(AP64,"_","JUST","_",Tab_4.DISP_INEX[[#This Row],[FORNECEDOR]]) -> 60_JUST_3R CAPACITA COMERCIO DE MATERIAIS DIDATICOS E SERVICOS EDUCACIONAIS LTDA | AS64: =_xlfn.CONCAT(AP64,"_","RAT","_",Tab_4.DISP_INEX[[#This Row],[FORNECEDOR]]) -> 60_RAT_3R CAPACITA COMERCIO DE MATERIAIS DIDATICOS E SERVICOS EDUCACIONAIS LTDA
B65: 45810 | C65: FRANCIELE | D65: FINALIZADO | E65: FINALIZADO | F65: TLB-PRO-2025/02561 | G65: 2000-DAFRI | H65: GGP | I65: Serviços | J65: Contratação da Capacitação ISO 31000:2018 - Capacitação em Gestão de Riscos | K65: Inexigibilidade | L65: ADMINISTRATIVO | M65: QSP - CENTRO DA QUALIDADE, SEGURANCA E PRODUTIVIDADE PARA O BRASIL E AMERICA LATINA | N65: 67.634.022/0001-84 | O65: Nota de Empenho | P65: 2025NE000761 | Q65: 2025NE000761 | R65: 2025NE000761 | S65: 45813 | T65: 45817 | U65: 45817 | V65: 10545 | W65: TLB-DEG-2025/00079 | X65: Adryana Ramos de Oliveira | Y65: PÚBLICO | Z65: 10015733 | AA65: 10004257 | AC65: 45810 | AD65: =NETWORKDAYS.INTL(Tab_4.DISP_INEX[[#This Row],[DATA RECEBIDO]],Tab_4.DISP_INEX[[#This Row],[DATA FINALIZADO]],1,Lista!$U$3:$U$15) -> 1 | AE65: FRANCIELE | AF65: CAPACITAÇÃO | AG65: 925150 - 14/2025 | AH65: 37753638000103-1-000043/2025 | AI65: SIM | AJ65: https://www.telebras.com.br/wp-content/uploads/2025/07/11.2025NE761-QSP-CENTRO-DA-QUALIDADE-SEGURANCA-E-PRODUTIVIDADE-PARA-O-BRASIL-E-AMERICA-LATINA.pdf | AK65: - | AL65: - | AM65: - | AP65: 61 | AQ65: =_xlfn.CONCAT(AP65,"_","TR","_",Tab_4.DISP_INEX[[#This Row],[FORNECEDOR]]) -> 61_TR_QSP - CENTRO DA QUALIDADE, SEGURANCA E PRODUTIVIDADE PARA O BRASIL E AMERICA LATINA | AR65: =_xlfn.CONCAT(AP65,"_","JUST","_",Tab_4.DISP_INEX[[#This Row],[FORNECEDOR]]) -> 61_JUST_QSP - CENTRO DA QUALIDADE, SEGURANCA E PRODUTIVIDADE PARA O BRASIL E AMERICA LATINA | AS65: =_xlfn.CONCAT(AP65,"_","RAT","_",Tab_4.DISP_INEX[[#This Row],[FORNECEDOR]]) -> 61_RAT_QSP - CENTRO DA QUALIDADE, SEGURANCA E PRODUTIVIDADE PARA O BRASIL E AMERICA LATINA
B66: 45807 | C66: FRANCIELE | D66: FINALIZADO | E66: FINALIZADO | F66: TLB-PRO-2025/02662 | G66: 2000-DAFRI | H66: GGP | I66: Serviços | J66: Participação da GGP no CONARH 2025- Congresso Nacional de Gestão de Pessoas | K66: Inexigibilidade | L66: ADMINISTRATIVO | M66: ABRH- Associação Brasileira de Recursos Humanos | N66: 43.456.425/0001-12 | O66: Nota de Empenho | P66: 2025NE000774 | Q66: 2025NE000774 | R66: 2025NE000774 | S66: 45817 | T66: 45817 | U66: 45818 | V66: 14700 | W66: TLB-DEG-2025/00080 | X66: Adryana Ramos de Oliveira | Y66: PÚBLICO | Z66: 10015740 | AA66: 10003939 | AC66: 45813 | AD66: =NETWORKDAYS.INTL(Tab_4.DISP_INEX[[#This Row],[DATA RECEBIDO]],Tab_4.DISP_INEX[[#This Row],[DATA FINALIZADO]],1,Lista!$U$3:$U$15) -> 5 | AE66: FRANCIELE | AF66: EVENTO | AG66: 925150 - 15/2025 | AH66: 37753638000103-1-000044/2025 | AI66: SIM | AJ66: https://www.telebras.com.br/wp-content/uploads/2025/07/12.2025NE774-ABRH-Associacao-Brasileira-de-Recursos-Humanos.pdf | AK66: - | AL66: - | AM66: - | AP66: 62 | AQ66: =_xlfn.CONCAT(AP66,"_","TR","_",Tab_4.DISP_INEX[[#This Row],[FORNECEDOR]]) -> 62_TR_ABRH- Associação Brasileira de Recursos Humanos | AR66: =_xlfn.CONCAT(AP66,"_","JUST","_",Tab_4.DISP_INEX[[#This Row],[FORNECEDOR]]) -> 62_JUST_ABRH- Associação Brasileira de Recursos Humanos | AS66: =_xlfn.CONCAT(AP66,"_","RAT","_",Tab_4.DISP_INEX[[#This Row],[FORNECEDOR]]) -> 62_RAT_ABRH- Associação Brasileira de Recursos Humanos
B67: 45841 | C67: FRANCIELE | D67: FINALIZADO | E67: FINALIZADO | F67: TLB-PRO-2025/03118 | G67: 2000-DAFRI | H67: GPM | I67: Serviços | J67: Participação da Telebras, por meio de ação promocional, no evento SECOP 2025 | K67: Inexigibilidade | L67: ADMINISTRATIVO | M67: Associação Brasileira de Entidades Estaduais e Públicas de Tecnologia da Informação e Comunicação | N67: 77.639.433/0001-16 | O67: Contrato | P67: 2025NE000885 | Q67: TLB-CTR-2025/00048 | R67: TLB-AUT-2025/12277 | S67: 45854 | T67: 45862 | U67: 46022 | V67: 109865.44 | W67: TLB-DEG-2025/00100 | X67: Mariana Rodrigues Boavista Leite | Y67: PÚBLICO | Z67: 10015778 | AA67: 10001625 | AB67: 2025NE000885 | AC67: 45841 | AD67: =NETWORKDAYS.INTL(Tab_4.DISP_INEX[[#This Row],[DATA RECEBIDO]],Tab_4.DISP_INEX[[#This Row],[DATA FINALIZADO]],1,Lista!$U$3:$U$15) -> 1 | AE67: FRANCIELE | AF67: EVENTO | AG67: 925150 - 21/2025 | AH67: 37753638000103-2-000043/2025 | AI67: SIM | AJ67: https://www.telebras.com.br/wp-content/uploads/2025/08/18.TLB-CTR-2025.00048-ASSOCIACAO-BRASILEIRA-DE-ENTIDADES-ESTADUAIS-E-PUBLICAS-DE-TECNOLOGIA-DA-INFORMACAO-E-COMUNICACAO-–-ABEP-TIC.pdf | AK67: - | AL67: - | AM67: - | AP67: 63 | AQ67: =_xlfn.CONCAT(AP67,"_","TR","_",Tab_4.DISP_INEX[[#This Row],[FORNECEDOR]]) -> 63_TR_Associação Brasileira de Entidades Estaduais e Públicas de Tecnologia da Informação e Comunicação | AR67: =_xlfn.CONCAT(AP67,"_","JUST","_",Tab_4.DISP_INEX[[#This Row],[FORNECEDOR]]) -> 63_JUST_Associação Brasileira de Entidades Estaduais e Públicas de Tecnologia da Informação e Comunicação | AS67: =_xlfn.CONCAT(AP67,"_","RAT","_",Tab_4.DISP_INEX[[#This Row],[FORNECEDOR]]) -> 63_RAT_Associação Brasileira de Entidades Estaduais e Públicas de Tecnologia da Informação e Comunicação
B68: 45839 | C68: FRANCIELE | D68: FINALIZADO | E68: FINALIZADO | F68: TLB-PRO-2025/02831 | G68: 2000-DAFRI | H68: GGP | I68: Serviços | J68: Curso/Treinamento: 15 ª Convenção de Contabilidade do Distrito Federal: inovação, conhecimento e networking | K68: Inexigibilidade | L68: ADMINISTRATIVO | M68: CONSELHO REGIONAL DE CONTABILIDADE DO DISTRITO FEDERAL | N68: 00.113.035/0001-37 | O68: Nota de Empenho | P68: 2025N000E846 | Q68: 2025N000E846 | R68: 2025N000E846 | S68: 45841 | T68: 45842 | U68: 45842 | V68: 2100 | W68: TLB-DEG-2025/00086 | X68: Camila Daniela Gomes | Y68: PÚBLICO | Z68: 10015827 | AA68: 10003176 | AC68: 45839 | AD68: =NETWORKDAYS.INTL(Tab_4.DISP_INEX[[#This Row],[DATA RECEBIDO]],Tab_4.DISP_INEX[[#This Row],[DATA FINALIZADO]],1,Lista!$U$3:$U$15) -> 1 | AE68: FRANCIELE | AF68: CAPACITAÇÃO | AG68: 925150 - 16/2025 | AH68: 37753638000103-1-000045/2025 | AI68: SIM | AJ68: https://www.telebras.com.br/wp-content/uploads/2025/07/13.2025NE846-CONSELHO-REGIONAL-DE-CONTABILIDADE-DO-DISTRITO-FEDERAL.pdf | AK68: - | AL68: - | AM68: - | AP68: 64 | AQ68: =_xlfn.CONCAT(AP68,"_","TR","_",Tab_4.DISP_INEX[[#This Row],[FORNECEDOR]]) -> 64_TR_CONSELHO REGIONAL DE CONTABILIDADE DO DISTRITO FEDERAL | AR68: =_xlfn.CONCAT(AP68,"_","JUST","_",Tab_4.DISP_INEX[[#This Row],[FORNECEDOR]]) -> 64_JUST_CONSELHO REGIONAL DE CONTABILIDADE DO DISTRITO FEDERAL | AS68: =_xlfn.CONCAT(AP68,"_","RAT","_",Tab_4.DISP_INEX[[#This Row],[FORNECEDOR]]) -> 64_RAT_CONSELHO REGIONAL DE CONTABILIDADE DO DISTRITO FEDERAL
B69: 45824 | C69: LAYLLAH | D69: FINALIZADO | E69: FINALIZADO | F69: TLB-PRO-2024/04999 | G69: 2000-DAFRI | H69: ARI | I69: Serviços | J69: Contratação de escritório de advocacia especializado para defesa judicial do ex Diretor da Telebras, o Sr. Paulo Ferreira, contra decisão proferida no Processo Administrativo Sancionador nº RJ2018/5158 (Processo Eletrônico SEI 19957.007825/2018 11), instaurado pela Comissão de Valores Mobiliários (CVM). | K69: Inexigibilidade | L69: ADMINISTRATIVO | M69: Badia e Quartim Advogados – BQA | N69: 60.525.730/0001-38 | O69: Nota de Empenho | P69: 2025NE001037 | Q69: 2025NE001037 | R69: TLB-ASS-2025/11220 | S69: 45880 | T69: 45880 | U69: 46022 | V69: 50000 | W69: TLB-DEG-2025/00126 | X69: JORGE PEREIRA FRAGOSO NETTO | Z69: 10014023 | AC69: 45849 | AD69: =NETWORKDAYS.INTL(Tab_4.DISP_INEX[[#This Row],[DATA RECEBIDO]],Tab_4.DISP_INEX[[#This Row],[DATA FINALIZADO]],1,Lista!$U$3:$U$15) -> 20 | AJ69: https://www.telebras.com.br/wp-content/uploads/2026/03/2025NE001037_Badia-e-Quartim-Advogados-–-BQA.pdf | AK69: - | AL69: - | AM69: - | AP69: 65 | AQ69: =_xlfn.CONCAT(AP69,"_","TR","_",Tab_4.DISP_INEX[[#This Row],[FORNECEDOR]]) -> 65_TR_Badia e Quartim Advogados – BQA | AR69: =_xlfn.CONCAT(AP69,"_","JUST","_",Tab_4.DISP_INEX[[#This Row],[FORNECEDOR]]) -> 65_JUST_Badia e Quartim Advogados – BQA | AS69: =_xlfn.CONCAT(AP69,"_","RAT","_",Tab_4.DISP_INEX[[#This Row],[FORNECEDOR]]) -> 65_RAT_Badia e Quartim Advogados – BQA
B70: 45859 | C70: ROSILDA | D70: FINALIZADO | E70: FINALIZADO | F70: TLB-PRO-2025/03743 | G70: 2000-DAFRI | H70: GGP | I70: Serviços | J70: Contratação de empresa para inscrição de até 35 empregados(as) da Telebras, no curso Apresentações estratégicas PPTPLAY. | K70: Inexigibilidade | L70: ADMINISTRATIVO | M70: RENATO DE PAULA - APRESENTACOES INTELIGENTES LTDA (PPTPLAY) | N70: 27.570.039/0001-09 | O70: Nota de Empenho | P70: 2025NE000953 | Q70: 2025NE000953 | R70: 2025NE000953 | S70: 45869 | T70: 45869 | U70: 46022 | V70: 23350 | W70: TLB-DEG-2025/00099 | X70: Adryana Ramos De Oliveira | Y70: PÚBLICO | Z70: 10015866 | AA70: 10004286 | AC70: 45866 | AD70: =NETWORKDAYS.INTL(Tab_4.DISP_INEX[[#This Row],[DATA RECEBIDO]],Tab_4.DISP_INEX[[#This Row],[DATA FINALIZADO]],1,Lista!$U$3:$U$15) -> 6 | AG70: 925150 - 22/2025 | AH70: 37753638000103-1-000057/2025 | AI70: SIM | AJ70: https://www.telebras.com.br/wp-content/uploads/2025/09/14.2025NE000953-RENATO-DE-PAULA-APRESENTACOES-INTELIGENTES-LTDA-PPTPLAY.pdf | AK70: - | AL70: - | AM70: - | AP70: 66 | AQ70: =_xlfn.CONCAT(AP70,"_","TR","_",Tab_4.DISP_INEX[[#This Row],[FORNECEDOR]]) -> 66_TR_RENATO DE PAULA - APRESENTACOES INTELIGENTES LTDA (PPTPLAY) | AR70: =_xlfn.CONCAT(AP70,"_","JUST","_",Tab_4.DISP_INEX[[#This Row],[FORNECEDOR]]) -> 66_JUST_RENATO DE PAULA - APRESENTACOES INTELIGENTES LTDA (PPTPLAY) | AS70: =_xlfn.CONCAT(AP70,"_","RAT","_",Tab_4.DISP_INEX[[#This Row],[FORNECEDOR]]) -> 66_RAT_RENATO DE PAULA - APRESENTACOES INTELIGENTES LTDA (PPTPLAY)
B71: 45867 | C71: FRANCIELE | D71: FINALIZADO | E71: FINALIZADO | F71: TLB-PRO-2025/03829 | G71: 2000-DAFRI | H71: GGP | I71: Serviços | J71: Contratação de empresa para inscrição de 09 empresário(s), no evento Agile Trends GOV 2025. | K71: Inexigibilidade | L71: ADMINISTRATIVO | M71: Neurobox Tecnologia em Informática Ltda | N71: 09.136.376/0001-00 | O71: Nota de Empenho | P71: 2025NE001029 | Q71: 2025NE001029 | R71: 2025NE001029 | S71: 45870 | T71: 45874 | U71: 45874 | V71: 16605 | W71: TLB-DEG-2025/00102 | X71: Adryana Ramos De Oliveira | Y71: PÚBLICO | Z71: 10015900 | AA71: 10004285 | AC71: 45869 | AD71: =NETWORKDAYS.INTL(Tab_4.DISP_INEX[[#This Row],[DATA RECEBIDO]],Tab_4.DISP_INEX[[#This Row],[DATA FINALIZADO]],1,Lista!$U$3:$U$15) -> 3 | AE71: FRANCIELE | AF71: EVENTO | AG71: 925150 - 23/2025 | AH71: 37753638000103-1-000058/2025 | AI71: SIM | AJ71: https://www.telebras.com.br/wp-content/uploads/2025/08/14.2025NE001029-Neurobox-Tecnologia-em-Informatica-Ltda.pdf | AK71: - | AL71: - | AM71: - | AP71: 67 | AQ71: =_xlfn.CONCAT(AP71,"_","TR","_",Tab_4.DISP_INEX[[#This Row],[FORNECEDOR]]) -> 67_TR_Neurobox Tecnologia em Informática Ltda | AR71: =_xlfn.CONCAT(AP71,"_","JUST","_",Tab_4.DISP_INEX[[#This Row],[FORNECEDOR]]) -> 67_JUST_Neurobox Tecnologia em Informática Ltda | AS71: =_xlfn.CONCAT(AP71,"_","RAT","_",Tab_4.DISP_INEX[[#This Row],[FORNECEDOR]]) -> 67_RAT_Neurobox Tecnologia em Informática Ltda
B72: 45883 | C72: FRANCIELE | D72: FINALIZADO | E72: FINALIZADO | F72: TLB-PRO-2025/04301 | G72: 2000-DAFRI | H72: GGP | I72: Serviços | J72: Contratação de empresa para inscrição de até 40 colaboradores das 4 diretorias da Telebras, com foco para a Diretoria Comercial, no curso Conteúdo, Corpo e Voz: Estratégias de Comunicação Eficaz para Fechamento de Acordos Comerciais. | K72: Inexigibilidade | L72: ADMINISTRATIVO | M72: IBMEC EDUCACIONAL LTDA | N72: 04.298.309/0001-60 | O72: Nota de Empenho | P72: 2025NE001047 | Q72: 2025NE001047 | R72: 2025NE001047 | S72: 45887 | T72: 45888 | U72: 45888 | V72: 26800 | W72: TLB-DEG-2025/00104 | X72: Adryana Ramos De Oliveira | Y72: PÚBLICO | Z72: 10015924 | AA72: 10003967 | AC72: 45884 | AD72: =NETWORKDAYS.INTL(Tab_4.DISP_INEX[[#This Row],[DATA RECEBIDO]],Tab_4.DISP_INEX[[#This Row],[DATA FINALIZADO]],1,Lista!$U$3:$U$15) -> 2 | AE72: FRANCIELE | AF72: CAPACITAÇÃO | AG72: 925150 - 24/2025 | AH72: 37753638000103-1-000059/2025 | AI72: SIM | AJ72: https://www.telebras.com.br/wp-content/uploads/2025/08/15.2025NE001047-Ibmec-Educacional-Ltda.pdf | AK72: - | AL72: - | AM72: - | AP72: 68 | AQ72: =_xlfn.CONCAT(AP72,"_","TR","_",Tab_4.DISP_INEX[[#This Row],[FORNECEDOR]]) -> 68_TR_IBMEC EDUCACIONAL LTDA | AR72: =_xlfn.CONCAT(AP72,"_","JUST","_",Tab_4.DISP_INEX[[#This Row],[FORNECEDOR]]) -> 68_JUST_IBMEC EDUCACIONAL LTDA | AS72: =_xlfn.CONCAT(AP72,"_","RAT","_",Tab_4.DISP_INEX[[#This Row],[FORNECEDOR]]) -> 68_RAT_IBMEC EDUCACIONAL LTDA
B73: 45902 | C73: FRANCIELE | D73: FINALIZADO | E73: FINALIZADO | F73: TLB-PRO-2025/04685 | G73: 2000-DAFRI | H73: GGP | I73: Serviços | J73: Contratação de empresa para inscrição dos(as) Conselheiros(as) José Cabral Guedes, Paula Vicente da Silva e Cleber Santiago no 26º Congresso IBGC - Governança em um Mundo Disruptivo . | K73: Inexigibilidade | L73: ADMINISTRATIVO | M73: Instituto Brasileiro de Governança Corporativa | N73: 01.082.331/0001-80 | O73: Nota de Empenho | P73: 2025NE001089 | Q73: 2025NE001089 | R73: 2025NE001089 | S73: 45905 | T73: 45905 | U73: 45905 | V73: 11090 | W73: TLB-DEG-2025/00114 | X73: Adryana Ramos De Oliveira | Y73: PÚBLICO | Z73: 10016027 | AA73: 10003951 | AC73: 45902 | AD73: =NETWORKDAYS.INTL(Tab_4.DISP_INEX[[#This Row],[DATA RECEBIDO]],Tab_4.DISP_INEX[[#This Row],[DATA FINALIZADO]],1,Lista!$U$3:$U$15) -> 1 | AE73: FRANCIELE | AF73: EVENTO | AG73: 925150-19/2025 | AH73: 37753638000103-1-000068/2025 | AI73: SIM | AJ73: https://www.telebras.com.br/wp-content/uploads/2025/10/17.2025NE001089-Instituto-Brasileiro-de-Governanca-Corporativa.pdf | AK73: - | AL73: - | AM73: - | AP73: 69 | AQ73: =_xlfn.CONCAT(AP73,"_","TR","_",Tab_4.DISP_INEX[[#This Row],[FORNECEDOR]]) -> 69_TR_Instituto Brasileiro de Governança Corporativa | AR73: =_xlfn.CONCAT(AP73,"_","JUST","_",Tab_4.DISP_INEX[[#This Row],[FORNECEDOR]]) -> 69_JUST_Instituto Brasileiro de Governança Corporativa | AS73: =_xlfn.CONCAT(AP73,"_","RAT","_",Tab_4.DISP_INEX[[#This Row],[FORNECEDOR]]) -> 69_RAT_Instituto Brasileiro de Governança Corporativa
B74: 45903 | C74: FRANCIELE | D74: FINALIZADO | E74: FINALIZADO | F74: TLB-PRO-2025/03622 | G74: 2000-DAFRI | H74: GGP | I74: Serviços | J74: Contratação de empresa para inscrição a inscrição de 03 funcionário(s) da AUD, no Congresso Brasileiro de Auditoria Interna - CONBRAI - 2025. | K74: Inexigibilidade | L74: ADMINISTRATIVO | M74: Congresso Brasileiro de Auditoria Interna | N74: 62.070.115/0001-00 | O74: Nota de Empenho | P74: 2025NE001096 | Q74: 2025NE001096 | R74: 2025NE001096 | S74: 45910 | T74: 45910 | U74: 45910 | V74: 14840 | W74: TLB-DEG-2025/00118 | X74: Adryana Ramos De Oliveira | Y74: PÚBLICO | Z74: 10016067 | AA74: 10004111 | AC74: 45904 | AD74: =NETWORKDAYS.INTL(Tab_4.DISP_INEX[[#This Row],[DATA RECEBIDO]],Tab_4.DISP_INEX[[#This Row],[DATA FINALIZADO]],1,Lista!$U$3:$U$15) -> 2 | AE74: FRANCIELE | AF74: EVENTO | AG74: 925150 - 29/2025 | AH74: 37753638000103-1-000069/2025 | AI74: SIM | AJ74: https://www.telebras.com.br/wp-content/uploads/2025/10/18.2025NE001096-Congresso-Brasileiro-de-Auditoria-Interna.pdf | AK74: - | AL74: - | AM74: - | AP74: 70 | AQ74: =_xlfn.CONCAT(AP74,"_","TR","_",Tab_4.DISP_INEX[[#This Row],[FORNECEDOR]]) -> 70_TR_Congresso Brasileiro de Auditoria Interna | AR74: =_xlfn.CONCAT(AP74,"_","JUST","_",Tab_4.DISP_INEX[[#This Row],[FORNECEDOR]]) -> 70_JUST_Congresso Brasileiro de Auditoria Interna | AS74: =_xlfn.CONCAT(AP74,"_","RAT","_",Tab_4.DISP_INEX[[#This Row],[FORNECEDOR]]) -> 70_RAT_Congresso Brasileiro de Auditoria Interna
B75: 45904 | C75: FRANCIELE | D75: FINALIZADO | E75: FINALIZADO | F75: TLB-PRO-2025/03941 | G75: 2000-DAFRI | H75: GGP | I75: Serviços | J75: Participação no Futurecom 2025 - Evento de Conectividade, Inovação e Cibersegurança (30/09 a 02/10 - São Paulo Expo). | K75: Inexigibilidade | L75: ADMINISTRATIVO | M75: Informa Markets Ltda | N75: 01.914.765/0001-08 | O75: Nota de Empenho | P75: 2025NE001103 | Q75: 2025NE001103 | R75: 2025NE001103 | S75: 45910 | T75: 45910 | U75: 45910 | V75: 13560 | W75: TLB-DEG-2025/00117 | X75: Adryana Ramos De Oliveira | Y75: PÚBLICO | Z75: 10016040 | AA75: 10002345 | AC75: 45905 | AD75: =NETWORKDAYS.INTL(Tab_4.DISP_INEX[[#This Row],[DATA RECEBIDO]],Tab_4.DISP_INEX[[#This Row],[DATA FINALIZADO]],1,Lista!$U$3:$U$15) -> 2 | AE75: FRANCIELE | AF75: EVENTO | AG75: 925150 - 30/2025 | AH75: 37753638000103-1-000070/2025 | AI75: SIM | AJ75: https://www.telebras.com.br/wp-content/uploads/2025/10/19.2025NE001103-Informa-Markets-Ltda.pdf | AK75: - | AL75: - | AM75: - | AP75: 71 | AQ75: =_xlfn.CONCAT(AP75,"_","TR","_",Tab_4.DISP_INEX[[#This Row],[FORNECEDOR]]) -> 71_TR_Informa Markets Ltda | AR75: =_xlfn.CONCAT(AP75,"_","JUST","_",Tab_4.DISP_INEX[[#This Row],[FORNECEDOR]]) -> 71_JUST_Informa Markets Ltda | AS75: =_xlfn.CONCAT(AP75,"_","RAT","_",Tab_4.DISP_INEX[[#This Row],[FORNECEDOR]]) -> 71_RAT_Informa Markets Ltda
B76: 45909 | C76: FRANCIELE | D76: FINALIZADO | E76: FINALIZADO | F76: TLB-PRO-2025/04652 | G76: 2000-DAFRI | H76: GGP | I76: Serviços | J76: Participação dos colaboradores da GEOS no Spacecraft Operations Course 2025 | K76: Inexigibilidade | L76: ADMINISTRATIVO | M76: DLR (Deutsches Zentrum für Luft- und Raumfahrt) | N76: - | O76: Nota de Empenho | P76: 2025NE001105 | Q76: 2025NE001105 | R76: 2025NE001105 | S76: 45911 | T76: 45911 | U76: 45911 | V76: 19508.83 | W76: TLB-DEG-2025/00120 | X76: Adryana Ramos De Oliveira | Y76: PÚBLICO | Z76: 10016042 | AC76: 45909 | AD76: =NETWORKDAYS.INTL(Tab_4.DISP_INEX[[#This Row],[DATA RECEBIDO]],Tab_4.DISP_INEX[[#This Row],[DATA FINALIZADO]],1,Lista!$U$3:$U$15) -> 1 | AE76: FRANCIELE | AF76: EVENTO | AG76: Internacional | AH76: Internacional | AI76: NA | AJ76: https://www.telebras.com.br/wp-content/uploads/2025/10/20.2025NE001105-DLR-Deutsches-Zentrum-fur-Luft-und-Raumfahrt.pdf | AK76: - | AL76: - | AM76: - | AP76: 72 | AQ76: =_xlfn.CONCAT(AP76,"_","TR","_",Tab_4.DISP_INEX[[#This Row],[FORNECEDOR]]) -> 72_TR_DLR (Deutsches Zentrum für Luft- und Raumfahrt) | AR76: =_xlfn.CONCAT(AP76,"_","JUST","_",Tab_4.DISP_INEX[[#This Row],[FORNECEDOR]]) -> 72_JUST_DLR (Deutsches Zentrum für Luft- und Raumfahrt) | AS76: =_xlfn.CONCAT(AP76,"_","RAT","_",Tab_4.DISP_INEX[[#This Row],[FORNECEDOR]]) -> 72_RAT_DLR (Deutsches Zentrum für Luft- und Raumfahrt)
B77: 45912 | C77: FRANCIELE | D77: FINALIZADO | E77: FINALIZADO | F77: TLB-PRO-2025/03846 | G77: 2000-DAFRI | H77: GGP | I77: Serviços | J77: Curso/Treinamento: Congresso Latino-americano de Satélites 2025 | K77: Inexigibilidade | L77: ADMINISTRATIVO | M77: GLASBERG COMUNICAÇÕES LTDA | N77: 65.011.538/0001-47 | O77: Ordem de Compra | P77: TLB-ORC-2025/00003 | Q77: TLB-ORC-2025/00003 | R77: TLB-ORC-2025/00003 | S77: 45922 | T77: 45922 | U77: 45922 | V77: 10800 | W77: TLB-DEG-2025/00133 | X77: Adryana Ramos De Oliveira | Y77: PÚBLICO | Z77: 10015968 | AC77: 45918 | AD77: =NETWORKDAYS.INTL(Tab_4.DISP_INEX[[#This Row],[DATA RECEBIDO]],Tab_4.DISP_INEX[[#This Row],[DATA FINALIZADO]],1,Lista!$U$3:$U$15) -> 5 | AE77: FRANCIELE | AF77: EVENTO | AG77: 925150 - 31/2025 | AH77: 37753638000103-1-000071/2025 | AI77: SIM | AJ77: https://www.telebras.com.br/wp-content/uploads/2025/10/21.-TLB-ORC-2025-00003-GLASBERG-COMUNICACOES-LTDA.pdf | AK77: - | AL77: - | AM77: - | AP77: 73 | AQ77: =_xlfn.CONCAT(AP77,"_","TR","_",Tab_4.DISP_INEX[[#This Row],[FORNECEDOR]]) -> 73_TR_GLASBERG COMUNICAÇÕES LTDA | AR77: =_xlfn.CONCAT(AP77,"_","JUST","_",Tab_4.DISP_INEX[[#This Row],[FORNECEDOR]]) -> 73_JUST_GLASBERG COMUNICAÇÕES LTDA | AS77: =_xlfn.CONCAT(AP77,"_","RAT","_",Tab_4.DISP_INEX[[#This Row],[FORNECEDOR]]) -> 73_RAT_GLASBERG COMUNICAÇÕES LTDA
B78: 45831 | C78: ALENCASTRO | D78: FINALIZADO | E78: FINALIZADO | F78: TLB-PRO-2025/02898 | G78: 3000-DTO | H78: GEOS | I78: Compras | J78: Aquisição de bebedouros para atender as necessidades da sede da Telebras no COPE-P | K78: Dispensa | L78: ADMINISTRATIVO | M78: M & J REFRIGERACAO LTDA | N78: 54.638.483/0001-83 | O78: Nota de Empenho | P78: 2025NE000855 | Q78: 2025NE000855 | R78: TLB-ASS-2025/09363 | S78: 45845 | T78: 45845 | U78: 46022 | V78: 3245 | W78: TLB-DEG-2025/00091 | X78: SERGIO PINHO PIRETTI | Y78: PÚBLICO | Z78: 10004266 | AD78: =NETWORKDAYS.INTL(Tab_4.DISP_INEX[[#This Row],[DATA RECEBIDO]],Tab_4.DISP_INEX[[#This Row],[DATA FINALIZADO]],1,Lista!$U$3:$U$15) -> -32727 | AF78: Dispensa Eletrônica | AG78: 90006/2025 | AH78: 37753638000103-1-000038/2025 | AI78: SIM | AJ78: https://www.telebras.com.br/wp-content/uploads/2026/01/29.2025NE000855-M-J-REFRIGERACAO-LTDA.pdf | AK78: - | AL78: - | AM78: - | AP78: 74 | AQ78: =_xlfn.CONCAT(AP78,"_","TR","_",Tab_4.DISP_INEX[[#This Row],[FORNECEDOR]]) -> 74_TR_M & J REFRIGERACAO LTDA | AR78: =_xlfn.CONCAT(AP78,"_","JUST","_",Tab_4.DISP_INEX[[#This Row],[FORNECEDOR]]) -> 74_JUST_M & J REFRIGERACAO LTDA | AS78: =_xlfn.CONCAT(AP78,"_","RAT","_",Tab_4.DISP_INEX[[#This Row],[FORNECEDOR]]) -> 74_RAT_M & J REFRIGERACAO LTDA
B79: 45912 | C79: FRANCIELE | D79: FINALIZADO | E79: FINALIZADO | F79: TLB-PRO-2025/04974 | G79: 2000-DAFRI | H79: GGP | I79: Serviços | J79: Contratação da participação no 39° Congresso Brasileiro de Direito Administrativo | K79: Inexigibilidade | L79: ADMINISTRATIVO | M79: INSTITUTO BRASILEIRO DE DIREITO ADMINISTRATIVO - IBDA | N79: 29.419.181/0001-77 | O79: Ordem de Compra | Q79: TLB-ORC-2025/00002 | R79: TLB-ORC-2025/00002 | S79: 45916 | T79: 45916 | U79: 45916 | V79: 4000 | W79: TLB-DEG-2025/00124 | X79: Adryana Ramos De Oliveira | Y79: PÚBLICO | Z79: 10016047 | AA79: 10004306 | AC79: 45912 | AD79: =NETWORKDAYS.INTL(Tab_4.DISP_INEX[[#This Row],[DATA RECEBIDO]],Tab_4.DISP_INEX[[#This Row],[DATA FINALIZADO]],1,Lista!$U$3:$U$15) -> 1 | AG79: 925150 - 32/2025 | AH79: 37753638000103-1-000072/2025 | AI79: SIM | AJ79: https://www.telebras.com.br/wp-content/uploads/2025/10/22.TLB-ORC-2025-00002-INSTITUTO-BRASILEIRO-DE-DIREITO-ADMINISTRATIVO-IBDA.pdf | AK79: - | AL79: - | AM79: - | AP79: 75 | AQ79: =_xlfn.CONCAT(AP79,"_","TR","_",Tab_4.DISP_INEX[[#This Row],[FORNECEDOR]]) -> 75_TR_INSTITUTO BRASILEIRO DE DIREITO ADMINISTRATIVO - IBDA | AR79: =_xlfn.CONCAT(AP79,"_","JUST","_",Tab_4.DISP_INEX[[#This Row],[FORNECEDOR]]) -> 75_JUST_INSTITUTO BRASILEIRO DE DIREITO ADMINISTRATIVO - IBDA | AS79: =_xlfn.CONCAT(AP79,"_","RAT","_",Tab_4.DISP_INEX[[#This Row],[FORNECEDOR]]) -> 75_RAT_INSTITUTO BRASILEIRO DE DIREITO ADMINISTRATIVO - IBDA
B80: 45923 | C80: LAYLLAH | D80: FINALIZADO | E80: FINALIZADO | F80: TLB-PRO-2025/01134 | G80: 2000-DAFRI | H80: GMP | I80: Compras | J80: Contratação para aquisição de equipamentos do sistema de ar climatização (condensadoras) para as Estações de Acesso / Gateways | K80: Inexigibilidade | L80: ADMINISTRATIVO | M80: VERTIV TECNOLOGIA DO BRASIL LTDA. | N80: 03.698.870/0008-40 | O80: Contrato | Q80: TLB-CTR-2025/00090 | R80: TLB-AUT-2025/22260 | S80: 46006 | T80: 46006 | U80: 46736 | V80: 4357243.3 | W80: TLB-DEG-2025/00194 | X80: Isac Pires Moraes Filho | Y80: PÚBLICO | Z80: 10016045 | AD80: =NETWORKDAYS.INTL(Tab_4.DISP_INEX[[#This Row],[DATA RECEBIDO]],Tab_4.DISP_INEX[[#This Row],[DATA FINALIZADO]],1,Lista!$U$3:$U$15) -> -32793 | AJ80: https://www.telebras.com.br/wp-content/uploads/2026/01/39.TLB-CTR-2025.00090-VERTIV-TECNOLOGIA-DO-BRASIL-LTDA.pdf | AK80: - | AL80: - | AM80: - | AP80: 76 | AQ80: =_xlfn.CONCAT(AP80,"_","TR","_",Tab_4.DISP_INEX[[#This Row],[FORNECEDOR]]) -> 76_TR_VERTIV TECNOLOGIA DO BRASIL LTDA. | AR80: =_xlfn.CONCAT(AP80,"_","JUST","_",Tab_4.DISP_INEX[[#This Row],[FORNECEDOR]]) -> 76_JUST_VERTIV TECNOLOGIA DO BRASIL LTDA. | AS80: =_xlfn.CONCAT(AP80,"_","RAT","_",Tab_4.DISP_INEX[[#This Row],[FORNECEDOR]]) -> 76_RAT_VERTIV TECNOLOGIA DO BRASIL LTDA.
B81: 45932 | C81: LAYLLAH | D81: FINALIZADO | E81: FINALIZADO | F81: TLB-PRO-2025/01043 | G81: 2000-DAFRI | H81: GGP | I81: Serviços | J81: CONSULTORIA PARA IMPLANTAÇÃO DE PRÁTICAS DE GESTÃO DO CONHECIMENTO | K81: Inexigibilidade | L81: ADMINISTRATIVO | M81: IMPAKT CONSULTORIA S/S LIMITADA | N81: 08.170.564/0001-84 | O81: Contrato | P81: - | Q81: TLB-CTR-2025/00089 | R81: TLB-AUT-2025/20268 | S81: 45967 | T81: 45967 | U81: 46424 | V81: 1252476 | W81: TLB-DEG-2025/00178 | X81: Camila Daniela Lima de Souza Gomes | AD81: =NETWORKDAYS.INTL(Tab_4.DISP_INEX[[#This Row],[DATA RECEBIDO]],Tab_4.DISP_INEX[[#This Row],[DATA FINALIZADO]],1,Lista!$U$3:$U$15) -> -32800 | AJ81: https://www.telebras.com.br/wp-content/uploads/2025/12/29.TLB-CTR-2025.00089-IMPAKT-CONSULTORIA-SS-LIMITADA.pdf | AK81: - | AL81: - | AM81: - | AP81: 77 | AQ81: =_xlfn.CONCAT(AP81,"_","TR","_",Tab_4.DISP_INEX[[#This Row],[FORNECEDOR]]) -> 77_TR_IMPAKT CONSULTORIA S/S LIMITADA | AR81: =_xlfn.CONCAT(AP81,"_","JUST","_",Tab_4.DISP_INEX[[#This Row],[FORNECEDOR]]) -> 77_JUST_IMPAKT CONSULTORIA S/S LIMITADA | AS81: =_xlfn.CONCAT(AP81,"_","RAT","_",Tab_4.DISP_INEX[[#This Row],[FORNECEDOR]]) -> 77_RAT_IMPAKT CONSULTORIA S/S LIMITADA
B82: 45932 | C82: LAYLLAH | D82: FINALIZADO | E82: FINALIZADO | F82: TLB-PRO-2025/01133 | G82: 2000-DAFRI | H82: GMP | I82: Compras | J82: Processo de contratação para aquisição de componentes do Grupo Motor Gerador (GMG) para as Estações de Acesso / Gateways | K82: Inexigibilidade | L82: ADMINISTRATIVO | M82: ROLLS ROYCE SOLUTIONS BRASIL LTDA | N82: 48.600.191/0001-59 | O82: Contrato | P82: - | Q82: TLB-CTR-2026/00010 | R82: TLB-AUT-2026/01125 | S82: 46044 | T82: 46044 | U82: 46409 | V82: 762535.47 | W82: TLB-DEG-2026/00043 | X82: Rodrigo Andrade Silveira de Araujo | Z82: 10016046 | AD82: =NETWORKDAYS.INTL(Tab_4.DISP_INEX[[#This Row],[DATA RECEBIDO]],Tab_4.DISP_INEX[[#This Row],[DATA FINALIZADO]],1,Lista!$U$3:$U$15) -> -32800 | AG82: 925150 - 2/2026 | AH82: SIM | AI82: SIM | AJ82: https://www.telebras.com.br/wp-content/uploads/2026/03/TLB-CTR-202600010.pdf | AK82: https://www.telebras.com.br/wp-content/uploads/2026/06/78_TR_ROLLS-ROYCE-SOLUTIONS-BRASIL-LTDA.pdf | AL82: https://www.telebras.com.br/wp-content/uploads/2026/06/78_JUST_ROLLS-ROYCE-SOLUTIONS-BRASIL-LTDA.pdf | AM82: https://www.telebras.com.br/wp-content/uploads/2026/06/78_RAT_ROLLS-ROYCE-SOLUTIONS-BRASIL-LTDA.pdf | AP82: 77 | AQ82: =_xlfn.CONCAT(AP82,"_","TR","_",Tab_4.DISP_INEX[[#This Row],[FORNECEDOR]]) -> 77_TR_ROLLS ROYCE SOLUTIONS BRASIL LTDA | AR82: =_xlfn.CONCAT(AP82,"_","JUST","_",Tab_4.DISP_INEX[[#This Row],[FORNECEDOR]]) -> 77_JUST_ROLLS ROYCE SOLUTIONS BRASIL LTDA | AS82: =_xlfn.CONCAT(AP82,"_","RAT","_",Tab_4.DISP_INEX[[#This Row],[FORNECEDOR]]) -> 77_RAT_ROLLS ROYCE SOLUTIONS BRASIL LTDA
B83: 45937 | C83: FRANCIELE | D83: FINALIZADO | E83: FINALIZADO | F83: TLB-PRO-2025/05401 | G83: 2000-DAFRI | H83: GCC | I83: Serviços | J83: Contratação da versão Plus 100 da ferramenta de pesquisa e comparação de preços praticados pela administração pública, denominada Banco de Preços, que consiste num sistema de pesquisa baseado em resultados de licitações adjudicadas e homologadas, a fim de facilitar a pesquisa de mercado para estimar os custos das contratações da TELEBRAS. | K83: Inexigibilidade | L83: ADMINISTRATIVO | M83: NP Tecnologia e Gestão de Dados Ltda | N83: 07.797.967/0001-95 | O83: Ordem de Compra | P83: - | Q83: TLB-ORC-2025/00005 | R83: TLB-ORC-2025/00005 | S83: 45938 | T83: 45938 | U83: 45938 | V83: 18100 | W83: TLB-DEG-2025/00144 | X83: Franciele Ferreira da Silva | Y83: PÚBLICO | Z83: 10016086 | AA83: 10001658 | AC83: 45945 | AD83: =NETWORKDAYS.INTL(Tab_4.DISP_INEX[[#This Row],[DATA RECEBIDO]],Tab_4.DISP_INEX[[#This Row],[DATA FINALIZADO]],1,Lista!$U$3:$U$15) -> 7 | AJ83: https://www.telebras.com.br/wp-content/uploads/2026/06/TLBORC202500005A_NP-TECNOLOGIA-E-GESTAO-DE-DADOS-LTDA.pdf | AK83: - | AL83: - | AM83: - | AP83: 77 | AQ83: =_xlfn.CONCAT(AP83,"_","TR","_",Tab_4.DISP_INEX[[#This Row],[FORNECEDOR]]) -> 77_TR_NP Tecnologia e Gestão de Dados Ltda | AR83: =_xlfn.CONCAT(AP83,"_","JUST","_",Tab_4.DISP_INEX[[#This Row],[FORNECEDOR]]) -> 77_JUST_NP Tecnologia e Gestão de Dados Ltda | AS83: =_xlfn.CONCAT(AP83,"_","RAT","_",Tab_4.DISP_INEX[[#This Row],[FORNECEDOR]]) -> 77_RAT_NP Tecnologia e Gestão de Dados Ltda
B84: 45944 | C84: FRANCIELE | D84: FINALIZADO | E84: FINALIZADO | F84: TLB-PRO-2025/05423 | G84: 2000-DAFRI | H84: GGP | I84: Serviços | J84: Contratação de empresa para a inscrição de 01 colaboradora da AUD curso AUDI 2 EOP, com a respectiva associaçãos. | K84: Inexigibilidade | L84: ADMINISTRATIVO | M84: INSTITUTO DOS AUDITORES INTERNOS DO BRASIL | N84: 62.070.115/0001-00 | O84: Ordem de Compra | P84: TLB-ORC-2025/00006 | Q84: TLB-ORC-2025/00006 | R84: TLB-ORC-2025/00006 | S84: 45947 | T84: 45947 | U84: 45947 | V84: 2775 | W84: TLB-DEG-2025/00166 | X84: Adryana Ramos De Oliveira | Y84: PÚBLICO | Z84: 10016089 | AA84: 10004111 | AD84: =NETWORKDAYS.INTL(Tab_4.DISP_INEX[[#This Row],[DATA RECEBIDO]],Tab_4.DISP_INEX[[#This Row],[DATA FINALIZADO]],1,Lista!$U$3:$U$15) -> -32808 | AG84: 925150 - 36/2025 | AH84: 37753638000103-1-000091/2025 | AI84: SIM | AJ84: https://www.telebras.com.br/wp-content/uploads/2025/12/23.-TLB-ORC-2025.00006-Instituto-dos-Auditores-Internos-do-Brasil.pdf | AK84: - | AL84: - | AM84: - | AP84: 79 | AQ84: =_xlfn.CONCAT(AP84,"_","TR","_",Tab_4.DISP_INEX[[#This Row],[FORNECEDOR]]) -> 79_TR_INSTITUTO DOS AUDITORES INTERNOS DO BRASIL | AR84: =_xlfn.CONCAT(AP84,"_","JUST","_",Tab_4.DISP_INEX[[#This Row],[FORNECEDOR]]) -> 79_JUST_INSTITUTO DOS AUDITORES INTERNOS DO BRASIL | AS84: =_xlfn.CONCAT(AP84,"_","RAT","_",Tab_4.DISP_INEX[[#This Row],[FORNECEDOR]]) -> 79_RAT_INSTITUTO DOS AUDITORES INTERNOS DO BRASIL
B85: 45954 | C85: FRANCIELE | D85: FINALIZADO | E85: FINALIZADO | F85: TLB-PRO-2025/05572 | G85: 2000-DAFRI | H85: GGP | I85: Serviços | J85: Contratação da capacitação HSM + 2025. | K85: Inexigibilidade | L85: ADMINISTRATIVO | M85: MCI BRASIL LTDA | N85: 11.321.229/0001-44 | O85: Ordem de Compra | P85: TLB-ORC-2025/00007 | Q85: TLB-ORC-2025/00007 | R85: TLB-ORC-2025/00007 | S85: 45958 | T85: 45958 | U85: 45958 | V85: 17500 | W85: TLB-DEG-2025/00168 | X85: Adryana Ramos De Oliveira | Y85: PÚBLICO | Z85: 10016133 | AA85: 10002161 | AB85: TLB-ORC-2025/00007 | AD85: =NETWORKDAYS.INTL(Tab_4.DISP_INEX[[#This Row],[DATA RECEBIDO]],Tab_4.DISP_INEX[[#This Row],[DATA FINALIZADO]],1,Lista!$U$3:$U$15) -> -32816 | AG85: 925150 - 37/2025 | AH85: 37753638000103-1-000092/2025 | AI85: SIM | AJ85: https://www.telebras.com.br/wp-content/uploads/2025/12/24.TLB-ORC-2025.00007-MCI-BRASIL-LTDA.pdf | AK85: - | AL85: - | AM85: - | AP85: 80 | AQ85: =_xlfn.CONCAT(AP85,"_","TR","_",Tab_4.DISP_INEX[[#This Row],[FORNECEDOR]]) -> 80_TR_MCI BRASIL LTDA | AR85: =_xlfn.CONCAT(AP85,"_","JUST","_",Tab_4.DISP_INEX[[#This Row],[FORNECEDOR]]) -> 80_JUST_MCI BRASIL LTDA | AS85: =_xlfn.CONCAT(AP85,"_","RAT","_",Tab_4.DISP_INEX[[#This Row],[FORNECEDOR]]) -> 80_RAT_MCI BRASIL LTDA
B86: 45961 | C86: FRANCIELE | D86: FINALIZADO | E86: FINALIZADO | F86: TLB-PRO-2025/05575 | G86: 2000-DAFRI | H86: GGP | I86: Serviços | J86: Contratação da Capacitação - Aprimoramento em Governança para Empresas Estatais. | K86: Inexigibilidade | L86: ADMINISTRATIVO | M86: INSTITUTO BRASILEIRO DE GOVERNANÇA CORPORATIVA | N86: 01.082.331/0001-80 | O86: Ordem de Compra | P86: TLB-ORC-2025/00008 | Q86: TLB-ORC-2025/00008 | R86: TLB-ORC-2025/00008 | S86: 45966 | T86: 45966 | U86: 45966 | V86: 25500 | W86: TLB-DEG-2025/00177 | X86: Adryana Ramos De Oliveira | Y86: PÚBLICO | Z86: 10016135 | AA86: 10003951 | AC86: 45968 | AD86: =NETWORKDAYS.INTL(Tab_4.DISP_INEX[[#This Row],[DATA RECEBIDO]],Tab_4.DISP_INEX[[#This Row],[DATA FINALIZADO]],1,Lista!$U$3:$U$15) -> 6 | AG86: 925150 - 38/2025 | AH86: 37753638000103-1-000093/2025 | AI86: SIM | AJ86: https://www.telebras.com.br/wp-content/uploads/2025/12/25.TLB-ORC-2025.00008-Instituto-Brasileiro-de-Governanca-Corporativa.pdf | AK86: - | AL86: - | AM86: - | AP86: 81 | AQ86: =_xlfn.CONCAT(AP86,"_","TR","_",Tab_4.DISP_INEX[[#This Row],[FORNECEDOR]]) -> 81_TR_INSTITUTO BRASILEIRO DE GOVERNANÇA CORPORATIVA | AR86: =_xlfn.CONCAT(AP86,"_","JUST","_",Tab_4.DISP_INEX[[#This Row],[FORNECEDOR]]) -> 81_JUST_INSTITUTO BRASILEIRO DE GOVERNANÇA CORPORATIVA | AS86: =_xlfn.CONCAT(AP86,"_","RAT","_",Tab_4.DISP_INEX[[#This Row],[FORNECEDOR]]) -> 81_RAT_INSTITUTO BRASILEIRO DE GOVERNANÇA CORPORATIVA
B87: 45968 | C87: FRANCIELE | D87: FINALIZADO | E87: FINALIZADO | F87: TLB-PRO-2025/05053 | G87: 2000-DAFRI | H87: GGP | I87: Serviços | J87: Contratação do Workshop de Gestão de Riscos. | K87: Inexigibilidade | L87: ADMINISTRATIVO | M87: IBMEC EDUCACIONAL LTDA | N87: 04.298.309/0013-02 | O87: Ordem de Compra | P87: TLB-ORC-2025/00010 | Q87: TLB-ORC-2025/00010 | R87: TLB-ORC-2025/00010 | S87: 45972 | T87: 45972 | U87: 45972 | V87: 17000 | W87: TLB-DEG-2025/00179 | X87: Anna Cláudia Amorim da Silva | Y87: PÚBLICO | Z87: 10016203 | AA87: 10003967 | AC87: 45974 | AD87: =NETWORKDAYS.INTL(Tab_4.DISP_INEX[[#This Row],[DATA RECEBIDO]],Tab_4.DISP_INEX[[#This Row],[DATA FINALIZADO]],1,Lista!$U$3:$U$15) -> 5 | AG87: 925150 - 39/2025 | AH87: 37753638000103-1-000094/2025 | AI87: SIM | AJ87: https://www.telebras.com.br/wp-content/uploads/2025/12/26.-TLB-ORC-2025.00010-Ibmec-Educacional-Ltda.pdf | AK87: - | AL87: - | AM87: - | AP87: 82 | AQ87: =_xlfn.CONCAT(AP87,"_","TR","_",Tab_4.DISP_INEX[[#This Row],[FORNECEDOR]]) -> 82_TR_IBMEC EDUCACIONAL LTDA | AR87: =_xlfn.CONCAT(AP87,"_","JUST","_",Tab_4.DISP_INEX[[#This Row],[FORNECEDOR]]) -> 82_JUST_IBMEC EDUCACIONAL LTDA | AS87: =_xlfn.CONCAT(AP87,"_","RAT","_",Tab_4.DISP_INEX[[#This Row],[FORNECEDOR]]) -> 82_RAT_IBMEC EDUCACIONAL LTDA
B88: 45994 | C88: MARCUS VINÍCIUS | D88: FINALIZADO | E88: FINALIZADO | F88: TLB-PRO-2025/04066 | G88: 2000-DAFRI | H88: GTI | I88: Serviços | J88: Contratação de serviços especializados em consultas às bases do Cadastro de Pessoa Física - CPF e Cadastro Nacional de Pessoa Jurídica - CNPJ | K88: Inexigibilidade | L88: ADMINISTRATIVO | M88: SERPRO - SERVIÇO FEDERAL DE PROCESSAMENTO DE DADOS | N88: 33.683.111/0001-07 | O88: Contrato de Adesão | P88: - | Q88: TLB-AUT-2026/00714 | R88: TLB-AUT-2026/00714 | S88: 46036 | T88: 46036 | U88: 46401 | V88: 6353.64 | W88: TLB-DEG-2026/00035 | X88: DALVA HELENA ROSA FERREIRA | AD88: =NETWORKDAYS.INTL(Tab_4.DISP_INEX[[#This Row],[DATA RECEBIDO]],Tab_4.DISP_INEX[[#This Row],[DATA FINALIZADO]],1,Lista!$U$3:$U$15) -> -32844 | AG88: 925150 - 4/2026 | AH88: SIM | AI88: SIM | AJ88: https://www.telebras.com.br/wp-content/uploads/2026/03/1.TLB-AUT-202600714-SERPRO-SERVICO-FEDERAL-DE-PROCESSAMENTO-DE-DADOS-Tipo-do-objeto-Servicos.pdf | AK88: https://www.telebras.com.br/wp-content/uploads/2026/06/83_TR_SERPRO-SERVICO-FEDERAL-DE-PROCESSAMENTO-DE-DADOS.pdf | AL88: https://www.telebras.com.br/wp-content/uploads/2026/06/83_JUST_SERPRO-SERVICO-FEDERAL-DE-PROCESSAMENTO-DE-DADOS.pdf | AM88: https://www.telebras.com.br/wp-content/uploads/2026/06/83_RAT_SERPRO-SERVICO-FEDERAL-DE-PROCESSAMENTO-DE-DADOS.pdf | AP88: 83 | AQ88: =_xlfn.CONCAT(AP88,"_","TR","_",Tab_4.DISP_INEX[[#This Row],[FORNECEDOR]]) -> 83_TR_SERPRO - SERVIÇO FEDERAL DE PROCESSAMENTO DE DADOS | AR88: =_xlfn.CONCAT(AP88,"_","JUST","_",Tab_4.DISP_INEX[[#This Row],[FORNECEDOR]]) -> 83_JUST_SERPRO - SERVIÇO FEDERAL DE PROCESSAMENTO DE DADOS | AS88: =_xlfn.CONCAT(AP88,"_","RAT","_",Tab_4.DISP_INEX[[#This Row],[FORNECEDOR]]) -> 83_RAT_SERPRO - SERVIÇO FEDERAL DE PROCESSAMENTO DE DADOS
B89: 45925 | C89: LAYLLAH | D89: FINALIZADO | E89: FINALIZADO | F89: TLB-PRO-2025/03496 | G89: 3000-DTO | H89: TBGPR-ASCOM | I89: Compras | J89: HDs | K89: Dispensa | L89: ADMINISTRATIVO | M89: MARFAP COMERCIAL LTDA | N89: 49.978.985/0001-13 | O89: Ordem de Compra | P89: - | Q89: TLB-ORC-2025/00004 | R89: TLB-ORC-2025/00004 | S89: 45932 | T89: 45932 | U89: 45952 | V89: 7760 | W89: TLB-DEG-2025/00140 | X89: Érico Luís Cortes Cazarré | Y89: PÚBLICO | AC89: 45940 | AD89: =NETWORKDAYS.INTL(Tab_4.DISP_INEX[[#This Row],[DATA RECEBIDO]],Tab_4.DISP_INEX[[#This Row],[DATA FINALIZADO]],1,Lista!$U$3:$U$15) -> 12 | AG89: 925150 - 25/2025 | AH89: 37753638000103-1-000061/2025 | AI89: SIM | AJ89: https://www.telebras.com.br/wp-content/uploads/2025/12/27.TLB-ORC-2025.00004-MARFAP-COMERCIAL-LTDA.pdf | AK89: - | AL89: - | AM89: - | AP89: 84 | AQ89: =_xlfn.CONCAT(AP89,"_","TR","_",Tab_4.DISP_INEX[[#This Row],[FORNECEDOR]]) -> 84_TR_MARFAP COMERCIAL LTDA | AR89: =_xlfn.CONCAT(AP89,"_","JUST","_",Tab_4.DISP_INEX[[#This Row],[FORNECEDOR]]) -> 84_JUST_MARFAP COMERCIAL LTDA | AS89: =_xlfn.CONCAT(AP89,"_","RAT","_",Tab_4.DISP_INEX[[#This Row],[FORNECEDOR]]) -> 84_RAT_MARFAP COMERCIAL LTDA
B90: 45932 | C90: LAYLLAH | D90: FINALIZADO | E90: FINALIZADO | F90: TLB-PRO-2025/03511 | G90: 3000-DTO | H90: TBGEOS | I90: Compras | J90: Estantes para COPE | K90: Dispensa | L90: ADMINISTRATIVO | M90: SOUL DISTRIBUIDORA DE PRODUTOS E EQUIPAMENTOS INDUSTRIAIS LTDA | N90: 51.659.136/0001-49 | O90: Ordem de Compra | P90: - | Q90: TLB-ORC-2025/00011 | R90: TLB-ORC-2025/00011 | S90: 45982 | T90: 45982 | U90: 46003 | V90: 12680 | W90: TLB-DEG-2025/00189 | X90: Fernando Lambert | Y90: PÚBLICO | AC90: 45996 | AD90: =NETWORKDAYS.INTL(Tab_4.DISP_INEX[[#This Row],[DATA RECEBIDO]],Tab_4.DISP_INEX[[#This Row],[DATA FINALIZADO]],1,Lista!$U$3:$U$15) -> 47 | AG90: 925150 - 33/2025 | AH90: 37753638000103-1-000080/2025 | AI90: SIM | AJ90: https://www.telebras.com.br/wp-content/uploads/2025/12/28.TLB-ORC-2025.00011-SOUL-DISTRIBUIDORA-DE-PRODUTOS-E-EQUIPAMENTOS-INDUSTRIAIS-LTDA.pdf | AK90: - | AL90: - | AM90: - | AP90: 85 | AQ90: =_xlfn.CONCAT(AP90,"_","TR","_",Tab_4.DISP_INEX[[#This Row],[FORNECEDOR]]) -> 85_TR_SOUL DISTRIBUIDORA DE PRODUTOS E EQUIPAMENTOS INDUSTRIAIS LTDA | AR90: =_xlfn.CONCAT(AP90,"_","JUST","_",Tab_4.DISP_INEX[[#This Row],[FORNECEDOR]]) -> 85_JUST_SOUL DISTRIBUIDORA DE PRODUTOS E EQUIPAMENTOS INDUSTRIAIS LTDA | AS90: =_xlfn.CONCAT(AP90,"_","RAT","_",Tab_4.DISP_INEX[[#This Row],[FORNECEDOR]]) -> 85_RAT_SOUL DISTRIBUIDORA DE PRODUTOS E EQUIPAMENTOS INDUSTRIAIS LTDA
B91: 45932 | C91: LAYLLAH | D91: FINALIZADO | E91: FINALIZADO | F91: TLB-PRO-2025/01337 | G91: 3000-DTO | H91: TBGERP | I91: Serviços | J91: Cabos breakout | K91: Dispensa | L91: ADMINISTRATIVO | M91: FONNET COMÉRCIO DE EQUIPAMENTOS DE TELECOMUNICAÇÕES LTDA | N91: 11.035.558/0001-29 | O91: Contrato | P91: - | Q91: TLB-CTR-2025/00061 | R91: TLB-CTR-2025/00061 | S91: 45924 | T91: 45936 | U91: 46301 | V91: 19500 | W91: TLB-DEG-2025/00165 | X91: Mirele de Almeida Mencari | Y91: PÚBLICO | Z91: 4400003101 | AA91: 4400003101 | AB91: TLB-AUT-2025/19125 | AC91: 45951 | AD91: =NETWORKDAYS.INTL(Tab_4.DISP_INEX[[#This Row],[DATA RECEBIDO]],Tab_4.DISP_INEX[[#This Row],[DATA FINALIZADO]],1,Lista!$U$3:$U$15) -> 14 | AJ91: https://www.telebras.com.br/wp-content/uploads/2025/10/25.TLB-CTR-2025.00061-FONNET-COMERCIO-DE-EQUIPAMENTOS-DE-TELECOMUNICACOES-LTDA.pdf | AK91: - | AL91: - | AM91: - | AP91: 86 | AQ91: =_xlfn.CONCAT(AP91,"_","TR","_",Tab_4.DISP_INEX[[#This Row],[FORNECEDOR]]) -> 86_TR_FONNET COMÉRCIO DE EQUIPAMENTOS DE TELECOMUNICAÇÕES LTDA | AR91: =_xlfn.CONCAT(AP91,"_","JUST","_",Tab_4.DISP_INEX[[#This Row],[FORNECEDOR]]) -> 86_JUST_FONNET COMÉRCIO DE EQUIPAMENTOS DE TELECOMUNICAÇÕES LTDA | AS91: =_xlfn.CONCAT(AP91,"_","RAT","_",Tab_4.DISP_INEX[[#This Row],[FORNECEDOR]]) -> 86_RAT_FONNET COMÉRCIO DE EQUIPAMENTOS DE TELECOMUNICAÇÕES LTDA
B92: 45946 | C92: LAYLLAH | D92: FINALIZADO | E92: FINALIZADO | F92: TLB-PRO-2025/03416 | G92: 2000-DAFRI | H92: GGP | I92: Serviços | J92: Realização de concurso público | K92: Dispensa | L92: ADMINISTRATIVO | M92: CENTRO BRASILEIRO DE PESQUISA EM AVALIAÇÃO E SELEÇÃO E DE PROMOÇÃO DE EVENTOS (CEBRASPE) | N92: 18.284.407/0001-53 | O92: Contrato | P92: - | Q92: TLB-CTR-2025/00103 | R92: TLB-CTR-2025/00103 | S92: 45986 | T92: 45986 | U92: 47812 | V92: R$ 1.496.376,51 | W92: TLB-DEG-2025/00186 | X92: ANNA CLÁUDIA AMORIM DA SILVA | Y92: PÚBLICO | Z92: 4400003111 | AA92: 4400003111 | AB92: TLB-AUT-2025/21982 | AC92: 46001 | AD92: =NETWORKDAYS.INTL(Tab_4.DISP_INEX[[#This Row],[DATA RECEBIDO]],Tab_4.DISP_INEX[[#This Row],[DATA FINALIZADO]],1,Lista!$U$3:$U$15) -> 40 | AJ92: https://www.telebras.com.br/wp-content/uploads/2025/12/33.TLB-CTR-2025.00103-CENTRO-BRASILEIRO-DE-PESQUISA-EM-AVALIACAO-E-SELECAO-E-DE-PROMOCAO-DE-EVENTOS-CEBRASPE.pdf | AK92: - | AL92: - | AM92: - | AP92: 87 | AQ92: =_xlfn.CONCAT(AP92,"_","TR","_",Tab_4.DISP_INEX[[#This Row],[FORNECEDOR]]) -> 87_TR_CENTRO BRASILEIRO DE PESQUISA EM AVALIAÇÃO E SELEÇÃO E DE PROMOÇÃO DE EVENTOS (CEBRASPE) | AR92: =_xlfn.CONCAT(AP92,"_","JUST","_",Tab_4.DISP_INEX[[#This Row],[FORNECEDOR]]) -> 87_JUST_CENTRO BRASILEIRO DE PESQUISA EM AVALIAÇÃO E SELEÇÃO E DE PROMOÇÃO DE EVENTOS (CEBRASPE) | AS92: =_xlfn.CONCAT(AP92,"_","RAT","_",Tab_4.DISP_INEX[[#This Row],[FORNECEDOR]]) -> 87_RAT_CENTRO BRASILEIRO DE PESQUISA EM AVALIAÇÃO E SELEÇÃO E DE PROMOÇÃO DE EVENTOS (CEBRASPE)
B93: 45960 | C93: MARCUS VINÍCIUS | D93: FINALIZADO | E93: FINALIZADO | F93: TLB-PRO-2025/04504 | G93: 2000-DAFRI | H93: GLOG | I93: Compras | J93: Aquisição de peças e partes para recuperação de sistema de ar condicionado do Datacenter da sede da Telebras | K93: Dispensa | L93: ADMINISTRATIVO | M93: G2 AR CONDICIONADO LTDA | N93: 38.708.432/0001-24 | O93: Ordem de Compra | P93: - | Q93: TLB-ORC-2026/00002 | R93: TLB-ORC-2026/00002 | S93: 46036 | T93: 46036 | U93: 46053 | V93: 4188.1 | W93: TLB-DEG-2026/00031 | X93: THALES SETSUO YOSHIDA | Y93: PÚBLICO | AC93: 46003 | AD93: =NETWORKDAYS.INTL(Tab_4.DISP_INEX[[#This Row],[DATA RECEBIDO]],Tab_4.DISP_INEX[[#This Row],[DATA FINALIZADO]],1,Lista!$U$3:$U$15) -> 32 | AG93: 925150 - 5/2026 | AH93: SIM | AI93: SIM | AJ93: https://www.telebras.com.br/wp-content/uploads/2026/03/2.TLB-ORC-202600002-G2-AR-CONDICIONADO-LTDA-Tipo-do-objeto-Compras.pdf | AK93: https://www.telebras.com.br/wp-content/uploads/2026/06/88_TR_G2-AR-CONDICIONADO-LTDA.pdf | AL93: https://www.telebras.com.br/wp-content/uploads/2026/06/88_JUST_G2-AR-CONDICIONADO-LTDA.pdf | AM93: https://www.telebras.com.br/wp-content/uploads/2026/06/88_APR_G2-AR-CONDICIONADO-LTDA.pdf | AP93: 88 | AQ93: =_xlfn.CONCAT(AP93,"_","TR","_",Tab_4.DISP_INEX[[#This Row],[FORNECEDOR]]) -> 88_TR_G2 AR CONDICIONADO LTDA | AR93: =_xlfn.CONCAT(AP93,"_","JUST","_",Tab_4.DISP_INEX[[#This Row],[FORNECEDOR]]) -> 88_JUST_G2 AR CONDICIONADO LTDA | AS93: =_xlfn.CONCAT(AP93,"_","RAT","_",Tab_4.DISP_INEX[[#This Row],[FORNECEDOR]]) -> 88_RAT_G2 AR CONDICIONADO LTDA
B94: 45982 | C94: MARCUS VINÍCIUS | D94: FINALIZADO | E94: FINALIZADO | F94: TLB-PRO-2025/05445 | G94: 2000-DAFRI | H94: GLOG | I94: Serviços | J94: Contratação direta da Empresa Brasileira de Correios e Telégrafos - ECT, mediante adesão a Termo de Condições Comerciais, vinculado a Pacote de Serviços dos CORREIOS denominado Platinum. | K94: Inexigibilidade | L94: ADMINISTRATIVO | M94: Empresa Brasileira de Correios e Telégrafos | N94: 34.028.316/0001-03 | O94: Contrato de Adesão | P94: - | Q94: TLB-AUT-2026/00688 | R94: TLB-AUT-2026/00688 | S94: 46038 | T94: 46038 | U94: 47864 | V94: 1200000 | W94: TLB-DEG-2026/00033 | X94: NILTON CESAR SOARES DA SILVA LIRA | Y94: PÚBLICO | Z94: 4400003301 | AD94: =NETWORKDAYS.INTL(Tab_4.DISP_INEX[[#This Row],[DATA RECEBIDO]],Tab_4.DISP_INEX[[#This Row],[DATA FINALIZADO]],1,Lista!$U$3:$U$15) -> -32836 | AG94: 925150 - 6/2026 | AH94: SIM | AI94: SIM | AJ94: https://www.telebras.com.br/wp-content/uploads/2026/03/3.TLB-AUT-202600688-Empresa-Brasileira-de-Correios-e-Telegrafos-Tipo-do-objeto-Servicos.pdf | AK94: https://www.telebras.com.br/wp-content/uploads/2026/06/89_RAT_Empresa-Brasileira-de-Correios-e-Telegrafos.pdf | AL94: https://www.telebras.com.br/wp-content/uploads/2026/06/89_JUST_Empresa-Brasileira-de-Correios-e-Telegrafos.pdf | AM94: https://www.telebras.com.br/wp-content/uploads/2026/06/89_RAT_Empresa-Brasileira-de-Correios-e-Telegrafos.pdf | AP94: 89 | AQ94: =_xlfn.CONCAT(AP94,"_","TR","_",Tab_4.DISP_INEX[[#This Row],[FORNECEDOR]]) -> 89_TR_Empresa Brasileira de Correios e Telégrafos | AR94: =_xlfn.CONCAT(AP94,"_","JUST","_",Tab_4.DISP_INEX[[#This Row],[FORNECEDOR]]) -> 89_JUST_Empresa Brasileira de Correios e Telégrafos | AS94: =_xlfn.CONCAT(AP94,"_","RAT","_",Tab_4.DISP_INEX[[#This Row],[FORNECEDOR]]) -> 89_RAT_Empresa Brasileira de Correios e Telégrafos
B95: 45982 | C95: MARCUS VINÍCIUS | D95: FINALIZADO | E95: FINALIZADO | F95: TLB-PRO-2025/06493 | G95: 2000-DAFRI | H95: GGP | I95: Serviços | J95: Contratação emergencial de empresa especializada na prestação de serviços de saúde do trabalho, visando à execução do Programa de Controle Médico de Saúde Ocupacional (PCMSO) e demais atividades correlatas, em atendimento à SEDE e COPE-P (DF), COPE-S (RJ) e Escritório Regional de Belém (PA). | K95: Dispensa | L95: ADMINISTRATIVO | M95: MPV - SERVIÇOS DE CLÍNICA MÉDICA, CARDIOLOGIA E CIRURGIA GERAL LTD | N95: 15.471.958/0001-38 | O95: Contrato | P95: - | Q95: TLB-CTR-2025/00115 | R95: TLB-AUT-2025/23446 | S95: 46010 | T95: 46010 | U95: 46190 | V95: 213535.56 | W95: TLB-DEG-2026/00002 | X95: SARAH LIMA MOREIRA MOURA | Y95: PÚBLICO | AD95: =NETWORKDAYS.INTL(Tab_4.DISP_INEX[[#This Row],[DATA RECEBIDO]],Tab_4.DISP_INEX[[#This Row],[DATA FINALIZADO]],1,Lista!$U$3:$U$15) -> -32836 | AJ95: https://www.telebras.com.br/wp-content/uploads/2026/01/41.TLB-CTR-2025.00115-MPV-SERVICOS-DE-CLINICA-MEDICA-CARDIOLOGIA-E-CIRURGIA-GERAL-LTDA.pdf | AK95: - | AL95: - | AM95: - | AP95: 90 | AQ95: =_xlfn.CONCAT(AP95,"_","TR","_",Tab_4.DISP_INEX[[#This Row],[FORNECEDOR]]) -> 90_TR_MPV - SERVIÇOS DE CLÍNICA MÉDICA, CARDIOLOGIA E CIRURGIA GERAL LTD | AR95: =_xlfn.CONCAT(AP95,"_","JUST","_",Tab_4.DISP_INEX[[#This Row],[FORNECEDOR]]) -> 90_JUST_MPV - SERVIÇOS DE CLÍNICA MÉDICA, CARDIOLOGIA E CIRURGIA GERAL LTD | AS95: =_xlfn.CONCAT(AP95,"_","RAT","_",Tab_4.DISP_INEX[[#This Row],[FORNECEDOR]]) -> 90_RAT_MPV - SERVIÇOS DE CLÍNICA MÉDICA, CARDIOLOGIA E CIRURGIA GERAL LTD
B96: 46044 | C96: ROBERTA | D96: FINALIZADO | E96: FINALIZADO | F96: TLB-PRO-2026/00317 | G96: 2000-DAFRI | H96: GGP | I96: Serviços | J96: Contratação de empresa para a realização de palestra sobre Educação Financeira, cujo título apresentado pela prestadora do serviço seja: " Recalculando a Rota" | K96: Inexigibilidade | L96: ADMINISTRATIVO | M96: TOSTAO FURADO LTDA | N96: 42.460.333/0001-43 | O96: Ordem de Compra | P96: - | Q96: TLB-ORC-2026/00003 | R96: TLB-ORC-2026/00003 | S96: 46048 | T96: 46048 | U96: 46048 | V96: 2650 | W96: TLB-DEG-2026/00041 | X96: Elisa Macêdo e Silva | Y96: PÚBLICO | Z96: 10016598 | AC96: 46049 | AD96: =NETWORKDAYS.INTL(Tab_4.DISP_INEX[[#This Row],[DATA RECEBIDO]],Tab_4.DISP_INEX[[#This Row],[DATA FINALIZADO]],1,Lista!$U$3:$U$15) -> 4 | AG96: 925150 - 7/2026 | AH96: SIM | AI96: SIM | AJ96: https://www.telebras.com.br/wp-content/uploads/2026/03/4.TLB-ORC-202600003-TOSTAO-FURADO-LTDA-Tipo-do-objeto-Servicos.pdf | AK96: - | AL96: - | AM96: - | AP96: 91 | AQ96: =_xlfn.CONCAT(AP96,"_","TR","_",Tab_4.DISP_INEX[[#This Row],[FORNECEDOR]]) -> 91_TR_TOSTAO FURADO LTDA | AR96: =_xlfn.CONCAT(AP96,"_","JUST","_",Tab_4.DISP_INEX[[#This Row],[FORNECEDOR]]) -> 91_JUST_TOSTAO FURADO LTDA | AS96: =_xlfn.CONCAT(AP96,"_","RAT","_",Tab_4.DISP_INEX[[#This Row],[FORNECEDOR]]) -> 91_RAT_TOSTAO FURADO LTDA
B97: 45988 | C97: MARCUS VINÍCIUS | D97: FINALIZADO | E97: CANCELADO | F97: TLB-PRO-2025/05074 | G97: 1000-PRES | H97: GPR - ASCOM | I97: Serviços | J97: Contratação de empresa especializada para fornecimento de serviços de assinatura de veículos jornalísticos em formato digital para atender a Assessoria de Comunicação da Telebras | K97: Dispensa | L97: ADMINISTRATIVO | P97: - | AD97: =NETWORKDAYS.INTL(Tab_4.DISP_INEX[[#This Row],[DATA RECEBIDO]],Tab_4.DISP_INEX[[#This Row],[DATA FINALIZADO]],1,Lista!$U$3:$U$15) -> -32840 | AJ97: - | AK97: - | AL97: - | AM97: - | AP97: 92 | AQ97: =_xlfn.CONCAT(AP97,"_","TR","_",Tab_4.DISP_INEX[[#This Row],[FORNECEDOR]]) -> 92_TR_ | AR97: =_xlfn.CONCAT(AP97,"_","JUST","_",Tab_4.DISP_INEX[[#This Row],[FORNECEDOR]]) -> 92_JUST_ | AS97: =_xlfn.CONCAT(AP97,"_","RAT","_",Tab_4.DISP_INEX[[#This Row],[FORNECEDOR]]) -> 92_RAT_
B98: 46044 | C98: ROBERTA | D98: FINALIZADO | E98: FINALIZADO | F98: TLB-PRO-2025/07216 | G98: 2000-DAFRI | H98: GGP | I98: Serviços | J98: Contratação de empresa para inscrição de até 40 funcionários/as da Telebras, no curso Reforma Tributária. | K98: Inexigibilidade | L98: ADMINISTRATIVO | M98: IBMEC EDUCACIONAL LTDA | N98: 04.298.309/0013-02 | O98: Ordem de Compra | P98: - | Q98: TLB-ORC-2026/00006 | R98: TLB-ORC-2026/00006 | S98: 46057 | T98: 46057 | U98: 46057 | V98: 29900 | W98: TLB-DEG-2026/00047 | X98: Elisa Macêdo e Silva | Y98: PÚBLICO | Z98: 10016135 | AA98: 10003967 | AC98: 46057 | AD98: =NETWORKDAYS.INTL(Tab_4.DISP_INEX[[#This Row],[DATA RECEBIDO]],Tab_4.DISP_INEX[[#This Row],[DATA FINALIZADO]],1,Lista!$U$3:$U$15) -> 10 | AG98: 925150 - 8/2026 | AH98: SIM | AI98: SIM | AJ98: https://www.telebras.com.br/wp-content/uploads/2026/03/5.TLB-ORC-202600006-Ibmec-Educacional-Ltda-Tipo-do-objeto-Servicos.pdf | AK98: https://www.telebras.com.br/wp-content/uploads/2026/06/93_TR_IBMEC-EDUCACIONAL-LTDA.pdf | AL98: https://www.telebras.com.br/wp-content/uploads/2026/06/93_JUST_IBMEC-EDUCACIONAL-LTDA.pdf | AM98: https://www.telebras.com.br/wp-content/uploads/2026/06/93_RAT_IBMEC-EDUCACIONAL-LTDA.pdf | AP98: 93 | AQ98: =_xlfn.CONCAT(AP98,"_","TR","_",Tab_4.DISP_INEX[[#This Row],[FORNECEDOR]]) -> 93_TR_IBMEC EDUCACIONAL LTDA | AR98: =_xlfn.CONCAT(AP98,"_","JUST","_",Tab_4.DISP_INEX[[#This Row],[FORNECEDOR]]) -> 93_JUST_IBMEC EDUCACIONAL LTDA | AS98: =_xlfn.CONCAT(AP98,"_","RAT","_",Tab_4.DISP_INEX[[#This Row],[FORNECEDOR]]) -> 93_RAT_IBMEC EDUCACIONAL LTDA
B99: 46048 | C99: ROBERTA | D99: FINALIZADO | E99: FINALIZADO | F99: TLB-PRO-2026/00378 | G99: 2000-DAFRI | H99: GGP | I99: Serviços | J99: Contratação da participação na capacitação AUDI 2 EOP | K99: Inexigibilidade | L99: ADMINISTRATIVO | M99: INSTITUTO DOS AUDITORES INTERNOS DO BRASIL | N99: 62.070.115/0001-00 | O99: Ordem de Compra | P99: - | Q99: TLB-ORC-2026/00004 | R99: TLB-ORC-2026/00004 | S99: 46049 | T99: 46049 | U99: 46049 | V99: 5550 | W99: TLB-DEG-2026/00045 | X99: Adryana Ramos De Oliveira | Y99: PÚBLICO | Z99: 10016645 | AA99: 10004111 | AC99: 46049 | AD99: =NETWORKDAYS.INTL(Tab_4.DISP_INEX[[#This Row],[DATA RECEBIDO]],Tab_4.DISP_INEX[[#This Row],[DATA FINALIZADO]],1,Lista!$U$3:$U$15) -> 2 | AG99: 925150 - 9/2026 | AH99: SIM | AI99: SIM | AJ99: https://www.telebras.com.br/wp-content/uploads/2026/03/6.TLB-ORC-202600004-Instituto-dos-Auditores-Internos-do-Brasil-Tipo-do-objeto-Servicos.pdf | AK99: https://www.telebras.com.br/wp-content/uploads/2026/06/94_TR_INSTITUTO-DOS-AUDITORES-INTERNOS-DO-BRASIL.pdf | AL99: https://www.telebras.com.br/wp-content/uploads/2026/06/94_JUST_INSTITUTO-DOS-AUDITORES-INTERNOS-DO-BRASIL.pdf | AM99: https://www.telebras.com.br/wp-content/uploads/2026/06/94_RAT_INSTITUTO-DOS-AUDITORES-INTERNOS-DO-BRASIL.pdf | AP99: 94 | AQ99: =_xlfn.CONCAT(AP99,"_","TR","_",Tab_4.DISP_INEX[[#This Row],[FORNECEDOR]]) -> 94_TR_INSTITUTO DOS AUDITORES INTERNOS DO BRASIL | AR99: =_xlfn.CONCAT(AP99,"_","JUST","_",Tab_4.DISP_INEX[[#This Row],[FORNECEDOR]]) -> 94_JUST_INSTITUTO DOS AUDITORES INTERNOS DO BRASIL | AS99: =_xlfn.CONCAT(AP99,"_","RAT","_",Tab_4.DISP_INEX[[#This Row],[FORNECEDOR]]) -> 94_RAT_INSTITUTO DOS AUDITORES INTERNOS DO BRASIL
B100: 46057 | C100: FRANCIELE | D100: FINALIZADO | E100: FINALIZADO | F100: TLB-PRO-2026/00436 | G100: 2000-DAFRI | H100: GGP | I100: Serviços | J100: Contratação da inscrição de 4 empregados(as) da Telebras, no curso ISO 31000:2018 - Capacitação em Gestão de Riscos. | K100: Inexigibilidade | L100: ADMINISTRATIVO | M100: QSP - Centro da Qualidade, Segurança e Produtividade para o Brasil e América Latina | N100: 67.634.022/0001-84 | O100: Ordem de Compra | P100: - | Q100: TLB-ORC-2026/00007 | R100: TLB-ORC-2026/00007 | S100: 46059 | T100: 46059 | U100: 46059 | V100: 11172 | W100: TLB-DEG-2026/00048 | X100: Elisa Macêdo e Silva | Y100: PÚBLICO | Z100: 10016660 | AA100: 10004257 | AC100: 46059 | AD100: =NETWORKDAYS.INTL(Tab_4.DISP_INEX[[#This Row],[DATA RECEBIDO]],Tab_4.DISP_INEX[[#This Row],[DATA FINALIZADO]],1,Lista!$U$3:$U$15) -> 3 | AG100: 925150 - 10/2026 | AH100: SIM | AI100: SIM | AJ100: https://www.telebras.com.br/wp-content/uploads/2026/03/7.TLB-ORC-202600007-QSP-Centro-da-Qualidade-Seguranca-e-Produtividade-para-o-Brasil-e-America-Latina-Tipo-do-objeto-Servicos.pdf | AK100: https://www.telebras.com.br/wp-content/uploads/2026/06/95_TR_-QSP-Centro-da-Qualidade-Seguranca-e-Produtividade-para-o-Brasil-e-America-Latina.pdf | AL100: https://www.telebras.com.br/wp-content/uploads/2026/06/95_JUST_-QSP-Centro-da-Qualidade-Seguranca-e-Produtividade-para-o-Brasil-e-America-Latina.pdf | AM100: https://www.telebras.com.br/wp-content/uploads/2026/06/95_RAT_-QSP-Centro-da-Qualidade-Seguranca-e-Produtividade-para-o-Brasil-e-America-Latina.pdf | AP100: 95 | AQ100: =_xlfn.CONCAT(AP100,"_","TR","_",Tab_4.DISP_INEX[[#This Row],[FORNECEDOR]]) -> 95_TR_ QSP - Centro da Qualidade, Segurança e Produtividade para o Brasil e América Latina | AR100: =_xlfn.CONCAT(AP100,"_","JUST","_",Tab_4.DISP_INEX[[#This Row],[FORNECEDOR]]) -> 95_JUST_ QSP - Centro da Qualidade, Segurança e Produtividade para o Brasil e América Latina | AS100: =_xlfn.CONCAT(AP100,"_","RAT","_",Tab_4.DISP_INEX[[#This Row],[FORNECEDOR]]) -> 95_RAT_ QSP - Centro da Qualidade, Segurança e Produtividade para o Brasil e América Latina
B101: 46058 | C101: FRANCIELE | D101: FINALIZADO | E101: FINALIZADO | F101: TLB-PRO-2026/00475 | G101: 2000-DAFRI | H101: GGP | I101: Serviços | J101: Contratação da capacitação “e-Social e EFD-Reinf com Foco na DCTFWeb para Órgãos Públicos” | K101: Inexigibilidade | L101: ADMINISTRATIVO | M101: SUPREME CAPACITAÇÃO E TREINAMENTO LTDA | N101: 34.370.234/0001-42 | O101: Ordem de Compra | P101: - | Q101: TLB-ORC-2026/00008 | R101: TLB-ORC-2026/00008 | S101: 46062 | T101: 46062 | U101: 46062 | V101: 4740 | W101: TLB-DEG-2026/00051 | X101: Elisa Macêdo e Silva | Y101: PÚBLICO | Z101: 10016667 | AA101: 10004411 | AC101: 46066 | AD101: =NETWORKDAYS.INTL(Tab_4.DISP_INEX[[#This Row],[DATA RECEBIDO]],Tab_4.DISP_INEX[[#This Row],[DATA FINALIZADO]],1,Lista!$U$3:$U$15) -> 7 | AG101: 925150 - 11/2026 | AH101: SIM | AI101: SIM | AJ101: https://www.telebras.com.br/wp-content/uploads/2026/03/8.-TLB-ORC-202600008-SUPREME-CAPACITACAO-E-TREINAMENTO-LTDA-Tipo-do-objeto-Servicos.pdf | AK101: https://www.telebras.com.br/wp-content/uploads/2026/06/96_TR_-SUPREME-CAPACITACAO-E-TREINAMENTO-LTDA.pdf | AL101: https://www.telebras.com.br/wp-content/uploads/2026/06/96_RAT_-SUPREME-CAPACITACAO-E-TREINAMENTO-LTDA.pdf | AM101: https://www.telebras.com.br/wp-content/uploads/2026/06/96_JUST_-SUPREME-CAPACITACAO-E-TREINAMENTO-LTDA.pdf | AP101: 96 | AQ101: =_xlfn.CONCAT(AP101,"_","TR","_",Tab_4.DISP_INEX[[#This Row],[FORNECEDOR]]) -> 96_TR_ SUPREME CAPACITAÇÃO E TREINAMENTO LTDA | AR101: =_xlfn.CONCAT(AP101,"_","JUST","_",Tab_4.DISP_INEX[[#This Row],[FORNECEDOR]]) -> 96_JUST_ SUPREME CAPACITAÇÃO E TREINAMENTO LTDA | AS101: =_xlfn.CONCAT(AP101,"_","RAT","_",Tab_4.DISP_INEX[[#This Row],[FORNECEDOR]]) -> 96_RAT_ SUPREME CAPACITAÇÃO E TREINAMENTO LTDA
B102: 46062 | C102: ROBERTA | D102: FINALIZADO | E102: FINALIZADO | F102: TLB-PRO-2026/00657 | G102: 2000-DAFRI | H102: GGP | I102: Serviços | J102: Contratação da participação na capacitação AUDI TI. | K102: Inexigibilidade | L102: ADMINISTRATIVO | M102: INSTITUTO DOS AUDITORES INTERNOS DO BRASIL | N102: 62.070.115/0001-00 | O102: Ordem de Compra | P102: - | Q102: TLB-ORC-2026/00011 | R102: TLB-ORC-2026/00011 | S102: 46071 | T102: 46071 | U102: 46071 | V102: 5000 | W102: TLB-DEG-2026/00056 | X102: Elisa Macêdo e Silva | Y102: PÚBLICO | Z102: 10016714 | AA102: 10004111 | AC102: 46071 | AD102: =NETWORKDAYS.INTL(Tab_4.DISP_INEX[[#This Row],[DATA RECEBIDO]],Tab_4.DISP_INEX[[#This Row],[DATA FINALIZADO]],1,Lista!$U$3:$U$15) -> 8 | AG102: 925150 - 12/2026 | AH102: SIM | AI102: SIM | AJ102: https://www.telebras.com.br/wp-content/uploads/2026/03/9.-TLB-ORC-202600011-Instituto-dos-Auditores-Internos-do-Brasil-Tipo-do-objeto-Servicos.pdf | AK102: https://www.telebras.com.br/wp-content/uploads/2026/06/97_TR_INSTITUTO-DOS-AUDITORES-INTERNOS-DO-BRASIL.pdf | AL102: https://www.telebras.com.br/wp-content/uploads/2026/06/97_JUST_INSTITUTO-DOS-AUDITORES-INTERNOS-DO-BRASIL.pdf | AM102: https://www.telebras.com.br/wp-content/uploads/2026/06/97_RAT_INSTITUTO-DOS-AUDITORES-INTERNOS-DO-BRASIL.pdf | AP102: 97 | AQ102: =_xlfn.CONCAT(AP102,"_","TR","_",Tab_4.DISP_INEX[[#This Row],[FORNECEDOR]]) -> 97_TR_INSTITUTO DOS AUDITORES INTERNOS DO BRASIL | AR102: =_xlfn.CONCAT(AP102,"_","JUST","_",Tab_4.DISP_INEX[[#This Row],[FORNECEDOR]]) -> 97_JUST_INSTITUTO DOS AUDITORES INTERNOS DO BRASIL | AS102: =_xlfn.CONCAT(AP102,"_","RAT","_",Tab_4.DISP_INEX[[#This Row],[FORNECEDOR]]) -> 97_RAT_INSTITUTO DOS AUDITORES INTERNOS DO BRASIL
...

Sheet ÍNDICES GGE
B3: Rótulos de Linha | C3: Soma de DIAS ÚTEIS
B4: 45727 | C4: 2
B5: 45734 | C5: 376
B6: 45742 | C6: 1
B7: 45743 | C7: 766
B8: 45744 | C8: 62
B9: 45751 | C9: 1
B10: 45761 | C10: 3
B11: 45762 | C11: 6
B12: 45763 | C12: 314
B13: 45764 | C13: 307
B14: 45786 | C14: 1
B15: 45800 | C15: 1
... B27: 45922 | C27: 5
B28: Total Geral | C28: 1871

Sheet Relatório de Gestão GCC
B2: DATA ASSINATURA | C2: (Vários itens)
B3: TIPO DO CONTRATO | C3: (Vários itens) | D3: os contratos (CTRs) já estão inclusos na planilha 14
B5: Rótulos de Linha | C5: Soma de VALOR CONTRATO | D5: Contagem de VALOR CONTRATO
B6: Inexigibilidade | C6: 499552.28 | D6: 0.89655172
B7: Dispensa | C7: 23685 | D7: 0.10344828
B8: Total Geral | C8: 523237.28 | D8: 1

Sheet RAG 1
A3: Nº PROCESSO SIGA | B3: MODALIDADE | C3: FORNECEDOR | D3: OBJETO | E3: INÍCIO VIGÊNCIA | F3: FINAL VIGÊNCIA | G3: Soma de VALOR CONTRATO
A4: TLB-PRO-2024/05271 | B4: Inexigibilidade | C4: DELL COMPUTADORES DO BRASIL LTDA | D4: Contratação de empresa especializada para fornecimento de suporte e garantia de servidores Dell. | E4: 45743 | F4: 45947 | G4: 53604
A5: TLB-PRO-2024/05944 | B5: Dispensa | C5: LEGIS JET LTDA | D5: Contratação de empresa especializada na prestação de serviços de informações e pesquisa no âmbito fiscal, trabalhista, previdenciário, contábil, auditoria e societário. | E5: 45748 | F5: 46843 | G5: 29500
A6: TLB-PRO-2024/06004 | B6: Inexigibilidade | C6: Instituto Brasileiro de Governança Corporativa - IBGC | D6: Associação da Telebras ao Instituto Brasileiro de Governança Corporativa - IBGC | E6: 45734 | F6: 46099 | G6: 23474
A7: TLB-PRO-2024/06558 | B7: Inexigibilidade | C7: DELL COMPUTADORES DO BRASIL LTDA | D7: Contratação de empresa especializada para fornecimento de suporte e garantia de switches Dell. | E7: 45743 | F7: 46407 | G7: 122605
A8: TLB-PRO-2025/00933 | B8: Inexigibilidade | C8: Zênite Informação e Consultoria S/A | D8: Contratação da Capacitação - Inteligência Artificial Apliacada às Contratações Públicas | E8: 45729 | F8: 45744 | G8: 4860
A9: TLB-PRO-2025/01070 | B9: Inexigibilidade | C9: Inove Treinamentos e Capacitação Ltda | D9: Contratação da Capacitação - Pesquisa de Preços para Contratações Públicas com o uso de Inteligência Artificial | E9: 45743 | F9: 45743 | G9: 1990
A10: TLB-PRO-2025/01408 | B10: Inexigibilidade | C10: Zênite Informação e Consultoria S/A | D10: Contratação de assinatura anual dos produtos de suporte jurídico à administração referente às contratações públicas: Zênite Fácil - Estatais e Zênite Fácil Inteligência Artificial - ZIÁ, que é a assistente de pesquisa do Zênite Fácil - Estatais que utiliza IA generativa. | E10: 45751 | F10: 46116 | G10: 15546
A11: TLB-PRO-2025/01643 | B11: Inexigibilidade | C11: ABRINT | D11: Participação da Telebras, por meio de ação promocional, no Evento Abrint Global Congress 2025, organizado exclusivamente pela Abrint - Associação Brasileira de Provedores de Internet. O evento ocorrerá no Anhembi, em São Paulo, de 07 a 09 de maio de 2025. | E11: 45764 | F11: 45786 | G11: 180470.65
A12: TLB-PRO-2024/06151 | B12: Dispensa | C12: SC BRASIL GROUP SOLUÇÕES TECNOLÓGICAS LTDA | D12: Aquisição de impressora de cartão PVC/crachá para a Telebras. | E12: 45744 | F12: 46109 | G12: 6500
A13: TLB-PRO-2024/06219 | B13: Inexigibilidade | C13: KPMG Business School |Treinamentos Corporativos | D13: Treinamento - Environmental, Social & Governance (ESG) | E13: 45762 | F13: 45762 | G13: 5860
A14: TLB-PRO-2025/01806 | B14: Inexigibilidade | C14: MODERNPMO GESTAO E TECNOLOGIA LTDA GESTAO E TECNOLOGIA LTDA | D14: Curso Preparatório PMP | E14: 45762 | F14: 45762 | G14: 2247
A15: TLB-PRO-2025/01053 | B15: Inexigibilidade | C15: A. F. Comércio de Livros e Cursos Especializados Ltda | D15: Capacitação interna - Modelagem Financeira | E15: 45763 | F15: 45763 | G15: 7180.8
... A32: TLB-PRO-2025/05423 | B32: Inexigibilidade | C32: Instituto dos Auditores Internos do Brasil | D32: Contratação de empresa para a inscrição de 01 colaboradora da AUD curso AUDI 2 EOP, com a respectiva associaçãos. | E32: 45947 | F32: 45947 | G32: 2775

Sheet Din_Pub_OC_PNCP_2026
B1: UASG | C1: 925150 | E1: CATMAT/CATSER | F1: 21172 | I1: 70610-440
B2: PUBLICAÇÃO DA CONTRATAÇÃO - DISPENSAS E INEXIGIBILIDADE NO PNCP 2026 | I2: FERNANDA | J2: 967.144.251-04 | K2: fernanda.elias@telebras.com.br | N2: 21172 | O2: Treinamento qualificação profissional
B3: Telebras não utiliza o sistema PGC (Não SISG). | I3: TATIANA | J3: 510.391.332-15 | K3: tatiana.miranda@telebras.com.br
B4: Sistema de gestão documental SIGA-DOC com acesso restrito para usuários
B5: DATA RECEBIDO | C5: DATA ASSINATURA | D5: Nº PROCESSO SIGA | E5: Nº CONTRATO | F5: TIPO DO CONTRATO | G5: FORNECEDOR | H5: CNPJ/CPF | I5: OBJETO | J5: TIPO DO OBJETO | K5: MODALIDADE | L5: INÍCIO VIGÊNCIA | M5: FINAL VIGÊNCIA | N5: Compra divulgada no PNCP | O5: Publicação do Contrato PNCP | P5: Nº DA LICITAÇÃO | Q5: VALOR CONTRATO

Sheet Din_Pub_OC_SITE_2026
C4: Retire o campo Contrato | G4: Atualizar
B5: Nº PROCESSO SIGA | C5: TIPO DO CONTRATO | D5: MODALIDADE | E5: INÍCIO VIGÊNCIA | F5: FINAL VIGÊNCIA | G5: TIPO DO OBJETO | H5: OBJETO | I5: FORNECEDOR | J5: Soma de VALOR CONTRATO
B6: TLB-PRO-2025/04066 | C6: Contrato de Adesão | D6: Inexigibilidade | E6: 46036 | F6: 46401 | G6: Serviços | H6: Contratação de serviços especializados em consultas às bases do Cadastro de Pessoa Física - CPF e Cadastro Nacional de Pessoa Jurídica - CNPJ | I6: SERPRO - SERVIÇO FEDERAL DE PROCESSAMENTO DE DADOS | J6: 6353.64
B7: TLB-PRO-2025/04504 | C7: Ordem de Compra | D7: Dispensa | E7: 46036 | F7: 46053 | G7: Compras | H7: Aquisição de peças e partes para recuperação de sistema de ar condicionado do Datacenter da sede da Telebras | I7: G2 AR CONDICIONADO LTDA | J7: 4188.1
B8: TLB-PRO-2025/05445 | C8: Contrato de Adesão | D8: Inexigibilidade | E8: 46038 | F8: 47864 | G8: Serviços | H8: Contratação direta da Empresa Brasileira de Correios e Telégrafos - ECT, mediante adesão a Termo de Condições Comerciais, vinculado a Pacote de Serviços dos CORREIOS denominado Platinum. | I8: Empresa Brasileira de Correios e Telégrafos | J8: 1200000
B9: TLB-PRO-2026/00317 | C9: Ordem de Compra | D9: Inexigibilidade | E9: 46048 | F9: 46048 | G9: Serviços | H9: Contratação de empresa para a realização de palestra sobre Educação Financeira, cujo título apresentado pela prestadora do serviço seja: " Recalculando a Rota" | I9: TOSTAO FURADO LTDA | J9: 2650
B10: TLB-PRO-2025/07216 | C10: Ordem de Compra | D10: Inexigibilidade | E10: 46057 | F10: 46057 | G10: Serviços | H10: Contratação de empresa para inscrição de até 40 funcionários/as da Telebras, no curso Reforma Tributária. | I10: Ibmec Educacional Ltda | J10: 29900
B11: TLB-PRO-2026/00378 | C11: Ordem de Compra | D11: Inexigibilidade | E11: 46049 | F11: 46049 | G11: Serviços | H11: Contratação da participação na capacitação AUDI 2 EOP | I11: Instituto dos Auditores Internos do Brasil | J11: 5550
B12: TLB-PRO-2026/00436 | C12: Ordem de Compra | D12: Inexigibilidade | E12: 46059 | F12: 46059 | G12: Serviços | H12: Contratação da inscrição de 4 empregados(as) da Telebras, no curso ISO 31000:2018 - Capacitação em Gestão de Riscos. | I12: QSP - Centro da Qualidade, Segurança e Produtividade para o Brasil e América Latina | J12: 11172
B13: TLB-PRO-2026/00475 | C13: Ordem de Compra | D13: Inexigibilidade | E13: 46062 | F13: 46062 | G13: Serviços | H13: Contratação da capacitação “e-Social e EFD-Reinf com Foco na DCTFWeb para Órgãos Públicos” | I13: SUPREME CAPACITAÇÃO E TREINAMENTO LTDA | J13: 4740
B14: TLB-PRO-2026/00657 | C14: Ordem de Compra | D14: Inexigibilidade | E14: 46071 | F14: 46071 | G14: Serviços | H14: Contratação da participação na capacitação AUDI TI. | I14: Instituto dos Auditores Internos do Brasil | J14: 5000
B15: TLB-PRO-2026/00580 | C15: Ordem de Compra | D15: Inexigibilidade | E15: 46071 | F15: 46071 | G15: Serviços | H15: Contratação da capacitação - NR 05 CIPA - Comissão Interna de Prevenção a Acidentes - Grau de Risco 2 | I15: BIOSEG BRASILIA SOLUCOES EM SEGURANCA E MEDICINA DO TRABALHO LTDA | J15: 3450
B16: TLB-PRO-2026/00447 | C16: Ordem de Compra | D16: Inexigibilidade | E16: 46071 | F16: 46071 | G16: Serviços | H16: Contratação da capacitação - NR 01 - Treinamento de Integração de Segurança 1 | I16: BIOSEG BRASILIA SOLUCOES EM SEGURANCA E MEDICINA DO TRABALHO LTDA | J16: 999.5
B17: TLB-PRO-2026/01002 | C17: Ordem de Compra | D17: Inexigibilidade | E17: 46076 | F17: 46076 | G17: Serviços | H17: Contratação da participação no seminário políticas de comunicações. | I17: SAVE PRODUÇÕES EDITORIAIS LTDA | J17: 10500
... B19: TLB-PRO-2026/01444 | C19: Ordem de Compra | D19: Inexigibilidade | E19: 46093 | F19: 46093 | G19: Serviços | H19: Contratação da participação do presidente da Telebras no evento Satellite GovMilSpace. | I19: Access Intelligence, LLC | J19: 7388.3
A21: x
A33: x

Sheet TAB_PUB_OC_site 2026
B3: ORDENS DE COMPRAS 2026
B5: Nº PROCESSO | C5: TIPO DO CONTRATO | D5: Nº CONTRATO | E5: FISCAL | F5: MODALID. LICITAÇÃO | G5: INÍCIO DA VIGÊNCIA | H5: FIM DA VIGÊNCIA | I5: Tipo do Objeto | J5: OBJETO | K5: FORNECEDOR | L5: VALOR DO CONTRATO | M5: Para renomear cada arquivo:
A6: 1 | B6: TLB-PRO-2025/04066 | C6: Contrato de Adesão | D6: TLB-AUT-2026/00714 | E6: DALVA HELENA ROSA FERREIRA | F6: Inexigibilidade | G6: 46036 | H6: 46401 | I6: Serviços | J6: Contratação de serviços especializados em consultas às bases do Cadastro de Pessoa Física - CPF e Cadastro Nacional de Pessoa Jurídica - CNPJ | K6: SERPRO - SERVIÇO FEDERAL DE PROCESSAMENTO DE DADOS | L6: 6353.64 | M6: =CONCATENATE(A6,".",D6,," ","-"," ",K6," ", "(","Tipo do objeto: ",Tabela1524[[#This Row],[Tipo do Objeto]],")") -> 1.TLB-AUT-2026/00714 - SERPRO - SERVIÇO FEDERAL DE PROCESSAMENTO DE DADOS (Tipo do objeto: Serviços)
A7: 2 | B7: TLB-PRO-2025/04504 | C7: Ordem de Compra | D7: TLB-ORC-2026/00002 | E7: THALES SETSUO YOSHIDA | F7: Dispensa | G7: 46036 | H7: 46053 | I7: Compras | J7: Aquisição de peças e partes para recuperação de sistema de ar condicionado do Datacenter da sede da Telebras | K7: G2 AR CONDICIONADO LTDA | L7: 4188.1 | M7: =CONCATENATE(A7,".",D7,," ","-"," ",K7," ", "(","Tipo do objeto: ",Tabela1524[[#This Row],[Tipo do Objeto]],")") -> 2.TLB-ORC-2026/00002 - G2 AR CONDICIONADO LTDA (Tipo do objeto: Compras)
A8: 3 | B8: TLB-PRO-2025/05445 | C8: Contrato de Adesão | D8: TLB-AUT-2026/00688 | E8: NILTON CESAR SOARES DA SILVA LIRA | F8: Dispensa | G8: 46038 | H8: 47864 | I8: Serviços | J8: Contratação direta da Empresa Brasileira de Correios e Telégrafos - ECT, mediante adesão a Termo de Condições Comerciais, vinculado a Pacote de Serviços dos CORREIOS denominado Platinum. | K8: Empresa Brasileira de Correios e Telégrafos | L8: 1200000 | M8: =CONCATENATE(A8,".",D8,," ","-"," ",K8," ", "(","Tipo do objeto: ",Tabela1524[[#This Row],[Tipo do Objeto]],")") -> 3.TLB-AUT-2026/00688 - Empresa Brasileira de Correios e Telégrafos (Tipo do objeto: Serviços)
A9: 4 | B9: TLB-PRO-2026/00317 | C9: Ordem de Compra | D9: TLB-ORC-2026/00003 | E9: Elisa Macêdo e Silva | F9: Inexigibilidade | G9: 46048 | H9: 46048 | I9: Serviços | J9: Contratação de empresa para a realização de palestra sobre Educação Financeira, cujo título apresentado pela prestadora do serviço seja: " Recalculando a Rota" | K9: TOSTAO FURADO LTDA | L9: 2650 | M9: =CONCATENATE(A9,".",D9,," ","-"," ",K9," ", "(","Tipo do objeto: ",Tabela1524[[#This Row],[Tipo do Objeto]],")") -> 4.TLB-ORC-2026/00003 - TOSTAO FURADO LTDA (Tipo do objeto: Serviços)
A10: 5 | B10: TLB-PRO-2025/07216 | C10: Ordem de Compra | D10: TLB-ORC-2026/00006 | E10: Elisa Macêdo e Silva | F10: Inexigibilidade | G10: 46057 | H10: 46057 | I10: Serviços | J10: Contratação de empresa para inscrição de até 40 funcionários/as da Telebras, no curso Reforma Tributária. | K10: Ibmec Educacional Ltda | L10: 29900 | M10: =CONCATENATE(A10,".",D10,," ","-"," ",K10," ", "(","Tipo do objeto: ",Tabela1524[[#This Row],[Tipo do Objeto]],")") -> 5.TLB-ORC-2026/00006 - Ibmec Educacional Ltda (Tipo do objeto: Serviços)
A11: 6 | B11: TLB-PRO-2026/00378 | C11: Ordem de Compra | D11: TLB-ORC-2026/00004 | E11: ADRYANA RAMOS DE OLIVEIRA | F11: Inexigibilidade | G11: 46049 | H11: 46049 | I11: Serviços | J11: Contratação da participação na capacitação AUDI 2 EOP | K11: Instituto dos Auditores Internos do Brasil | L11: 5550 | M11: =CONCATENATE(A11,".",D11,," ","-"," ",K11," ", "(","Tipo do objeto: ",Tabela1524[[#This Row],[Tipo do Objeto]],")") -> 6.TLB-ORC-2026/00004 - Instituto dos Auditores Internos do Brasil (Tipo do objeto: Serviços)
A12: 7 | B12: TLB-PRO-2026/00436 | C12: Ordem de Compra | D12: TLB-ORC-2026/00007 | E12: Elisa Macêdo e Silva | F12: Inexigibilidade | G12: 46059 | H12: 46059 | I12: Serviços | J12: Contratação da inscrição de 4 empregados(as) da Telebras, no curso ISO 31000:2018 - Capacitação em Gestão de Riscos. | K12: QSP - Centro da Qualidade, Segurança e Produtividade para o Brasil e América Latina | L12: 11172 | M12: =CONCATENATE(A12,".",D12,," ","-"," ",K12," ", "(","Tipo do objeto: ",Tabela1524[[#This Row],[Tipo do Objeto]],")") -> 7.TLB-ORC-2026/00007 - QSP - Centro da Qualidade, Segurança e Produtividade para o Brasil e América Latina (Tipo do objeto: Serviços)
A13: 8 | B13: TLB-PRO-2026/00475 | C13: Ordem de Compra | D13: TLB-ORC-2026/00008 | E13: Elisa Macêdo e Silva | F13: Inexigibilidade | G13: 46062 | H13: 46062 | I13: Serviços | J13: Contratação da capacitação “e-Social e EFD-Reinf com Foco na DCTFWeb para Órgãos Públicos” | K13: SUPREME CAPACITAÇÃO E TREINAMENTO LTDA | L13: 4740 | M13: =CONCATENATE(A13,".",D13,," ","-"," ",K13," ", "(","Tipo do objeto: ",Tabela1524[[#This Row],[Tipo do Objeto]],")") -> 8. TLB-ORC-2026/00008 - SUPREME CAPACITAÇÃO E TREINAMENTO LTDA (Tipo do objeto: Serviços)
A14: 9 | B14: TLB-PRO-2026/00657 | C14: Ordem de Compra | D14: TLB-ORC-2026/00011 | E14: Elisa Macêdo e Silva | F14: Inexigibilidade | G14: 46071 | H14: 46071 | I14: Serviços | J14: Contratação da participação na capacitação AUDI TI. | K14: Instituto dos Auditores Internos do Brasil | L14: 5000 | M14: =CONCATENATE(A14,".",D14,," ","-"," ",K14," ", "(","Tipo do objeto: ",Tabela1524[[#This Row],[Tipo do Objeto]],")") -> 9. TLB-ORC-2026/00011 - Instituto dos Auditores Internos do Brasil (Tipo do objeto: Serviços)
A15: 10 | B15: TLB-PRO-2026/00580 | C15: Ordem de Compra | D15: TLB-ORC-2026/00010 | E15: Elisa Macêdo e Silva | F15: Inexigibilidade | G15: 46071 | H15: 46071 | I15: Serviços | J15: Contratação da capacitação - NR 05 CIPA - Comissão Interna de Prevenção a Acidentes - Grau de Risco 2 | K15: BIOSEG BRASILIA SOLUCOES EM SEGURANCA E MEDICINA DO TRABALHO LTDA | L15: 3450 | M15: =CONCATENATE(A15,".",D15,," ","-"," ",K15," ", "(","Tipo do objeto: ",Tabela1524[[#This Row],[Tipo do Objeto]],")") -> 10.TLB-ORC-2026/00010 - BIOSEG BRASILIA SOLUCOES EM SEGURANCA E MEDICINA DO TRABALHO LTDA (Tipo do objeto: Serviços)
A16: 11 | B16: TLB-PRO-2026/00447 | C16: Ordem de Compra | D16: TLB-ORC-2026/00012 | E16: Elisa Macêdo e Silva | F16: Inexigibilidade | G16: 46071 | H16: 46071 | I16: Serviços | J16: Contratação da capacitação - NR 01 - Treinamento de Integração de Segurança 1 | K16: BIOSEG BRASILIA SOLUCOES EM SEGURANCA E MEDICINA DO TRABALHO LTDA | L16: 999.5 | M16: =CONCATENATE(A16,".",D16,," ","-"," ",K16," ", "(","Tipo do objeto: ",Tabela1524[[#This Row],[Tipo do Objeto]],")") -> 11. TLB-ORC-2026/00012 - BIOSEG BRASILIA SOLUCOES EM SEGURANCA E MEDICINA DO TRABALHO LTDA (Tipo do objeto: Serviços)
A17: 12 | B17: TLB-PRO-2026/01002 | C17: Ordem de Compra | D17: TLB-ORC-2026/00015 | E17: Elisa Macêdo e Silva | F17: Inexigibilidade | G17: 46076 | H17: 46076 | I17: Serviços | J17: Contratação da participação no seminário políticas de comunicações. | K17: SAVE PRODUÇÕES EDITORIAIS LTDA | L17: 10500 | M17: =CONCATENATE(A17,".",D17,," ","-"," ",K17," ", "(","Tipo do objeto: ",Tabela1524[[#This Row],[Tipo do Objeto]],")") -> 12.TLB-ORC-2026/00015 - SAVE PRODUÇÕES EDITORIAIS LTDA (Tipo do objeto: Serviços)
A18: 13 | B18: TLB-PRO-2026/00961 | C18: Ordem de Compra | D18: TLB-ORC-2026/00016 | E18: Elisa Macêdo e Silva | F18: Inexigibilidade | G18: 46093 | H18: 46093 | I18: Serviços | J18: Contratação da participação do presidente da Telebras no evento Satellite GovMilSpace. | K18: Access Intelligence, LLC | L18: 7388.3 | M18: =CONCATENATE(A18,".",D18,," ","-"," ",K18," ", "(","Tipo do objeto: ",Tabela1524[[#This Row],[Tipo do Objeto]],")") -> 13.TLB-ORC-2026/00016 - Access Intelligence, LLC (Tipo do objeto: Serviços)
B19: Total | D19: =SUBTOTAL(103,Tabela1524[Nº CONTRATO]) -> 13 | L19: =SUBTOTAL(109,Tabela1524[VALOR DO CONTRATO]) -> 1291891.5

Sheet Pub__NE 2025
B3: NOTAS DE EMPENHOS 2025
B5: Nº PROCESSO | C5: TIPO DO CONTRATO | D5: Nº CONTRATO | E5: FISCAL | F5: MODALID. LICITAÇÃO | G5: INÍCIO DA VIGÊNCIA | H5: FIM DA VIGÊNCIA | I5: Tipo do Objeto | J5: OBJETO | K5: FORNECEDOR | L5: VALOR DO CONTRATO
A6: 1 | B6: TLB-PRO-2024/06004 | C6: Nota de Empenho | D6: 2025NE000538 | E6: ANTÔNIO CELSON DE JESUS NERIS | F6: INEXIGIBILIDADE | G6: 45734 | H6: 46099 | I6: Serviços | J6: Associação da Telebras ao Instituto Brasileiro de Governança Corporativa - IBGC | K6: Instituto Brasileiro de Governança Corporativa - IBGC | L6: 23474 | M6: =CONCATENATE(A6,".",D6,," ","-"," ",K6," ", "(","Tipo do objeto: ",Tabela152[[#This Row],[Tipo do Objeto]],")") -> 1.2025NE000538 - Instituto Brasileiro de Governança Corporativa - IBGC (Tipo do objeto: Serviços)
A7: 2 | B7: TLB-PRO-2025/00933 | C7: Nota de Empenho | D7: 2025NE000539 | E7: ROSILDA ABREU DA SILVA | F7: INEXIGIBILIDADE | G7: 45729 | H7: 45744 | I7: Serviços | J7: Contratação da Capacitação - Inteligência Artificial Apliacada às Contratações Públicas | K7: Zênite Informação e Consultoria S/A | L7: 4860 | M7: =CONCATENATE(A7,".",D7,," ","-"," ",K7," ", "(","Tipo do objeto: ",Tabela152[[#This Row],[Tipo do Objeto]],")") -> 2.2025NE000539 - Zênite Informação e Consultoria S/A (Tipo do objeto: Serviços)
A8: 3 | B8: TLB-PRO-2025/01070 | C8: Nota de Empenho | D8: 2025NE000572 | E8: FRANCIELE FERREIRA DA SILVA | F8: INEXIGIBILIDADE | G8: 45743 | H8: 45743 | I8: Serviços | J8: Contratação da Capacitação - Pesquisa de Preços para Contratações Públicas com o uso de Inteligência Artificial | K8: Inove Treinamentos e Capacitação Ltda | L8: 1990 | M8: =CONCATENATE(A8,".",D8,," ","-"," ",K8," ", "(","Tipo do objeto: ",Tabela152[[#This Row],[Tipo do Objeto]],")") -> 3.2025NE000572 - Inove Treinamentos e Capacitação Ltda (Tipo do objeto: Serviços)
A9: 4 | B9: TLB-PRO-2025/01408 | C9: Nota de Empenho | D9: 2025NE000588 | E9: ROSILDA ABREU DA SILVA | F9: INEXIGIBILIDADE | G9: 45751 | H9: 46116 | I9: Serviços | J9: Contratação de assinatura anual dos produtos de suporte jurídico à administração referente às contratações públicas: Zênite Fácil - Estatais e Zênite Fácil Inteligência Artificial - ZIÁ, que é a assistente de pesquisa do Zênite Fácil - Estatais que utiliza IA generativa. | K9: Zênite Informação e Consultoria S/A | L9: 15546 | M9: =CONCATENATE(A9,".",D9,," ","-"," ",K9," ", "(","Tipo do objeto: ",Tabela152[[#This Row],[Tipo do Objeto]],")") -> 4.2025NE000588 - Zênite Informação e Consultoria S/A (Tipo do objeto: Serviços)
A10: 5 | B10: TLB-PRO-2025/01643 | C10: Contrato de Adesão | D10: TA nº 04720000_2025NE000613 | E10: MARIANA RODRIGUES BOAVISTA LEITE | F10: INEXIGIBILIDADE | G10: 45764 | H10: 45786 | I10: Serviços | J10: Participação da Telebras, por meio de ação promocional, no Evento Abrint Global Congress 2025, organizado exclusivamente pela Abrint - Associação Brasileira de Provedores de Internet. O evento ocorrerá no Anhembi, em São Paulo, de 07 a 09 de maio de 2025. | K10: ABRINT | L10: 180470.65 | M10: =CONCATENATE(A10,".",D10,," ","-"," ",K10," ", "(","Tipo do objeto: ",Tabela152[[#This Row],[Tipo do Objeto]],")") -> 5.TA nº 04720000_2025NE000613 - ABRINT (Tipo do objeto: Serviços)
A11: 6 | B11: TLB-PRO-2024/06219 | C11: Nota de Empenho | D11: 2025NE000608 | E11: Camila Daniela Lima | F11: INEXIGIBILIDADE | G11: 45762 | H11: 45762 | I11: Serviços | J11: Treinamento - Environmental, Social & Governance (ESG) | K11: KPMG Business School |Treinamentos Corporativos | L11: 5860 | M11: =CONCATENATE(A11,".",D11,," ","-"," ",K11," ", "(","Tipo do objeto: ",Tabela152[[#This Row],[Tipo do Objeto]],")") -> 6.2025NE000608 - KPMG Business School |Treinamentos Corporativos (Tipo do objeto: Serviços)
A12: 7 | B12: TLB-PRO-2025/01806 | C12: Nota de Empenho | D12: 2025NE000607 | E12: Camila Daniela Lima | F12: INEXIGIBILIDADE | G12: 45762 | H12: 45762 | I12: Serviços | J12: Curso Preparatório PMP | K12: MODERNPMO GESTAO E TECNOLOGIA LTDA GESTAO E TECNOLOGIA LTDA | L12: 2247 | M12: =CONCATENATE(A12,".",D12,," ","-"," ",K12," ", "(","Tipo do objeto: ",Tabela152[[#This Row],[Tipo do Objeto]],")") -> 7.2025NE000607 - MODERNPMO GESTAO E TECNOLOGIA LTDA GESTAO E TECNOLOGIA LTDA (Tipo do objeto: Serviços)
A13: 8 | B13: TLB-PRO-2025/01053 | C13: Nota de Empenho | D13: 2025NE000610 | E13: Camila Daniela Lima | F13: INEXIGIBILIDADE | G13: 45763 | H13: 45763 | I13: Serviços | J13: Capacitação interna - Modelagem Financeira | K13: FK PARTNERS | L13: 7180.8 | M13: =CONCATENATE(A13,".",D13,," ","-"," ",K13," ", "(","Tipo do objeto: ",Tabela152[[#This Row],[Tipo do Objeto]],")") -> 8.2025NE000610 - FK PARTNERS (Tipo do objeto: Serviços)
A14: 9 | B14: TLB-PRO-2025/01052 | C14: Nota de Empenho | D14: 2025NE000690 | E14: Camila Daniela Lima | F14: INEXIGIBILIDADE | G14: 45786 | H14: 45786 | I14: Serviços | J14: Capacitação "Análise de Viabilidade de Projetos". | K14: A. F. Comércio de Livros e Cursos Especializados Ltda | L14: 19000 | M14: =CONCATENATE(A14,".",D14,," ","-"," ",K14," ", "(","Tipo do objeto: ",Tabela152[[#This Row],[Tipo do Objeto]],")") -> 9.2025NE000690 - A. F. Comércio de Livros e Cursos Especializados Ltda (Tipo do objeto: Serviços)
A15: 10 | B15: TLB-PRO-2025/02256 | C15: Nota de Empenho | D15: 2025NE000716 | E15: ROSILDA ABREU DA SILVA | F15: INEXIGIBILIDADE | G15: 45800 | H15: 45800 | I15: Serviços | J15: Contratação da Capacitação - Programa de Imersão: Gestão Estratégica por Resultados em Licitações e Contratos | K15: 3R CAPACITA COMERCIO DE MATERIAIS DIDATICOS E SERVICOS EDUCACIONAIS LTDA | L15: 8250 | M15: =CONCATENATE(A15,".",D15,," ","-"," ",K15," ", "(","Tipo do objeto: ",Tabela152[[#This Row],[Tipo do Objeto]],")") -> 10.2025NE000716 - 3R CAPACITA COMERCIO DE MATERIAIS DIDATICOS E SERVICOS EDUCACIONAIS LTDA (Tipo do objeto: Serviços)
A16: 11 | B16: TLB-PRO-2025/02561 | C16: Nota de Empenho | D16: 2025NE761 | E16: ADRYANA RAMOS DE OLIVEIRA | F16: INEXIGIBILIDADE | G16: 45813 | H16: 46022 | I16: Serviços | J16: Contratação da Capacitação ISO 31000:2018 - Capacitação em Gestão de Riscos. | K16: QSP - CENTRO DA QUALIDADE, SEGURANCA E PRODUTIVIDADE PARA O BRASIL E AMERICA LATINA | L16: 10545 | M16: =CONCATENATE(A16,".",D16,," ","-"," ",K16," ", "(","Tipo do objeto: ",Tabela152[[#This Row],[Tipo do Objeto]],")") -> 11.2025NE761 - QSP - CENTRO DA QUALIDADE, SEGURANCA E PRODUTIVIDADE PARA O BRASIL E AMERICA LATINA (Tipo do objeto: Serviços)
A17: 12 | B17: TLB-PRO-2025/02662 | C17: Nota de Empenho | D17: 2025NE774 | E17: ADRYANA RAMOS DE OLIVEIRA | F17: INEXIGIBILIDADE | G17: 45817 | H17: 46022 | I17: Serviços | J17: Participação da GGP no CONARH 2025- Congresso Nacional de Gestão de Pessoas. | K17: ABRH- Associação Brasileira de Recursos Humanos | L17: 14700 | M17: =CONCATENATE(A17,".",D17,," ","-"," ",K17," ", "(","Tipo do objeto: ",Tabela152[[#This Row],[Tipo do Objeto]],")") -> 12.2025NE774 - ABRH- Associação Brasileira de Recursos Humanos (Tipo do objeto: Serviços)
... A34: 29 | B34: TLB-PRO-2025/02898 | C34: Nota de Empenho | D34: 2025NE000855 | E34: SERGIO PINHO PIRETTI | F34: Dispensa | G34: 45845 | H34: 46022 | I34: Compras | J34: Aquisição de bebedouros para atender as necessidades da sede da Telebras no COPE-P | K34: M & J REFRIGERACAO LTDA | L34: 3245 | M34: =CONCATENATE(A34,".",D34,," ","-"," ",K34," ", "(","Tipo do objeto: ",Tabela152[[#This Row],[Tipo do Objeto]],")") -> 29.2025NE000855 - M & J REFRIGERACAO LTDA (Tipo do objeto: Compras)
B35: Total | D35: =SUBTOTAL(103,Tabela152[Nº CONTRATO]) -> 29 | L35: =SUBTOTAL(109,Tabela152[VALOR DO CONTRATO]) -> 523237.28

Sheet Lista
C2: STATUS | E2: ETAPAS - INEXIGIBILIDADE | G2: MODALIDADE DE LICITAÇÃO | I2: SIGILO | K2: STATUS GESTÃO | M2: TIPO DO OBJETO | O2: NATUEZA DO OBJETO | Q2: RESPONSÁVEL | S2: DIRETORIA | U2: FERIADOS 2024 | X2: NATUREZA DO CONTRATO | Z2: RESPONSÁVEL GESTÃO | AB2: TIPO DO OBJETO
C3: EM ANDAMENTO | E3: 1. ANÁLISE DA INSTRUÇÃO PROCESSUAL | G3: Inexigibilidade | I3: SIGILOSO | K3: VIGENTE | M3: Cessão | O3: Serviço | Q3: LUCIANA | S3: 1000-PRES | U3: 45292 | V3: segunda-feira | X3: ADMINISTRATIVO | Z3: PEDRO LAGOS | AB3: Cessão
C4: FINALIZADO | E4: 2. PESQUISA DE MERCADO | G4: Dispensa | I4: PÚBLICO | K4: VENCIDO | M4: Compras | O4: Material | Q4: LAYLLAH | S4: 2000-DAFRI | U4: 45334 | V4: segunda-feira | X4: LOCAÇÃO | Z4: DANIEL PENALVA | AB4: Compras
E5: 3. PREVISÃO ORÇAMENTÁRIA | M5: Informática (TIC) | O5: Bens | Q5: ROSILDA | S5: 3000-DTO | U5: 45335 | V5: terça-feira | X5: COMPARTILHAMENTO | Z5: LUCIANA | AB5: Informática (TIC)
E6: 4. ANÁLISE JURÍDICA/SANEAMENTO DO PROCESSO | M6: Locação de Imóveis | O6: Bens e serviços | Q6: FRANCIELE | S6: 4000-DC | U6: 45380 | V6: sexta-feira | X6: ENERGIA | Z6: LAYLLAH | AB6: Obras e Serviço de Engenharia
E7: 5. TERMO DE APROVAÇÃO/TERMO DE RATIFICAÇÃO | M7: Mão de Obra | Q7: ROBERTA | S7: 5000-DG | U7: 45403 | V7: domingo | X7: AFASTAMENTO | Z7: ROSILDA | AB7: Locação de Imóveis
E8: 5. SANEADOR/LISTA DE VERIFICAÇÃO | M8: Obras | Q8: MARCUS VINICIUS | U8: 45413 | V8: quarta-feira | Z8: FRANCIELE | AB8: Mão de Obra
E9: 6. PUBLICAÇÃO DO EXTRATO DA INEXIGIBILIDADE/DISPENSA NO DOU | M9: Serviços | U9: 45442 | V9: quinta-feira | Z9: N/A | AB9: Obras
E10: 7. DIF/IVA/AJUSTE RC/DOCS SIGNATÁRIOS/CERTIDÕES | M10: Obras e Serviços de Engenharia | U10: 45542 | V10: sábado | AB10: Serviços
E11: 8. ASSINATURA DO CONTRATO/PUBLICAÇÃO NO DOU | U11: 45577 | V11: sábado
E12: FINALIZADO | U12: 45598 | V12: sábado
E13: CANCELADO | U13: 45611 | V13: sexta-feira
E14: SUSPENSO | U14: 45616 | V14: quarta-feira
E15: SOBRESTADO | U15: 45651 | V15: quarta-feira
G16: TIPO DO CONTRATO
G17: Contrato
G18: Nota de Empenho
G19: Contrato de Adesão
G20: Termo de Adesão
G21: Contrato de SWAP
G22: Concessão
G23: Ordem de Compra
